Workbook

Sheet 【1月】月間進捗管理シート
A1: 縞谷 | B1: 計画値 | D1: 現状 | E1: 土 | F1: 第1週 | G1: 月 | H1: 火 | I1: 水 | J1: 木 | K1: 金 | L1: 土 | M1: 第2週 | N1: 月 | O1: 火 | P1: 水 | Q1: 木 | R1: 金 | S1: 土 | T1: 第3週 | U1: 月 | V1: 火 | W1: 水 | X1: 木 | Y1: 金
E2: 45668 | F2: 45669 | G2: 45670 | H2: 45671 | I2: 45672 | J2: 45673 | K2: 45674 | L2: 45675 | M2: 45676 | N2: 45677 | O2: 45678 | P2: 45679 | Q2: 45680 | R2: 45681 | S2: 45682 | T2: 45683 | U2: 45684 | V2: 45685 | W2: 45686 | X2: 45687 | Y2: 45688
A3: 売上目標 | B3: 1000000 | C3: 現状売上 | D3: =sum(E3)+sum(G3:L3)+sum(N3:S3)+SUM(U3:Y3) -> 275000 | L3: 275000
A4: 目標受注数 | B4: 5 | C4: 現状受注数 | D4: =sum(E4)+sum(G4:L4)+sum(N4:S4)+SUM(U4:Y4) -> 1 | L4: 1
A5: 目標有効商談数 | B5: =B4/B11 -> 25 | C5: 現状有効商談数 | D5: =sum(E5)+sum(G5:L5)+sum(N5:S5)+SUM(U5:Y5) -> 5 | G5: 1 | H5: 1 | I5: 1 | L5: 1 | O5: 1
A6: 目標無効商談数 | C6: 現状無効商談数 | D6: =sum(E6)+sum(G6:L6)+sum(N6:S6)+SUM(U6:Y6) -> 0
C7: 商談予定 | D7: =sum(E7)+sum(G7:L7)+sum(N7:S7)+SUM(U7:Y7) -> 5 | G7: 1 | H7: 1 | I7: 1 | L7: 1 | O7: 1
C8: 当日アポ目標 | D8: =sum(E8)+sum(G8:L8)+sum(N8:S8)+SUM(U8:Y8) -> 0
A9: 目標アポ数 | B9: =B5/B12 -> 31.25 | C9: 現状アポ数 | D9: =sum(E9)+sum(G9:L9)+sum(N9:S9)+SUM(U9:Y9) -> 7 | E9: 1 | G9: 1 | H9: 0 | I9: 0 | J9: 1 | K9: 2 | L9: 1 | N9: 0 | O9: 1
A10: 目標コール数 | B10: =B9/B14 -> 1562.5 | C10: 現状コール数 | D10: =sum(E10)+sum(G10:L10)+sum(N10:S10)+SUM(U10:Y10) -> 537 | E10: 45 | G10: 43 | H10: 95 | I10: 57 | J10: 50 | K10: 30 | L10: 66 | N10: 73 | O10: 78
A11: 目標受注率 | B11: 0.2 | C11: 現状受注率 | D11: =D4/sum(D5:D6) -> 0.2
A12: 目標出席率 | B12: 0.8 | C12: 現状出席率 | D12: =sum(D5:D6)/D7 -> 1
A13: 目標商談転換率 | C13: 現状商談転換率 | D13: =SUM(D5:D6)/D9 -> 0.71428571
A14: 目標アポ転換率 | B14: 0.02 | C14: 現状アポ転換率 | D14: =D9/D10 -> 0.013035382
A16: 前川 | B16: 計画値 | D16: 現状 | E16: 土 | F16: 第1週 | G16: 月 | H16: 火 | I16: 水 | J16: 木 | K16: 金 | L16: 土 | M16: 第2週 | N16: 月 | O16: 火 | P16: 水 | Q16: 木 | R16: 金 | S16: 土 | T16: 第3週 | U16: 月 | V16: 火 | W16: 水 | X16: 木 | Y16: 金
E17: 45668 | F17: 45669 | G17: 45670 | H17: 45671 | I17: 45672 | J17: 45673 | K17: 45674 | L17: 45675 | M17: 45676 | N17: 45677 | O17: 45678 | P17: 45679 | Q17: 45680 | R17: 45681 | S17: 45682 | T17: 45683 | U17: 45684 | V17: 45685 | W17: 45686 | X17: 45687 | Y17: 45688
A18: 売上目標 | B18: 2640000 | C18: 現状売上 | D18: =sum(E18)+sum(G18:L18)+sum(N18:S18)+SUM(U18:Y18) -> 0
A19: 目標受注数 | B19: 12 | C19: 現状受注数 | D19: =sum(E19)+sum(G19:L19)+sum(N19:S19)+SUM(U19:Y19) -> 0
A20: 目標有効商談数 | B20: 40 | C20: 現状有効商談数 | D20: =sum(E20)+sum(G20:L20)+sum(N20:S20)+SUM(U20:Y20) -> 0
A21: 目標無効商談数 | C21: 現状無効商談数 | D21: =sum(E21)+sum(G21:L21)+sum(N21:S21)+SUM(U21:Y21) -> 0
C22: 当日アポ目標 | D22: =sum(E22)+sum(G22:L22)+sum(N22:S22)+SUM(U22:Y22) -> 0
C23: 商談予定 | D23: =sum(E23)+sum(G23:L23)+sum(N23:S23)+SUM(U23:Y23) -> 0
A24: 目標アポ数 | B24: 44 | C24: 現状アポ数 | D24: =sum(E24)+sum(G24:L24)+sum(N24:S24)+SUM(U24:Y24) -> 2 | E24: 0 | G24: 2 | I24: 0 | L24: 0
A25: 目標コール数 | B25: 2200 | C25: 現状コール数 | D25: =sum(E25)+sum(G25:L25)+sum(N25:S25)+SUM(U25:Y25) -> 150 | E25: 27 | G25: 26 | L25: 97
A26: 目標受注率 | B26: =B19/B20 -> 0.3 | C26: 現状受注率 | D26: =D19/sum(D20:D21) -> #DIV/0!
A27: 目標出席率 | B27: =B20/B24 -> 0.90909091 | C27: 現状出席率 | D27: =sum(D20:D21)/D23 -> #DIV/0!
A28: 目標商談転換率 | C28: 現状商談転換率 | D28: =SUM(D20:D21)/D24 -> 0
A29: 目標アポ転換率 | B29: =B24/B25 -> 0.02 | C29: 現状アポ転換率 | D29: =D24/D25 -> 0.013333333

Sheet 【2月】月間進捗管理シート
A1: 縞谷 | B1: 計画値 | D1: 現状 | E1: 土 | F1: 第1週 | G1: 月 | H1: 火 | I1: 水 | J1: 木 | K1: 金 | L1: 土 | M1: 第2週 | N1: 月 | O1: 火 | P1: 水 | Q1: 木 | R1: 金 | S1: 土 | T1: 第3週 | U1: 月 | V1: 火 | W1: 水 | X1: 木 | Y1: 金 | Z1: 土 | AA1: 日 | AB1: 月 | AC1: 火 | AD1: 水 | AE1: 木 | AF1: 金
E2: 45689 | F2: 45690 | G2: 45691 | H2: 45692 | I2: 45693 | J2: 45694 | K2: 45695 | L2: 45696 | M2: 45697 | N2: 45698 | O2: 45699 | P2: 45700 | Q2: 45701 | R2: 45702 | S2: 45703 | T2: 45704 | U2: 45705 | V2: 45706 | W2: 45707 | X2: 45708 | Y2: 45709 | Z2: 45710 | AA2: 45711 | AB2: 45712 | AC2: 45713 | AD2: 45714 | AE2: 45715 | AF2: 45716
A3: 売上目標 | B3: 1800000 | C3: 現状売上 | D3: =sum(E3)+sum(G3:L3)+sum(N3:S3)+SUM(U3:Y3) -> 0
A4: 目標受注数 | B4: 12 | C4: 現状受注数 | D4: =sum(E4)+sum(G4:L4)+sum(N4:S4)+SUM(U4:Y4) -> 0
A5: 目標有効商談数 | B5: =B4/B11 -> 40 | C5: 現状有効商談数 | D5: =sum(E5)+sum(G5:L5)+sum(N5:S5)+SUM(U5:Y5) -> 0
A6: 目標無効商談数 | C6: 現状無効商談数 | D6: =sum(E6)+sum(G6:L6)+sum(N6:S6)+SUM(U6:Y6) -> 0
C7: 商談予定 | D7: =sum(E7)+sum(G7:L7)+sum(N7:S7)+SUM(U7:Y7) -> 0
C8: 当日アポ目標 | D8: =sum(E8)+sum(G8:L8)+sum(N8:S8)+SUM(U8:Y8) -> 0
A9: 目標アポ数 | B9: =B5/B12 -> 47.058824 | C9: 現状アポ数 | D9: =sum(E9)+sum(G9:L9)+sum(N9:S9)+SUM(U9:Y9) -> 0
A10: 目標コール数 | B10: =B9/B14 -> 2352.9412 | C10: 現状コール数 | D10: =sum(E10)+sum(G10:L10)+sum(N10:S10)+SUM(U10:Y10) -> 0
A11: 目標受注率 | B11: 0.3 | C11: 現状受注率 | D11: =D4/sum(D5:D6) -> #DIV/0!
A12: 目標出席率 | B12: 0.85 | C12: 現状出席率 | D12: =sum(D5:D6)/D7 -> #DIV/0!
C13: 現状商談転換率 | D13: =SUM(D5:D6)/D9 -> #DIV/0!
A14: 目標アポ転換率 | B14: 0.02 | C14: 現状アポ転換率 | D14: =D9/D10 -> #DIV/0!
A16: 前川 | B16: 計画値 | D16: 現状 | E16: 土 | F16: 第1週 | G16: 月 | H16: 火 | I16: 水 | J16: 木 | K16: 金 | L16: 土 | M16: 第2週 | N16: 月 | O16: 火 | P16: 水 | Q16: 木 | R16: 金 | S16: 土 | T16: 第3週 | U16: 月 | V16: 火 | W16: 水 | X16: 木 | Y16: 金 | Z16: 土 | AA16: 日 | AB16: 月 | AC16: 火 | AD16: 水 | AE16: 木 | AF16: 金
E17: 45689 | F17: 45690 | G17: 45691 | H17: 45692 | I17: 45693 | J17: 45694 | K17: 45695 | L17: 45696 | M17: 45697 | N17: 45698 | O17: 45699 | P17: 45700 | Q17: 45701 | R17: 45702 | S17: 45703 | T17: 45704 | U17: 45705 | V17: 45706 | W17: 45707 | X17: 45708 | Y17: 45709 | Z17: 45710 | AA17: 45711 | AB17: 45712 | AC17: 45713 | AD17: 45714 | AE17: 45715 | AF17: 45716
A18: 売上目標 | C18: 現状売上 | D18: =sum(E18)+sum(G18:L18)+sum(N18:S18)+SUM(U18:Y18) -> 0
A19: 目標受注数 | C19: 現状受注数 | D19: =sum(E19)+sum(G19:L19)+sum(N19:S19)+SUM(U19:Y19) -> 0
A20: 目標有効商談数 | C20: 現状有効商談数 | D20: =sum(E20)+sum(G20:L20)+sum(N20:S20)+SUM(U20:Y20) -> 0
A21: 目標無効商談数 | C21: 現状無効商談数 | D21: =sum(E21)+sum(G21:L21)+sum(N21:S21)+SUM(U21:Y21) -> 0
C22: 当日アポ目標 | D22: =sum(E22)+sum(G22:L22)+sum(N22:S22)+SUM(U22:Y22) -> 0
C23: 商談予定 | D23: =sum(E23)+sum(G23:L23)+sum(N23:S23)+SUM(U23:Y23) -> 0
A24: 目標アポ数 | C24: 現状アポ数 | D24: =sum(E24)+sum(G24:L24)+sum(N24:S24)+SUM(U24:Y24) -> 0
A25: 目標コール数 | C25: 現状コール数 | D25: =sum(E25)+sum(G25:L25)+sum(N25:S25)+SUM(U25:Y25) -> 0
A26: 目標受注率 | C26: 現状受注率 | D26: =D19/sum(D20:D21) -> #DIV/0!
A27: 目標出席率 | C27: 現状出席率 | D27: =sum(D20:D21)/D23 -> #DIV/0!
C28: 現状商談転換率 | D28: =SUM(D20:D21)/D24 -> #DIV/0!
A29: 目標アポ転換率 | C29: 現状アポ転換率 | D29: =D24/D25 -> #DIV/0!

Sheet 【4月】月間進捗管理シート
A1: 全体 | B1: 計画値 | D1: 現状 | E1: 火 | F1: 水 | G1: 木 | H1: 金 | I1: 土 | J1: 日 | K1: 月 | L1: 火 | M1: 水 | N1: 木 | O1: 金 | P1: 土 | Q1: 日 | R1: 月 | S1: 火 | T1: 水 | U1: 木 | V1: 金 | W1: 土 | X1: 日 | Y1: 月 | Z1: 火 | AA1: 水 | AB1: 木 | AC1: 金 | AD1: 土 | AE1: 日 | AF1: 月 | AG1: 火 | AH1: 水
E2: 45748 | F2: 45749 | G2: 45750 | H2: 45751 | I2: 45752 | J2: 45753 | K2: 45754 | L2: 45755 | M2: 45756 | N2: 45757 | O2: 45758 | P2: 45759 | Q2: 45760 | R2: 45761 | S2: 45762 | T2: 45763 | U2: 45764 | V2: 45765 | W2: 45766 | X2: 45767 | Y2: 45768 | Z2: 45769 | AA2: 45770 | AB2: 45771 | AC2: 45772 | AD2: 45773 | AE2: 45774 | AF2: 45775 | AG2: 45776 | AH2: 45777
A3: 売上目標 | B3: 2800000 | C3: 現状売上 | D3: =I3+Q3+X3+AE3+AI3 -> #VALUE! | E3: =E18+E33 -> 0 | F3: =F18+F33 -> 0 | G3: =G18+G33 -> 0 | H3: =H18+H33 -> 0 | I3: =sum(E3:H3) -> 0 | K3: =K18+K33 -> 0 | L3: =L18+L33 -> 0 | M3: =M18+M33 -> #VALUE! | N3: =N18+N33 -> #VALUE! | O3: =O18+O33 -> 0 | P3: =P18+P33 -> 0 | Q3: =sum(K3:P3) -> #VALUE! | R3: =R18+R33 -> 235000 | S3: =S18+S33 -> #VALUE! | T3: =T18+T33 -> #VALUE! | U3: =U18+U33 -> #VALUE! | V3: =V18+V33 -> 180000 | W3: =W18+W33 -> 0 | X3: =sum(R3:W3) -> #VALUE! | Y3: =Y18+Y33 -> 0 | Z3: =Z18+Z33 -> 0 | AA3: =AA18+AA33 -> 470000 | AB3: =AB18+AB33 -> 0 | AC3: =AC18+AC33 -> 0 | AD3: =AD18+AD33 -> 0 | AE3: =sum(Y3:AD3) -> 470000 | AF3: =AF18+AF33 -> #VALUE! | AG3: =AG18+AG33 -> #VALUE! | AH3: =AH18+AH33 -> #VALUE! | AI3: =sum(AF3:AH3) -> #VALUE!
A4: 目標受注数 | B4: 14 | C4: 現状受注数 | D4: =I4+Q4+X4+AE4+AI4 -> 6 | E4: =E19+E34 -> 0 | F4: =F19+F34 -> 0 | G4: =G19+G34 -> 0 | H4: =H19+H34 -> 0 | I4: =sum(E4:H4) -> 0 | K4: =K19+K34 -> 0 | L4: =L19+L34 -> 0 | M4: =M19+M34 -> 0 | N4: =N19+N34 -> 0 | O4: =O19+O34 -> 0 | P4: =P19+P34 -> 0 | Q4: =SUM(K4:P4) -> 0 | R4: =R19+R34 -> 1 | S4: =S19+S34 -> 0 | T4: =T19+T34 -> 2 | U4: =U19+U34 -> 0 | V4: =V19+V34 -> 1 | W4: =W19+W34 -> 0 | X4: =sum(R4:W4) -> 4 | Y4: =Y19+Y34 -> 0 | Z4: =Z19+Z34 -> 0 | AA4: =AA19+AA34 -> 2 | AB4: =AB19+AB34 -> 0 | AC4: =AC19+AC34 -> 0 | AD4: =AD19+AD34 -> 0 | AE4: =sum(Y4:AD4) -> 2 | AF4: =AF19+AF34 -> 0 | AG4: =AG19+AG34 -> 0 | AH4: =AH19+AH34 -> 0 | AI4: =sum(AF4:AH4) -> 0
A5: 目標有効商談数 | B5: =B4/B8 -> 56 | C5: 現状有効商談数 | D5: =I5+Q5+X5+AE5+AI5 -> 25 | E5: =E20+E35 -> 0 | F5: =F20+F35 -> 0 | G5: =G20+G35 -> 0 | H5: =H20+H35 -> 2 | I5: =sum(E5:H5) -> 2 | K5: =K20+K35 -> 2 | L5: =L20+L35 -> 0 | M5: =M20+M35 -> 0 | N5: =N20+N35 -> 1 | O5: =O20+O35 -> 3 | P5: =P20+P35 -> 2 | Q5: =SUM(K5:P5) -> 8 | R5: =R20+R35 -> 3 | S5: =S20+S35 -> 3 | T5: =T20+T35 -> 1 | U5: =U20+U35 -> 3 | V5: =V20+V35 -> 1 | W5: =W20+W35 -> 1 | X5: =sum(R5:W5) -> 12 | Y5: =Y20+Y35 -> 0 | Z5: =Z20+Z35 -> 0 | AA5: =AA20+AA35 -> 1 | AB5: =AB20+AB35 -> 0 | AC5: =AC20+AC35 -> 0 | AD5: =AD20+AD35 -> 0 | AE5: =sum(Y5:AD5) -> 1 | AF5: =AF20+AF35 -> 1 | AG5: =AG20+AG35 -> 1 | AH5: =AH20+AH35 -> 0 | AI5: =sum(AF5:AH5) -> 2
A6: 目標アポ数 | B6: =B5/B9 -> 80 | C6: 現状無効商談数 | D6: =I6+Q6+X6+AE6+AI6 -> 0 | E6: =E21+E36 -> 0 | F6: =F21+F36 -> 0 | G6: =G21+G36 -> 0 | H6: =H21+H36 -> 0 | I6: =sum(E6:H6) -> 0 | K6: =K21+K36 -> 0 | L6: =L21+L36 -> 0 | M6: =M21+M36 -> 0 | N6: =N21+N36 -> 0 | O6: =O21+O36 -> 0 | P6: =P21+P36 -> 0 | Q6: =SUM(K6:P6) -> 0 | R6: =R21+R36 -> 0 | S6: =S21+S36 -> 0 | T6: =T21+T36 -> 0 | U6: =U21+U36 -> 0 | V6: =V21+V36 -> 0 | W6: =W21+W36 -> 0 | X6: =sum(R6:W6) -> 0 | Y6: =Y21+Y36 -> 0 | Z6: =Z21+Z36 -> 0 | AA6: =AA21+AA36 -> 0 | AB6: =AB21+AB36 -> 0 | AC6: =AC21+AC36 -> 0 | AD6: =AD21+AD36 -> 0 | AE6: =sum(Y6:AD6) -> 0 | AF6: =AF21+AF36 -> 0 | AG6: =AG21+AG36 -> 0 | AH6: =AH21+AH36 -> 0 | AI6: =sum(AF6:AH6) -> 0
A7: 目標コール数 | B7: =B6/B10 -> 4000 | C7: 新規商談予定 | D7: =I7+Q7+X7+AE7+AI7 -> 39 | E7: =E22+E37 -> 0 | F7: =F22+F37 -> 0 | G7: =G22+G37 -> 2 | H7: =H22+H37 -> 2 | I7: =sum(E7:H7) -> 4 | K7: =K22+K37 -> 3 | L7: =L22+L37 -> 1 | M7: =M22+M37 -> 2 | N7: =N22+N37 -> 2 | O7: =O22+O37 -> 3 | P7: =P22+P37 -> 3 | Q7: =SUM(K7:P7) -> 14 | R7: =R22+R37 -> 3 | S7: =S22+S37 -> 3 | T7: =T22+T37 -> 2 | U7: =U22+U37 -> 5 | V7: =V22+V37 -> 2 | W7: =W22+W37 -> 1 | X7: =sum(R7:W7) -> 16 | Y7: =Y22+Y37 -> 0 | Z7: =Z22+Z37 -> 0 | AA7: =AA22+AA37 -> 1 | AB7: =AB22+AB37 -> 1 | AC7: =AC22+AC37 -> 0 | AD7: =AD22+AD37 -> 1 | AE7: =sum(Y7:AD7) -> 3 | AF7: =AF22+AF37 -> 1 | AG7: =AG22+AG37 -> 1 | AH7: =AH22+AH37 -> 0 | AI7: =sum(AF7:AH7) -> 2
A8: 目標受注率 | B8: 0.25 | C8: 当日アポ目標 | D8: =I8+Q8+X8+AE8+AI8 -> 93 | E8: =E23+E38 -> 0 | F8: =F23+F38 -> 4 | G8: =G23+G38 -> 5 | H8: =H23+H38 -> 6 | I8: =sum(E8:H8) -> 15 | K8: =K23+K38 -> 3 | L8: =L23+L38 -> 6 | M8: =M23+M38 -> 6 | N8: =N23+N38 -> 6 | O8: =O23+O38 -> 5 | P8: =P23+P38 -> 6 | Q8: =SUM(K8:P8) -> 32 | R8: =R23+R38 -> 5 | S8: =S23+S38 -> 4 | T8: =T23+T38 -> 5 | U8: =U23+U38 -> 5 | V8: =V23+V38 -> 6 | W8: =W23+W38 -> 2 | X8: =sum(R8:W8) -> 27 | Y8: =Y23+Y38 -> 0 | Z8: =Z23+Z38 -> 0 | AA8: =AA23+AA38 -> 2 | AB8: =AB23+AB38 -> 4 | AC8: =AC23+AC38 -> 4 | AD8: =AD23+AD38 -> 2 | AE8: =sum(Y8:AD8) -> 12 | AF8: =AF23+AF38 -> 2 | AG8: =AG23+AG38 -> 3 | AH8: =AH23+AH38 -> 2 | AI8: =sum(AF8:AH8) -> 7
A9: 目標出席率 | B9: 0.7 | C9: 現状アポ数 | D9: =I9+Q9+X9+AE9+AI9 -> 41 | E9: =E24+E39 -> 0 | F9: =F24+F39 -> 2 | G9: =G24+G39 -> 5 | H9: =H24+H39 -> 3 | I9: =sum(E9:H9) -> 10 | K9: =K24+K39 -> 1 | L9: =L24+L39 -> 2 | M9: =M24+M39 -> 3 | N9: =N24+N39 -> 2 | O9: =O24+O39 -> 3 | P9: =P24+P39 -> 2 | Q9: =SUM(K9:P9) -> 13 | R9: =R24+R39 -> 3 | S9: =S24+S39 -> 1 | T9: =T24+T39 -> 2 | U9: =U24+U39 -> 1 | V9: =V24+V39 -> 2 | W9: =W24+W39 -> 0 | X9: =sum(R9:W9) -> 9 | Y9: =Y24+Y39 -> 0 | Z9: =Z24+Z39 -> 0 | AA9: =AA24+AA39 -> 1 | AB9: =AB24+AB39 -> 0 | AC9: =AC24+AC39 -> 1 | AD9: =AD24+AD39 -> 0 | AE9: =sum(Y9:AD9) -> 2 | AF9: =AF24+AF39 -> 2 | AG9: =AG24+AG39 -> 4 | AH9: =AH24+AH39 -> 1 | AI9: =sum(AF9:AH9) -> 7
A10: 目標アポ転換率 | B10: 0.02 | C10: 現状コール数 | D10: =I10+Q10+X10+AE10+AI10 -> 4219 | E10: =E25+E40 -> 0 | F10: =F25+F40 -> 220 | G10: =G25+G40 -> 237 | H10: =H25+H40 -> 191 | I10: =sum(E10:H10) -> 648 | K10: =K25+K40 -> 30 | L10: =L25+L40 -> 223 | M10: =M25+M40 -> 225 | N10: =N25+N40 -> 183 | O10: =O25+O40 -> 180 | P10: =P25+P40 -> 258 | Q10: =SUM(K10:P10) -> 1099 | R10: =R25+R40 -> 164 | S10: =S25+S40 -> 174 | T10: =T25+T40 -> 177 | U10: =U25+U40 -> 213 | V10: =V25+V40 -> 213 | W10: =W25+W40 -> 0 | X10: =sum(R10:W10) -> 941 | Y10: =Y25+Y40 -> 0 | Z10: =Z25+Z40 -> 0 | AA10: =AA25+AA40 -> 149 | AB10: =AB25+AB40 -> 315 | AC10: =AC25+AC40 -> 230 | AD10: =AD25+AD40 -> 114 | AE10: =sum(Y10:AD10) -> 808 | AF10: =AF25+AF40 -> 268 | AG10: =AG25+AG40 -> 298 | AH10: =AH25+AH40 -> 157 | AI10: =sum(AF10:AH10) -> 723
A11: 1日の平均受注数 | B11: =D4/23 -> 0.26086957 | C11: 現状受注率 | D11: =D4/sum(D5:D6) -> 0.24 | E11: 1週間の平均受注数 | I11: =I4/4 -> 0 | K11: 1週間の平均受注数 | Q11: =Q4/6 -> 0 | R11: 1週間の平均受注数 | X11: =X4/6 -> 0.66666667 | Y11: 1週間の平均受注数 | AE11: =AE4/6 -> 0.33333333 | AF11: 1週間の平均受注数 | AI11: =AI4/3 -> 0
A12: 1日の平均消化数 | B12: =D5/23 -> 1.0869565 | C12: 現状出席率 | D12: =sum(D5:D6)/D7 -> 0.64102564 | E12: 1週間の平均消化数 | I12: =I5/3 -> 0.66666667 | K12: 1週間の平均消化数 | Q12: =Q5/6 -> 1.3333333 | R12: 1週間の平均消化数 | X12: =X5/6 -> 2 | Y12: 1週間の平均消化数 | AE12: =AE5/6 -> 0.16666667 | AF12: 1週間の平均消化数 | AI12: =AI5/3 -> 0.66666667
A13: 1日の平均アポ数 | B13: =D9/23 -> 1.7826087 | C13: 現状商談転換率 | D13: =SUM(D5:D6)/D9 -> 0.6097561 | E13: 1週間の平均アポ数 | I13: =I9/3 -> 3.3333333 | K13: 1週間の平均アポ数 | Q13: =Q9/6 -> 2.1666667 | R13: 1週間の平均アポ数 | X13: =X9/6 -> 1.5 | Y13: 1週間の平均アポ数 | AE13: =AE9/6 -> 0.33333333 | AF13: 1週間の平均アポ数 | AI13: =AI9/3 -> 2.3333333
A14: 1日の平均コール数 | B14: =D10/23 -> 183.43478 | C14: 現状アポ転換率 | D14: =D9/D10 -> 0.0097179426 | E14: 1週間の平均コール数 | I14: =I10/3 -> 216 | K14: 1週間の平均コール数 | Q14: =Q10/6 -> 183.16667 | R14: 1週間の平均コール数 | X14: =X10/6 -> 156.83333 | Y14: 1週間の平均コール数 | AE14: =AE10/6 -> 134.66667 | AF14: 1週間の平均コール数 | AI14: =AI10/3 -> 241
A16: 縞谷 | B16: 計画値 | D16: 現状 | E16: 火 | F16: 水 | G16: 木 | H16: 金 | I16: 土 | J16: 日 | K16: 月 | L16: 火 | M16: 水 | N16: 木 | O16: 金 | P16: 土 | Q16: 日 | R16: 月 | S16: 火 | T16: 水 | U16: 木 | V16: 金 | W16: 土 | X16: 日 | Y16: 月 | Z16: 火 | AA16: 水 | AB16: 木 | AC16: 金 | AD16: 土 | AE16: 日 | AF16: 月 | AG16: 火 | AH16: 水
E17: 45748 | F17: 45749 | G17: 45750 | H17: 45751 | I17: 45752 | J17: 45753 | K17: 45754 | L17: 45755 | M17: 45756 | N17: 45757 | O17: 45758 | P17: 45759 | Q17: 45760 | R17: 45761 | S17: 45762 | T17: 45763 | U17: 45764 | V17: 45765 | W17: 45766 | X17: 45767 | Y17: 45768 | Z17: 45769 | AA17: 45770 | AB17: 45771 | AC17: 45772 | AD17: 45773 | AE17: 45774 | AF17: 45775 | AG17: 45776 | AH17: 45777
A18: 売上目標 | B18: 1600000 | C18: 現状売上 | D18: =I18+Q18+X18+AE18+AI18 -> 1355000 | I18: =sum(E18:H18) -> 0 | Q18: =sum(K18:P18) -> 0 | R18: 235000 | T18: 470000 | V18: 180000 | X18: =sum(R18:W18) -> 885000 | AA18: 470000 | AE18: =sum(Y18:AD18) -> 470000 | AI18: =sum(AF18:AH18) -> 0
A19: 目標受注数 | B19: 9 | C19: 現状受注数 | D19: =I19+Q19+X19+AE19+AI19 -> 6 | I19: =sum(E19:H19) -> 0 | Q19: =SUM(K19:P19) -> 0 | R19: 1 | T19: 2 | V19: 1 | X19: =sum(R19:W19) -> 4 | AA19: 2 | AE19: =sum(Y19:AD19) -> 2 | AI19: =sum(AF19:AH19) -> 0
A20: 目標有効商談数 | B20: =B19/B23 -> 36 | C20: 現状有効商談数 | D20: =I20+Q20+X20+AE20+AI20 -> 20 | G20: 0 | H20: 2 | I20: =sum(E20:H20) -> 2 | K20: 2 | L20: 0 | N20: 1 | O20: 3 | P20: 2 | Q20: =SUM(K20:P20) -> 8 | R20: 3 | S20: 3 | T20: 1 | U20: 2 | V20: 1 | X20: =sum(R20:W20) -> 10 | AE20: =sum(Y20:AD20) -> 0 | AI20: =sum(AF20:AH20) -> 0
A21: 目標アポ数 | B21: =B20/B24 -> 51.428571 | C21: 現状無効商談数 | D21: =I21+Q21+X21+AE21+AI21 -> 0 | I21: =sum(E21:H21) -> 0 | Q21: =SUM(K21:P21) -> 0 | X21: =sum(R21:W21) -> 0 | AE21: =sum(Y21:AD21) -> 0 | AI21: =sum(AF21:AH21) -> 0
A22: 目標コール数 | B22: =B21/B25 -> 2571.4286 | C22: 新規商談予定 | D22: =I22+Q22+X22+AE22+AI22 -> 32 | G22: 1 | H22: 2 | I22: =sum(E22:H22) -> 3 | K22: 3 | L22: 1 | M22: 2 | N22: 2 | O22: 3 | P22: 3 | Q22: =SUM(K22:P22) -> 14 | R22: 3 | S22: 3 | T22: 2 | U22: 3 | V22: 2 | X22: =sum(R22:W22) -> 13 | AB22: 1 | AD22: 1 | AE22: =sum(Y22:AD22) -> 2 | AI22: =sum(AF22:AH22) -> 0
A23: 目標受注率 | B23: 0.25 | C23: 当日アポ目標 | D23: =I23+Q23+X23+AE23+AI23 -> 38 | F23: 2 | G23: 2 | H23: 3 | I23: =sum(E23:H23) -> 7 | K23: 3 | L23: 3 | M23: 3 | N23: 2 | O23: 2 | P23: 3 | Q23: =SUM(K23:P23) -> 16 | R23: 2 | S23: 1 | T23: 2 | U23: 3 | V23: 3 | X23: =sum(R23:W23) -> 11 | AB23: 2 | AC23: 2 | AE23: =sum(Y23:AD23) -> 4 | AI23: =sum(AF23:AH23) -> 0
A24: 目標出席率 | B24: 0.7 | C24: 現状アポ数 | D24: =I24+Q24+X24+AE24+AI24 -> 24 | F24: 2 | G24: 4 | H24: 3 | I24: =sum(E24:H24) -> 9 | K24: 1 | L24: 2 | M24: 1 | N24: 0 | O24: 1 | P24: 1 | Q24: =SUM(K24:P24) -> 6 | R24: 2 | S24: 1 | T24: 1 | U24: 1 | V24: 0 | X24: =sum(R24:W24) -> 5 | AC24: 1 | AE24: =sum(Y24:AD24) -> 1 | AF24: 1 | AG24: 2 | AI24: =sum(AF24:AH24) -> 3
A25: 目標アポ転換率 | B25: 0.02 | C25: 現状コール数 | D25: =I25+Q25+X25+AE25+AI25 -> 1564 | F25: 88 | G25: 70 | H25: 70 | I25: =sum(E25:H25) -> 228 | K25: 30 | L25: 80 | M25: 95 | N25: 80 | O25: 40 | P25: 106 | Q25: =SUM(K25:P25) -> 431 | R25: 43 | S25: 33 | T25: 60 | U25: 105 | V25: 47 | X25: =sum(R25:W25) -> 288 | AB25: 146 | AC25: 230 | AE25: =sum(Y25:AD25) -> 376 | AF25: 119 | AG25: 122 | AI25: =sum(AF25:AH25) -> 241
A26: 1日の平均受注数 | B26: =D19/23 -> 0.26086957 | C26: 現状受注率 | D26: =D19/sum(D20:D21) -> 0.3 | E26: 1週間の平均受注数 | I26: =I19/4 -> 0 | K26: 1週間の平均受注数 | Q26: =Q19/6 -> 0 | R26: 1週間の平均受注数 | X26: =X19/6 -> 0.66666667 | Y26: 1週間の平均受注数 | AE26: =AE19/6 -> 0.33333333 | AF26: 1週間の平均受注数 | AI26: =AI19/3 -> 0
A27: 1日の平均消化数 | B27: =D20/23 -> 0.86956522 | C27: 現状出席率 | D27: =sum(D20:D21)/D22 -> 0.625 | E27: 1週間の平均消化数 | I27: =I20/3 -> 0.66666667 | K27: 1週間の平均消化数 | Q27: =Q20/6 -> 1.3333333 | R27: 1週間の平均消化数 | X27: =X20/6 -> 1.6666667 | Y27: 1週間の平均消化数 | AE27: =AE20/6 -> 0 | AF27: 1週間の平均消化数 | AI27: =AI20/3 -> 0
A28: 1日の平均アポ数 | B28: =D24/23 -> 1.0434783 | C28: 現状商談転換率 | D28: =SUM(D20:D21)/D24 -> 0.83333333 | E28: 1週間の平均アポ数 | I28: =I24/3 -> 3 | K28: 1週間の平均アポ数 | Q28: =Q24/6 -> 1 | R28: 1週間の平均アポ数 | X28: =X24/6 -> 0.83333333 | Y28: 1週間の平均アポ数 | AE28: =AE24/6 -> 0.16666667 | AF28: 1週間の平均アポ数 | AI28: =AI24/3 -> 1
A29: 1日の平均コール数 | B29: =D25/23 -> 68 | C29: 現状アポ転換率 | D29: =D24/D25 -> 0.015345269 | E29: 1週間の平均コール数 | I29: =I25/3 -> 76 | K29: 1週間の平均コール数 | Q29: =Q25/6 -> 71.833333 | R29: 1週間の平均コール数 | X29: =X25/6 -> 48 | Y29: 1週間の平均コール数 | AE29: =AE25/6 -> 62.666667 | AF29: 1週間の平均コール数 | AI29: =AI25/3 -> 80.333333
A31: 前川 | B31: 計画値 | D31: 現状 | E31: 火 | F31: 水 | G31: 木 | H31: 金 | I31: 土 | J31: 日 | K31: 月 | L31: 火 | M31: 水 | N31: 木 | O31: 金 | P31: 土 | Q31: 日 | R31: 月 | S31: 火 | T31: 水 | U31: 木 | V31: 金 | W31: 土 | X31: 日 | Y31: 月 | Z31: 火 | AA31: 水 | AB31: 木 | AC31: 金 | AD31: 土 | AE31: 日 | AF31: 月 | AG31: 火 | AH31: 水
E32: 45748 | F32: 45749 | G32: 45750 | H32: 45751 | I32: 45752 | J32: 45753 | K32: 45754 | L32: 45755 | M32: 45756 | N32: 45757 | O32: 45758 | P32: 45759 | Q32: 45760 | R32: 45761 | S32: 45762 | T32: 45763 | U32: 45764 | V32: 45765 | W32: 45766 | X32: 45767 | Y32: 45768 | Z32: 45769 | AA32: 45770 | AB32: 45771 | AC32: 45772 | AD32: 45773 | AE32: 45774 | AF32: 45775 | AG32: 45776 | AH32: 45777
A33: 売上目標 | B33: 1200000 | C33: 現状売上 | D33: =sum(E33:AH33) -> 0 | I33: =sum(E33:H33) -> 0 | Q33: =sum(K33:P33) -> 0 | X33: =sum(R33:W33) -> 0 | AE33: =sum(Y33:AD33) -> 0 | AI33: =sum(AF33:AH33) -> 0
A34: 目標受注数 | B34: 8 | C34: 現状受注数 | D34: =sum(E34:AH34) -> 0 | I34: =sum(E34:H34) -> 0 | Q34: =SUM(K34:P34) -> 0 | X34: =sum(R34:W34) -> 0 | AE34: =sum(Y34:AD34) -> 0 | AI34: =sum(AF34:AH34) -> 0
A35: 目標有効商談数 | B35: =B34/B38 -> 40 | C35: 現状有効商談数 | D35: =sum(E35:AH35) -> 8 | I35: =sum(E35:H35) -> 0 | Q35: =SUM(K35:P35) -> 0 | U35: 1 | W35: 1 | X35: =sum(R35:W35) -> 2 | AA35: 1 | AE35: =sum(Y35:AD35) -> 1 | AF35: 1 | AG35: 1 | AI35: =sum(AF35:AH35) -> 2
A36: 目標アポ数 | B36: =B35/B39 -> 50 | C36: 現状無効商談数 | D36: =sum(E36:AH36) -> 0 | I36: =sum(E36:H36) -> 0 | Q36: =SUM(K36:P36) -> 0 | X36: =sum(R36:W36) -> 0 | AE36: =sum(Y36:AD36) -> 0 | AI36: =sum(AF36:AH36) -> 0
A37: 目標コール数 | B37: =B36/B40 -> 2500 | C37: 新規商談予定 | D37: =sum(E37:AH37) -> 12 | G37: 1 | H37: 0 | I37: =sum(E37:H37) -> 1 | Q37: =SUM(K37:P37) -> 0 | U37: 2 | W37: 1 | X37: =sum(R37:W37) -> 3 | AA37: 1 | AE37: =sum(Y37:AD37) -> 1 | AF37: 1 | AG37: 1 | AI37: =sum(AF37:AH37) -> 2
A38: 目標受注率 | B38: 0.2 | C38: 当日アポ目標 | D38: =sum(E38:AH38) -> 103 | F38: 2 | G38: 3 | H38: 3 | I38: =sum(E38:H38) -> 8 | L38: 3 | M38: 3 | N38: 4 | O38: 3 | P38: 3 | Q38: =SUM(K38:P38) -> 16 | R38: 3 | S38: 3 | T38: 3 | U38: 2 | V38: 3 | W38: 2 | X38: =sum(R38:W38) -> 16 | AA38: 2 | AB38: 2 | AC38: 2 | AD38: 2 | AE38: =sum(Y38:AD38) -> 8 | AF38: 2 | AG38: 3 | AH38: 2 | AI38: =sum(AF38:AH38) -> 7
A39: 目標出席率 | B39: 0.8 | C39: 現状アポ数 | D39: =sum(E39:AH39) -> 30 | F39: 0 | G39: 1 | H39: 0 | I39: =sum(E39:H39) -> 1 | L39: 0 | M39: 2 | N39: 2 | O39: 2 | P39: 1 | Q39: =SUM(K39:P39) -> 7 | R39: 1 | S39: 0 | T39: 1 | V39: 2 | W39: 0 | X39: =sum(R39:W39) -> 4 | AA39: 1 | AB39: 0 | AE39: =sum(Y39:AD39) -> 1 | AF39: 1 | AG39: 2 | AH39: 1 | AI39: =sum(AF39:AH39) -> 4
A40: 目標アポ転換率 | B40: 0.02 | C40: 現状コール数 | D40: =I40+Q40+X40+AE40+AI40 -> 2655 | F40: 132 | G40: 167 | H40: 121 | I40: =sum(E40:H40) -> 420 | L40: 143 | M40: 130 | N40: 103 | O40: 140 | P40: 152 | Q40: =SUM(K40:P40) -> 668 | R40: 121 | S40: 141 | T40: 117 | U40: 108 | V40: 166 | X40: =sum(R40:W40) -> 653 | AA40: 149 | AB40: 169 | AD40: 114 | AE40: =sum(Y40:AD40) -> 432 | AF40: 149 | AG40: 176 | AH40: 157 | AI40: =sum(AF40:AH40) -> 482
A41: 1日の平均受注数 | B41: =D34/23 -> 0 | C41: 現状受注率 | D41: =D34/sum(D35:D36) -> 0 | E41: 1週間の平均受注数 | I41: =I34/4 -> 0 | K41: 1週間の平均受注数 | Q41: =Q34/6 -> 0 | R41: 1週間の平均受注数 | X41: =X34/6 -> 0 | Y41: 1週間の平均受注数 | AE41: =AE34/6 -> 0 | AF41: 1週間の平均受注数 | AI41: =AI34/3 -> 0
A42: 1日の平均消化数 | B42: =D35/23 -> 0.34782609 | C42: 現状出席率 | D42: =sum(D35:D36)/D37 -> 0.66666667 | E42: 1週間の平均消化数 | I42: =I35/3 -> 0 | K42: 1週間の平均消化数 | Q42: =Q35/6 -> 0 | R42: 1週間の平均消化数 | X42: =X35/6 -> 0.33333333 | Y42: 1週間の平均消化数 | AE42: =AE35/6 -> 0.16666667 | AF42: 1週間の平均消化数 | AI42: =AI35/3 -> 0.66666667
A43: 1日の平均アポ数 | B43: =D39/23 -> 1.3043478 | C43: 現状商談転換率 | D43: =SUM(D35:D36)/D39 -> 0.26666667 | E43: 1週間の平均アポ数 | I43: =I39/3 -> 0.33333333 | K43: 1週間の平均アポ数 | Q43: =Q39/6 -> 1.1666667 | R43: 1週間の平均アポ数 | X43: =X39/6 -> 0.66666667 | Y43: 1週間の平均アポ数 | AE43: =AE39/6 -> 0.16666667 | AF43: 1週間の平均アポ数 | AI43: =AI39/3 -> 1.3333333
A44: 1日の平均コール数 | B44: =D40/23 -> 115.43478 | C44: 現状アポ転換率 | D44: =D39/D40 -> 0.011299435 | E44: 1週間の平均コール数 | I44: =I40/3 -> 140 | K44: 1週間の平均コール数 | Q44: =Q40/6 -> 111.33333 | R44: 1週間の平均コール数 | X44: =X40/6 -> 108.83333 | Y44: 1週間の平均コール数 | AE44: =AE40/6 -> 72 | AF44: 1週間の平均コール数 | AI44: =AI40/3 -> 160.66667
V45: =4/653 -> 0.0061255743

Sheet 【4月】週次振り返り用
A1: 全体 | B1: 第１週 | G1: 第2週 | L1: 第3週 | Q1: 第4週 | V1: 第5週
B2: 45749 | C2: ~ | E2: 45751 | G2: 45754 | H2: ~ | J2: 45759 | L2: 45761 | M2: ~ | O2: 45766 | Q2: 45768 | R2: ~ | T2: 45773 | V2: 45775 | W2: ~ | Y2: 45777
B3: 売上 | C3: ='【4月】月間進捗管理シート'!I3 -> 0 | D3: 平均単価 | E3: =C3/C4 -> #DIV/0! | G3: 売上 | H3: ='【4月】月間進捗管理シート'!Q3 -> #VALUE! | I3: 平均単価 | J3: =H3/H4 -> #VALUE! | L3: 売上 | M3: ='【4月】月間進捗管理シート'!X3 -> #VALUE! | N3: 平均単価 | O3: =M3/M4 -> #VALUE! | Q3: 売上 | S3: 平均単価 | T3: =R3/R4 -> #DIV/0! | V3: 売上 | X3: 平均単価 | Y3: =W3/W4 -> #DIV/0!
B4: 受注数 | C4: ='【4月】月間進捗管理シート'!I4 -> 0 | D4: 現状受注率 | E4: =C5/C4 -> #DIV/0! | G4: 受注数 | H4: ='【4月】月間進捗管理シート'!Q4 -> 0 | I4: 現状受注率 | J4: =H5/H4 -> #DIV/0! | L4: 受注数 | M4: ='【4月】月間進捗管理シート'!X4 -> 4 | N4: 現状受注率 | O4: =M5/M4 -> 3 | Q4: 受注数 | S4: 現状受注率 | T4: =R5/R4 -> #DIV/0! | V4: 受注数 | X4: 現状受注率 | Y4: =W5/W4 -> #DIV/0!
B5: 有効商談数 | C5: ='【4月】月間進捗管理シート'!I5 -> 2 | D5: 現状出席率 | E5: =C5/C7 -> 0.5 | G5: 有効商談数 | H5: ='【4月】月間進捗管理シート'!Q5 -> 8 | I5: 現状出席率 | J5: =H5/H7 -> 0.57142857 | L5: 有効商談数 | M5: ='【4月】月間進捗管理シート'!X5 -> 12 | N5: 現状出席率 | O5: =M5/M7 -> 0.75 | Q5: 有効商談数 | S5: 現状出席率 | T5: =R5/R7 -> #DIV/0! | V5: 有効商談数 | X5: 現状出席率 | Y5: =W5/W7 -> #DIV/0!
B6: 無効商談数 | C6: ='【4月】月間進捗管理シート'!I6 -> 0 | D6: 現状アポ転換率 | E6: =C8/C9 -> 0.015432099 | G6: 無効商談数 | H6: ='【4月】月間進捗管理シート'!Q6 -> 0 | I6: 現状アポ転換率 | J6: =H8/H9 -> 0.011828935 | L6: 無効商談数 | M6: ='【4月】月間進捗管理シート'!X6 -> 0 | N6: 現状アポ転換率 | O6: =M8/M9 -> 0.0095642933 | Q6: 無効商談数 | S6: 現状アポ転換率 | T6: =R8/R9 -> #DIV/0! | V6: 無効商談数 | X6: 現状アポ転換率 | Y6: =W8/W9 -> #DIV/0!
B7: 新規商談予定 | C7: ='【4月】月間進捗管理シート'!I7 -> 4 | D7: アポ→商談 | E7: 4 | G7: 新規商談予定 | H7: ='【4月】月間進捗管理シート'!Q7 -> 14 | I7: アポ→商談 | J7: 3 | L7: 新規商談予定 | M7: ='【4月】月間進捗管理シート'!X7 -> 16 | N7: アポ→商談 | O7: 3 | Q7: 新規商談予定 | S7: アポ→商談 | V7: 新規商談予定 | X7: アポ→商談
B8: 現状アポ数 | C8: ='【4月】月間進捗管理シート'!I9 -> 10 | D8: アポ→受注 | E8: 10 | G8: 現状アポ数 | H8: ='【4月】月間進捗管理シート'!Q9 -> 13 | I8: アポ→受注 | J8: 10 | L8: 現状アポ数 | M8: ='【4月】月間進捗管理シート'!X9 -> 9 | N8: アポ→受注 | O8: 10 | Q8: 現状アポ数 | S8: アポ→受注 | V8: 現状アポ数 | X8: アポ→受注
B9: 現状コール数 | C9: ='【4月】月間進捗管理シート'!I10 -> 648 | D9: アポ→通過 | E9: 17 | G9: 現状コール数 | H9: ='【4月】月間進捗管理シート'!Q10 -> 1099 | I9: アポ→通過 | J9: 16 | L9: 現状コール数 | M9: ='【4月】月間進捗管理シート'!X10 -> 941 | N9: アポ→通過 | O9: 17 | Q9: 現状コール数 | S9: アポ→通過 | V9: 現状コール数 | X9: アポ→通過
B10: 1週間の平均受注数 | D10: ='【4月】月間進捗管理シート'!I11 -> 0 | G10: 1週間の平均受注数 | I10: ='【4月】月間進捗管理シート'!Q11 -> 0 | L10: 1週間の平均受注数 | N10: ='【4月】月間進捗管理シート'!X11 -> 0.66666667 | Q10: 1週間の平均受注数 | V10: 1週間の平均受注数
B11: 1週間の平均消化数 | D11: ='【4月】月間進捗管理シート'!I12 -> 0.66666667 | G11: 1週間の平均消化数 | I11: ='【4月】月間進捗管理シート'!Q12 -> 1.3333333 | L11: 1週間の平均消化数 | N11: ='【4月】月間進捗管理シート'!X12 -> 2 | Q11: 1週間の平均消化数 | V11: 1週間の平均消化数
B12: 1週間の平均アポ数 | D12: ='【4月】月間進捗管理シート'!I13 -> 3.3333333 | G12: 1週間の平均アポ数 | I12: ='【4月】月間進捗管理シート'!Q13 -> 2.1666667 | L12: 1週間の平均アポ数 | N12: ='【4月】月間進捗管理シート'!X13 -> 1.5 | Q12: 1週間の平均アポ数 | V12: 1週間の平均アポ数
B13: 1週間の平均コール数 | D13: ='【4月】月間進捗管理シート'!I14 -> 216 | G13: 1週間の平均コール数 | I13: ='【4月】月間進捗管理シート'!Q14 -> 183.16667 | L13: 1週間の平均コール数 | N13: ='【4月】月間進捗管理シート'!X14 -> 156.83333 | Q13: 1週間の平均コール数 | V13: 1週間の平均コール数
A15: 縞谷 | B15: 45749 | C15: ~ | E15: 45751 | G15: 45754 | H15: ~ | J15: 45759 | L15: 45761 | M15: ~ | O15: 45766 | Q15: 45768 | R15: ~ | T15: 45773 | V15: 45775 | W15: ~ | Y15: 45777
B16: 売上 | C16: ='【4月】月間進捗管理シート'!I18 -> 0 | D16: 平均単価 | E16: =C16/C17 -> #DIV/0! | G16: 売上 | H16: ='【4月】月間進捗管理シート'!Q18 -> 0 | I16: 平均単価 | J16: =H16/H17 -> #DIV/0! | L16: 売上 | M16: ='【4月】月間進捗管理シート'!X18 -> 885000 | N16: 平均単価 | O16: =M16/M17 -> 221250 | Q16: 売上 | S16: 平均単価 | T16: =R16/R17 -> #DIV/0! | V16: 売上 | X16: 平均単価 | Y16: =W16/W17 -> #DIV/0!
B17: 受注数 | C17: ='【4月】月間進捗管理シート'!I19 -> 0 | D17: 現状受注率 | E17: =C18/C17 -> #DIV/0! | G17: 受注数 | H17: ='【4月】月間進捗管理シート'!Q19 -> 0 | I17: 現状受注率 | J17: =H18/H17 -> #DIV/0! | L17: 受注数 | M17: ='【4月】月間進捗管理シート'!X19 -> 4 | N17: 現状受注率 | O17: =M18/M17 -> 2.5 | Q17: 受注数 | S17: 現状受注率 | T17: =R18/R17 -> #DIV/0! | V17: 受注数 | X17: 現状受注率 | Y17: =W18/W17 -> #DIV/0!
B18: 有効商談数 | C18: ='【4月】月間進捗管理シート'!I20 -> 2 | D18: 現状出席率 | E18: =C18/C20 -> 0.66666667 | G18: 有効商談数 | H18: ='【4月】月間進捗管理シート'!Q20 -> 8 | I18: 現状出席率 | J18: =H18/H20 -> 0.57142857 | L18: 有効商談数 | M18: ='【4月】月間進捗管理シート'!X20 -> 10 | N18: 現状出席率 | O18: =M18/M20 -> 0.76923077 | Q18: 有効商談数 | S18: 現状出席率 | T18: =R18/R20 -> #DIV/0! | V18: 有効商談数 | X18: 現状出席率 | Y18: =W18/W20 -> #DIV/0!
B19: 無効商談数 | C19: ='【4月】月間進捗管理シート'!I21 -> 0 | D19: 現状アポ転換率 | E19: =C21/C22 -> 0.039473684 | G19: 無効商談数 | H19: ='【4月】月間進捗管理シート'!Q21 -> 0 | I19: 現状アポ転換率 | J19: =H21/H22 -> 0.013921114 | L19: 無効商談数 | M19: ='【4月】月間進捗管理シート'!X21 -> 0 | N19: 現状アポ転換率 | O19: =M21/M22 -> 0.017361111 | Q19: 無効商談数 | S19: 現状アポ転換率 | T19: =R21/R22 -> #DIV/0! | V19: 無効商談数 | X19: 現状アポ転換率 | Y19: =W21/W22 -> #DIV/0!
B20: 新規商談予定 | C20: ='【4月】月間進捗管理シート'!I22 -> 3 | D20: アポ→商談 | G20: 新規商談予定 | H20: ='【4月】月間進捗管理シート'!Q22 -> 14 | I20: アポ→商談 | L20: 新規商談予定 | M20: ='【4月】月間進捗管理シート'!X22 -> 13 | N20: アポ→商談 | Q20: 新規商談予定 | S20: アポ→商談 | V20: 新規商談予定 | X20: アポ→商談
B21: 現状アポ数 | C21: ='【4月】月間進捗管理シート'!I24 -> 9 | D21: アポ→受注 | G21: 現状アポ数 | H21: ='【4月】月間進捗管理シート'!Q24 -> 6 | I21: アポ→受注 | L21: 現状アポ数 | M21: ='【4月】月間進捗管理シート'!X24 -> 5 | N21: アポ→受注 | Q21: 現状アポ数 | S21: アポ→受注 | V21: 現状アポ数 | X21: アポ→受注
B22: 現状コール数 | C22: ='【4月】月間進捗管理シート'!I25 -> 228 | D22: アポ→通過 | G22: 現状コール数 | H22: ='【4月】月間進捗管理シート'!Q25 -> 431 | I22: アポ→通過 | L22: 現状コール数 | M22: ='【4月】月間進捗管理シート'!X25 -> 288 | N22: アポ→通過 | Q22: 現状コール数 | S22: アポ→通過 | V22: 現状コール数 | X22: アポ→通過
B23: 1週間の平均受注数 | D23: ='【4月】月間進捗管理シート'!I26 -> 0 | G23: 1週間の平均受注数 | I23: ='【4月】月間進捗管理シート'!Q26 -> 0 | L23: 1週間の平均受注数 | N23: ='【4月】月間進捗管理シート'!X26 -> 0.66666667 | Q23: 1週間の平均受注数 | V23: 1週間の平均受注数
B24: 1週間の平均消化数 | D24: ='【4月】月間進捗管理シート'!I27 -> 0.66666667 | G24: 1週間の平均消化数 | I24: ='【4月】月間進捗管理シート'!Q27 -> 1.3333333 | L24: 1週間の平均消化数 | N24: ='【4月】月間進捗管理シート'!X27 -> 1.6666667 | Q24: 1週間の平均消化数 | V24: 1週間の平均消化数
B25: 1週間の平均アポ数 | D25: ='【4月】月間進捗管理シート'!I28 -> 3 | G25: 1週間の平均アポ数 | I25: ='【4月】月間進捗管理シート'!Q28 -> 1 | L25: 1週間の平均アポ数 | N25: ='【4月】月間進捗管理シート'!X28 -> 0.83333333 | Q25: 1週間の平均アポ数 | V25: 1週間の平均アポ数
B26: 1週間の平均コール数 | D26: ='【4月】月間進捗管理シート'!I29 -> 76 | G26: 1週間の平均コール数 | I26: ='【4月】月間進捗管理シート'!Q29 -> 71.833333 | L26: 1週間の平均コール数 | N26: ='【4月】月間進捗管理シート'!X29 -> 48 | Q26: 1週間の平均コール数 | V26: 1週間の平均コール数
A28: 前川 | B28: 45749 | C28: ~ | E28: 45751 | G28: 45754 | H28: ~ | J28: 45759 | L28: 45761 | M28: ~ | O28: 45766 | Q28: 45768 | R28: ~ | T28: 45773 | V28: 45775 | W28: ~ | Y28: 45777
B29: 売上 | C29: ='【4月】月間進捗管理シート'!I33 -> 0 | D29: 平均単価 | E29: =C29/C30 -> #DIV/0! | G29: 売上 | H29: ='【4月】月間進捗管理シート'!Q33 -> 0 | I29: 平均単価 | J29: =H29/H30 -> #DIV/0! | L29: 売上 | M29: ='【4月】月間進捗管理シート'!X33 -> 0 | N29: 平均単価 | O29: =M29/M30 -> #DIV/0! | Q29: 売上 | S29: 平均単価 | T29: =R29/R30 -> #DIV/0! | V29: 売上 | X29: 平均単価 | Y29: =W29/W30 -> #DIV/0!
B30: 受注数 | C30: ='【4月】月間進捗管理シート'!I34 -> 0 | D30: 現状受注率 | E30: =C31/C30 -> #DIV/0! | G30: 受注数 | H30: ='【4月】月間進捗管理シート'!Q34 -> 0 | I30: 現状受注率 | J30: =H31/H30 -> #DIV/0! | L30: 受注数 | M30: ='【4月】月間進捗管理シート'!X34 -> 0 | N30: 現状受注率 | O30: =M31/M30 -> #DIV/0! | Q30: 受注数 | S30: 現状受注率 | T30: =R31/R30 -> #DIV/0! | V30: 受注数 | X30: 現状受注率 | Y30: =W31/W30 -> #DIV/0!
B31: 有効商談数 | C31: ='【4月】月間進捗管理シート'!I35 -> 0 | D31: 現状出席率 | E31: =C31/C33 -> 0 | G31: 有効商談数 | H31: ='【4月】月間進捗管理シート'!Q35 -> 0 | I31: 現状出席率 | J31: =H31/H33 -> #DIV/0! | L31: 有効商談数 | M31: ='【4月】月間進捗管理シート'!X35 -> 2 | N31: 現状出席率 | O31: =M31/M33 -> 0.66666667 | Q31: 有効商談数 | S31: 現状出席率 | T31: =R31/R33 -> #DIV/0! | V31: 有効商談数 | X31: 現状出席率 | Y31: =W31/W33 -> #DIV/0!
B32: 無効商談数 | C32: ='【4月】月間進捗管理シート'!I36 -> 0 | D32: 現状アポ転換率 | E32: =C34/C35 -> 0.0023809524 | G32: 無効商談数 | H32: ='【4月】月間進捗管理シート'!Q36 -> 0 | I32: 現状アポ転換率 | J32: =H34/H35 -> 0.010479042 | L32: 無効商談数 | M32: ='【4月】月間進捗管理シート'!X36 -> 0 | N32: 現状アポ転換率 | O32: =M34/M35 -> 0.0061255743 | Q32: 無効商談数 | S32: 現状アポ転換率 | T32: =R34/R35 -> #DIV/0! | V32: 無効商談数 | X32: 現状アポ転換率 | Y32: =W34/W35 -> #DIV/0!
B33: 新規商談予定 | C33: ='【4月】月間進捗管理シート'!I37 -> 1 | D33: アポ→商談 | G33: 新規商談予定 | H33: ='【4月】月間進捗管理シート'!Q37 -> 0 | I33: アポ→商談 | L33: 新規商談予定 | M33: ='【4月】月間進捗管理シート'!X37 -> 3 | N33: アポ→商談 | Q33: 新規商談予定 | S33: アポ→商談 | V33: 新規商談予定 | X33: アポ→商談
B34: 現状アポ数 | C34: ='【4月】月間進捗管理シート'!I39 -> 1 | D34: アポ→受注 | G34: 現状アポ数 | H34: ='【4月】月間進捗管理シート'!Q39 -> 7 | I34: アポ→受注 | L34: 現状アポ数 | M34: ='【4月】月間進捗管理シート'!X39 -> 4 | N34: アポ→受注 | Q34: 現状アポ数 | S34: アポ→受注 | V34: 現状アポ数 | X34: アポ→受注
B35: 現状コール数 | C35: ='【4月】月間進捗管理シート'!I40 -> 420 | D35: アポ→通過 | G35: 現状コール数 | H35: ='【4月】月間進捗管理シート'!Q40 -> 668 | I35: アポ→通過 | L35: 現状コール数 | M35: ='【4月】月間進捗管理シート'!X40 -> 653 | N35: アポ→通過 | Q35: 現状コール数 | S35: アポ→通過 | V35: 現状コール数 | X35: アポ→通過
B36: 1週間の平均受注数 | D36: ='【4月】月間進捗管理シート'!I41 -> 0 | G36: 1週間の平均受注数 | I36: ='【4月】月間進捗管理シート'!Q41 -> 0 | L36: 1週間の平均受注数 | N36: ='【4月】月間進捗管理シート'!X41 -> 0 | Q36: 1週間の平均受注数 | V36: 1週間の平均受注数
B37: 1週間の平均消化数 | D37: ='【4月】月間進捗管理シート'!I42 -> 0 | G37: 1週間の平均消化数 | I37: ='【4月】月間進捗管理シート'!Q42 -> 0 | L37: 1週間の平均消化数 | N37: ='【4月】月間進捗管理シート'!X42 -> 0.33333333 | Q37: 1週間の平均消化数 | V37: 1週間の平均消化数
B38: 1週間の平均アポ数 | D38: ='【4月】月間進捗管理シート'!I43 -> 0.33333333 | G38: 1週間の平均アポ数 | I38: ='【4月】月間進捗管理シート'!Q43 -> 1.1666667 | L38: 1週間の平均アポ数 | N38: ='【4月】月間進捗管理シート'!X43 -> 0.66666667 | Q38: 1週間の平均アポ数 | V38: 1週間の平均アポ数
B39: 1週間の平均コール数 | D39: ='【4月】月間進捗管理シート'!I44 -> 140 | G39: 1週間の平均コール数 | I39: ='【4月】月間進捗管理シート'!Q44 -> 111.33333 | L39: 1週間の平均コール数 | N39: ='【4月】月間進捗管理シート'!X44 -> 108.83333 | Q39: 1週間の平均コール数 | V39: 1週間の平均コール数

Sheet 【5月】月間進捗管理シート
A1: 全体 | B1: 計画値 | D1: 現状 | E1: 水 | F1: 木 | G1: 金 | H1: 土 | I1: 日 | J1: 月 | K1: 火 | L1: 水 | M1: 木 | N1: 金 | O1: 土 | P1: 日 | Q1: 月 | R1: 火 | S1: 水 | T1: 木 | U1: 金 | V1: 土 | W1: 日 | X1: 月 | Y1: 火 | Z1: 水 | AA1: 木 | AB1: 金 | AC1: 土 | AD1: 日
E2: 45784 | F2: 45785 | G2: 45786 | H2: 45787 | I2: 45788 | J2: 45789 | K2: 45790 | L2: 45791 | M2: 45792 | N2: 45793 | O2: 45794 | P2: 45795 | Q2: 45796 | R2: 45797 | S2: 45798 | T2: 45799 | U2: 45800 | V2: 45801 | W2: 45802 | X2: 45803 | Y2: 45804 | Z2: 45805 | AA2: 45806 | AB2: 45807 | AC2: 45808
A3: 売上目標 | B3: =B19+B34 -> 2800000 | C3: 現状売上 | D3: =#REF!+P3+W3+AD3 -> #REF! | E3: =E19+E34 -> 0 | F3: =F19+F34 -> 0 | G3: =G19+G34 -> 0 | H3: =H19+H34 -> 0 | I3: =sum(E3:H3) -> 0 | J3: =J19+J34 -> 0 | K3: =K19+K34 -> 0 | L3: =L19+L34 -> 0 | M3: =M19+M34 -> 0 | N3: =N19+N34 -> 0 | O3: =O19+O34 -> 1 | P3: =sum(J3:O3) -> 1 | Q3: =Q19+Q34 -> 0 | R3: =R19+R34 -> 0 | S3: =S19+S34 -> 0 | T3: =T19+T34 -> 0 | U3: =U19+U34 -> 0 | V3: =V19+V34 -> 0 | W3: =sum(Q3:V3) -> 0 | X3: =X19+X34 -> 0 | Y3: =Y19+Y34 -> 0 | Z3: =Z19+Z34 -> 0 | AA3: =AA19+AA34 -> 0 | AB3: =AB19+AB34 -> 0 | AC3: =AC19+AC34 -> 0 | AD3: =sum(X3:AC3) -> 0
A4: 目標受注数 | B4: =B20+B35 -> 14 | C4: 現状受注数 | D4: =H4+P4+W4+AD4 -> 120000 | E4: =E20+E35 -> 0 | F4: =F20+F35 -> 0 | G4: =G20+G36 -> 1 | H4: =H20+H35 -> 0 | I4: =SUM(C4:H4) -> 120001 | J4: =J20+J35 -> 0 | K4: =K20+K35 -> 0 | L4: =L20+L35 -> 0 | M4: =M20+M35 -> 0 | N4: =N20+N35 -> 0 | O4: =O20+O35 -> 120000 | P4: =SUM(J4:O4) -> 120000 | Q4: =Q20+Q35 -> 0 | R4: =R20+R35 -> 0 | S4: =S20+S35 -> 0 | T4: =T20+T35 -> 0 | U4: =U20+U35 -> 0 | V4: =V20+V35 -> 0 | W4: =sum(Q4:V4) -> 0 | X4: =X20+X35 -> 0 | Y4: =Y20+Y35 -> 0 | Z4: =Z20+Z35 -> 0 | AA4: =AA20+AA35 -> 0 | AB4: =AB20+AB35 -> 0 | AC4: =AC20+AC35 -> 0 | AD4: =sum(X4:AC4) -> 0
A5: 目標有効商談数 | B5: =B4/B8 -> 56 | C5: 現状有効商談数 | D5: =H5+P5+W5+AD5 -> 16 | E5: =E21+E36 -> 2 | F5: =F21+F36 -> 2 | G5: =G21+G37 -> 1 | H5: =H21+H36 -> 2 | I5: =SUM(C5:H5) -> 23 | J5: =J21+J36 -> 0 | K5: =K21+K36 -> 0 | L5: =L21+L36 -> 1 | M5: =M21+M36 -> 2 | N5: =N21+N36 -> 1 | O5: =O21+O36 -> 3 | P5: =SUM(J5:O5) -> 7 | Q5: =Q21+Q36 -> 2 | R5: =R21+R36 -> 1 | S5: =S21+S36 -> 1 | T5: =T21+T36 -> 2 | U5: =U21+U36 -> 1 | V5: =V21+V36 -> 0 | W5: =sum(Q5:V5) -> 7 | X5: =X21+X36 -> 0 | Y5: =Y21+Y36 -> 0 | Z5: =Z21+Z36 -> 0 | AA5: =AA21+AA36 -> 0 | AB5: =AB21+AB36 -> 0 | AC5: =AC21+AC36 -> 0 | AD5: =sum(X5:AC5) -> 0
A6: 目標アポ数 | B6: =B5/B9 -> 80 | C6: 現状無効商談数 | D6: =H6+P6+W6+AD6 -> 0 | E6: =E22+E37 -> 0 | F6: =F22+F37 -> 0 | G6: =G22+#REF! -> #REF! | H6: =H22+H37 -> 0 | I6: =SUM(C6:H6) -> #REF! | J6: =J22+J37 -> 0 | K6: =K22+K37 -> 0 | L6: =L22+L37 -> 0 | M6: =M22+M37 -> 0 | N6: =N22+N37 -> 0 | O6: =O22+O37 -> 0 | P6: =SUM(J6:O6) -> 0 | Q6: =Q22+Q37 -> 0 | R6: =R22+R37 -> 0 | S6: =S22+S37 -> 0 | T6: =T22+T37 -> 0 | U6: =U22+U37 -> 0 | V6: =V22+V37 -> 0 | W6: =sum(Q6:V6) -> 0 | X6: =X22+X37 -> 0 | Y6: =Y22+Y37 -> 0 | Z6: =Z22+Z37 -> 0 | AA6: =AA22+AA37 -> 0 | AB6: =AB22+AB37 -> 0 | AC6: =AC22+AC37 -> 0 | AD6: =sum(X6:AC6) -> 0
A7: 目標コール数 | B7: =B6/B10 -> 4000 | C7: 新規商談予定 | D7: =H7+P7+W7+AD7 -> 31 | E7: =E23+E38 -> 2 | F7: =F23+F38 -> 3 | G7: =G23+G38 -> 2 | H7: =H23+H38 -> 2 | I7: =SUM(C7:H7) -> 40 | J7: =J23+J38 -> 2 | K7: =K23+K38 -> 0 | L7: =L23+L38 -> 2 | M7: =M23+M38 -> 4 | N7: =N23+N38 -> 2 | O7: =O23+O38 -> 3 | P7: =SUM(J7:O7) -> 13 | Q7: =Q23+Q38 -> 4 | R7: =R23+R38 -> 4 | S7: =S23+S38 -> 1 | T7: =T23+T38 -> 3 | U7: =U23+U38 -> 2 | V7: =V23+V38 -> 0 | W7: =sum(Q7:V7) -> 14 | X7: =X23+X38 -> 2 | Y7: =Y23+Y38 -> 0 | Z7: =Z23+Z38 -> 0 | AA7: =AA23+AA38 -> 0 | AB7: =AB23+AB38 -> 0 | AC7: =AC23+AC38 -> 0 | AD7: =sum(X7:AC7) -> 2
A8: 目標受注率 | B8: 0.25 | C8: 当日アポ目標 | D8: =H8+P8+W8+AD8 -> 40 | E8: =E24+E39 -> 4 | F8: =F24+F39 -> 5 | G8: =G24+G39 -> 5 | H8: =H24+H39 -> 5 | I8: =SUM(C8:H8) -> 59 | J8: =J24+J39 -> 6 | K8: =K24+K39 -> 5 | L8: =L24+L39 -> 5 | M8: =M24+M39 -> 5 | N8: =N24+N39 -> 3 | O8: =O24+O39 -> 3 | P8: =SUM(J8:O8) -> 27 | Q8: =Q24+Q39 -> 0 | R8: =R24+R39 -> 2 | S8: =S24+S39 -> 1 | T8: =T24+T39 -> 1 | U8: =U24+U39 -> 1 | V8: =V24+V39 -> 0 | W8: =sum(Q8:V8) -> 5 | X8: =X24+X39 -> 1 | Y8: =Y24+Y39 -> 2 | Z8: =Z24+Z39 -> 0 | AA8: =AA24+AA39 -> 0 | AB8: =AB24+AB39 -> 0 | AC8: =AC24+AC39 -> 0 | AD8: =sum(X8:AC8) -> 3
A9: 目標出席率 | B9: 0.7 | C9: 現状アポ数 | D9: =H9+P9+W9+AD9 -> 20 | E9: =E25+E40 -> 1 | F9: =F25+F40 -> 3 | G9: =G25+G40 -> 1 | H9: =H25+H40 -> 1 | I9: =SUM(C9:H9) -> 26 | J9: =J25+J40 -> 2 | K9: =K25+K40 -> 2 | L9: =L25+L40 -> 3 | M9: =M25+M40 -> 1 | N9: =N25+N40 -> 4 | O9: =O25+O40 -> 2 | P9: =SUM(J9:O9) -> 14 | Q9: =Q25+Q40 -> 0 | R9: =R25+R40 -> 1 | S9: =S25+S40 -> 2 | T9: =T25+T40 -> 1 | U9: =U25+U40 -> 1 | V9: =V25+V40 -> 0 | W9: =sum(Q9:V9) -> 5 | X9: =X25+X40 -> 0 | Y9: =Y25+Y40 -> 0 | Z9: =Z25+Z40 -> 0 | AA9: =AA25+AA40 -> 0 | AB9: =AB25+AB40 -> 0 | AC9: =AC25+AC40 -> 0 | AD9: =sum(X9:AC9) -> 0
A10: 目標アポ転換率 | B10: 0.02 | C10: 現状コール数 | D10: =H10+P10+W10+AD10 -> 2300 | E10: =E26+E41 -> 161 | F10: =F26+F41 -> 231 | G10: =G26+G41 -> 261 | H10: =H26+H41 -> 249 | I10: =SUM(C10:H10) -> 3202 | J10: =J26+J41 -> 229 | K10: =K26+K41 -> 109 | L10: =L26+L41 -> 170 | M10: =M26+M41 -> 147 | N10: =N26+N41 -> 217 | O10: =O26+O41 -> 239 | P10: =SUM(J10:O10) -> 1111 | Q10: =Q26+Q41 -> 194 | R10: =R26+R41 -> 155 | S10: =S26+S41 -> 190 | T10: =T26+T41 -> 134 | U10: =U26+U41 -> 6 | V10: =V26+V41 -> 0 | W10: =sum(Q10:V10) -> 679 | X10: =X26+X41 -> 121 | Y10: =Y26+Y41 -> 140 | Z10: =Z26+Z41 -> 0 | AA10: =AA26+AA41 -> 0 | AB10: =AB26+AB41 -> 0 | AC10: =AC26+AC41 -> 0 | AD10: =sum(X10:AC10) -> 261
A11: 1日の平均受注数 | B11: =D4/日にち -> #NAME? | C11: 現状受注率 | D11: =D4/sum(D5:D6) -> 7500 | E11: 1週間の平均受注数 | I11: =I4/4 -> 30000.25 | J11: 1週間の平均受注数 | P11: =P4/6 -> 20000 | Q11: 1週間の平均受注数 | W11: =W4/6 -> 0 | X11: 1週間の平均受注数 | AD11: =AD4/6 -> 0
A12: 1日の平均消化数 | B12: =D5/日にち -> #NAME? | C12: 現状出席率 | D12: =sum(D5:D6)/D7 -> 0.51612903 | E12: 1週間の平均消化数 | I12: =I5/4 -> 5.75 | J12: 1週間の平均消化数 | P12: =P5/6 -> 1.1666667 | Q12: 1週間の平均消化数 | W12: =W5/6 -> 1.1666667 | X12: 1週間の平均消化数 | AD12: =AD5/6 -> 0
A13: 1日の平均アポ数 | B13: =D9/日にち -> #NAME? | C13: 現状商談転換率 | D13: =SUM(D5:D6)/D9 -> 0.8 | E13: 1週間の平均アポ数 | I13: =I9/4 -> 6.5 | J13: 1週間の平均アポ数 | P13: =P9/6 -> 2.3333333 | Q13: 1週間の平均アポ数 | W13: =W9/6 -> 0.83333333 | X13: 1週間の平均アポ数 | AD13: =AD9/6 -> 0
A14: 1日の平均コール数 | B14: =D10/日にち -> #NAME? | C14: 現状アポ転換率 | D14: =D9/D10 -> 0.0086956522 | E14: 1週間の平均コール数 | I14: =I10/4 -> 800.5 | J14: 1週間の平均コール数 | P14: =P10/6 -> 185.16667 | Q14: 1週間の平均コール数 | W14: =W10/6 -> 113.16667 | X14: 1週間の平均コール数 | AD14: =AD10/6 -> 43.5
A17: 縞谷 | B17: 計画値 | D17: 現状 | E17: 水 | F17: 木 | G17: 金 | H17: 土 | I17: 日 | J17: 月 | K17: 火 | L17: 水 | M17: 木 | N17: 金 | O17: 土 | P17: 日 | Q17: 月 | R17: 火 | S17: 水 | T17: 木 | U17: 金 | V17: 土 | W17: 日 | X17: 月 | Y17: 火 | Z17: 水 | AA17: 木 | AB17: 金 | AC17: 土 | AD17: 日
E18: 45784 | F18: 45785 | G18: 45786 | H18: 45787 | I18: 45788 | J18: 45789 | K18: 45790 | L18: 45791 | M18: 45792 | N18: 45793 | O18: 45794 | P18: 45795 | Q18: 45796 | R18: 45797 | S18: 45798 | T18: 45799 | U18: 45800 | V18: 45801 | W18: 45802 | X18: 45803 | Y18: 45804 | Z18: 45805 | AA18: 45806 | AB18: 45807 | AC18: 45808
A19: 売上目標 | B19: 1800000 | C19: 現状売上 | D19: =I19+P19+W19+AD19 -> 1 | I19: =sum(E19:H19) -> 0 | O19: 1 | P19: =sum(J19:O19) -> 1 | W19: =sum(Q19:V19) -> 0 | AD19: =sum(X19:AC19) -> 0
A20: 目標受注数 | B20: 9 | C20: 現状受注数 | D20: =I20+P20+W20+AD20 -> 120000 | I20: =sum(E20:H20) -> 0 | O20: 120000 | P20: =SUM(J20:O20) -> 120000 | W20: =sum(Q20:V20) -> 0 | AD20: =sum(X20:AC20) -> 0
A21: 目標有効商談数 | B21: =B20/B24 -> 36 | C21: 現状有効商談数 | D21: =I21+P21+W21+AD21 -> 16 | E21: 2 | F21: 2 | G21: 1 | H21: 1 | I21: =sum(E21:H21) -> 6 | M21: 1 | N21: 1 | O21: 2 | P21: =SUM(J21:O21) -> 4 | Q21: 1 | R21: 1 | S21: 1 | T21: 2 | U21: 1 | W21: =sum(Q21:V21) -> 6 | AD21: =sum(X21:AC21) -> 0
A22: 目標アポ数 | B22: =B21/B25 -> 51.428571 | C22: 現状無効商談数 | D22: =I22+P22+W22+AD22 -> 0 | I22: =sum(E22:H22) -> 0 | P22: =SUM(J22:O22) -> 0 | W22: =sum(Q22:V22) -> 0 | AD22: =sum(X22:AC22) -> 0
A23: 目標コール数 | B23: =B22/B26 -> 3428.5714 | C23: 新規商談予定 | D23: =I23+P23+W23+AD23 -> 29 | E23: 2 | F23: 3 | G23: 1 | H23: 1 | I23: =sum(E23:H23) -> 7 | J23: 1 | L23: 1 | M23: 3 | N23: 2 | O23: 2 | P23: =SUM(J23:O23) -> 9 | Q23: 3 | R23: 4 | S23: 1 | T23: 3 | U23: 2 | W23: =sum(Q23:V23) -> 13 | AD23: =sum(X23:AC23) -> 0
A24: 目標受注率 | B24: 0.25 | C24: 当日アポ目標 | D24: =I24+P24+W24+AD24 -> 20 | E24: 2 | F24: 3 | G24: 3 | H24: 3 | I24: =sum(E24:H24) -> 11 | J24: 3 | K24: 2 | L24: 2 | M24: 2 | P24: =SUM(J24:O24) -> 9 | W24: =sum(Q24:V24) -> 0 | AD24: =sum(X24:AC24) -> 0
A25: 目標出席率 | B25: 0.7 | C25: 現状アポ数 | D25: =I25+P25+W25+AD25 -> 17 | E25: 1 | F25: 1 | G25: 0 | H25: 1 | I25: =sum(E25:H25) -> 3 | J25: 1 | K25: 1 | L25: 3 | M25: 0 | N25: 3 | O25: 2 | P25: =SUM(J25:O25) -> 10 | Q25: 0 | R25: 1 | S25: 2 | T25: 1 | W25: =sum(Q25:V25) -> 4 | AD25: =sum(X25:AC25) -> 0
A26: 目標アポ転換率 | B26: 0.015 | C26: 現状コール数 | D26: =I26+P26+W26+AD26 -> 827 | E26: 31 | F26: 59 | G26: 101 | H26: 100 | I26: =sum(E26:H26) -> 291 | J26: 82 | K26: 34 | L26: 60 | M26: 55 | N26: 66 | O26: 77 | P26: =SUM(J26:O26) -> 374 | Q26: 52 | R26: 11 | S26: 82 | T26: 17 | W26: =sum(Q26:V26) -> 162 | AD26: =sum(X26:AC26) -> 0
A27: 1日の平均受注数 | B27: =D20/'【第一】案件管理シート'!E2 -> 8000 | C27: 現状受注率 | D27: =D20/sum(D21:D22) -> 7500 | E27: 1週間の平均受注数 | I27: =I20/4 -> 0 | J27: 1週間の平均受注数 | P27: =P20/6 -> 20000 | Q27: 1週間の平均受注数 | W27: =W20/6 -> 0 | X27: 1週間の平均受注数 | AD27: =AD20/6 -> 0
A28: 1日の平均消化数 | B28: =D21/'【第一】案件管理シート'!E2 -> 1.0666667 | C28: 現状出席率 | D28: =sum(D21:D22)/D23 -> 0.55172414 | E28: 1週間の平均消化数 | I28: =I21/4 -> 1.5 | J28: 1週間の平均消化数 | P28: =P21/6 -> 0.66666667 | Q28: 1週間の平均消化数 | W28: =W21/6 -> 1 | X28: 1週間の平均消化数 | AD28: =AD21/6 -> 0
A29: 1日の平均アポ数 | B29: =D25/'【第一】案件管理シート'!E2 -> 1.1333333 | C29: 現状商談転換率 | D29: =SUM(D21:D22)/D25 -> 0.94117647 | E29: 1週間の平均アポ数 | I29: =I25/4 -> 0.75 | J29: 1週間の平均アポ数 | P29: =P25/6 -> 1.6666667 | Q29: 1週間の平均アポ数 | W29: =W25/6 -> 0.66666667 | X29: 1週間の平均アポ数 | AD29: =AD25/6 -> 0
A30: 1日の平均コール数 | B30: =D26/'【第一】案件管理シート'!E2 -> 55.133333 | C30: 現状アポ転換率 | D30: =D25/D26 -> 0.020556227 | E30: 1週間の平均コール数 | I30: =I26/4 -> 72.75 | J30: 1週間の平均コール数 | P30: =P26/6 -> 62.333333 | Q30: 1週間の平均コール数 | W30: =W26/6 -> 27 | X30: 1週間の平均コール数 | AD30: =AD26/6 -> 0
A32: 前川 | B32: 計画値 | D32: 現状 | E32: 水 | F32: 木 | G32: 金 | H32: 土 | I32: 日 | J32: 月 | K32: 火 | L32: 水 | M32: 木 | N32: 金 | O32: 土 | P32: 日 | Q32: 月 | R32: 火 | S32: 水 | T32: 木 | U32: 金 | V32: 土 | W32: 日 | X32: 月 | Y32: 火 | Z32: 水 | AA32: 木 | AB32: 金 | AC32: 土 | AD32: 日
E33: 45784 | F33: 45785 | G33: 45786 | H33: 45787 | I33: 45788 | J33: 45789 | K33: 45790 | L33: 45791 | M33: 45792 | N33: 45793 | O33: 45794 | P33: 45795 | Q33: 45796 | R33: 45797 | S33: 45798 | T33: 45799 | U33: 45800 | V33: 45801 | W33: 45802 | X33: 45803 | Y33: 45804 | Z33: 45805 | AA33: 45806 | AB33: 45807 | AC33: 45808
A34: 売上目標 | B34: 1000000 | C34: 現状売上 | D34: =I34+P34+W34+AD34 -> 0 | I34: =sum(E34:H34) -> 0 | P34: =sum(J34:O34) -> 0 | W34: =sum(Q34:V34) -> 0 | AD34: =sum(X34:AC34) -> 0
A35: 目標受注数 | B35: 5 | C35: 現状受注数 | D35: =I35+P35+W35+AD35 -> 0 | I35: =sum(E35:H35) -> 0 | P35: =SUM(J35:O35) -> 0 | W35: =sum(Q35:V35) -> 0 | AD35: =sum(X35:AC35) -> 0
A36: 目標有効商談数 | B36: =B35/B39 -> 25 | C36: 現状有効商談数 | D36: =I36+P36+W36+AD36 -> 6 | G36: 1 | H36: 1 | I36: =sum(E36:H36) -> 2 | L36: 1 | M36: 1 | O36: 1 | P36: =SUM(J36:O36) -> 3 | Q36: 1 | W36: =sum(Q36:V36) -> 1 | AD36: =sum(X36:AC36) -> 0
A37: 目標アポ数 | B37: =B36/B40 -> 35.714286 | C37: 現状無効商談数 | D37: =I37+P37+W37+AD37 -> 0 | I37: =sum(E37:H37) -> 0 | P37: =SUM(J37:O37) -> 0 | W37: =sum(Q37:V37) -> 0 | AD37: =sum(X37:AC37) -> 0
A38: 目標コール数 | B38: =B37/B41 -> 2380.9524 | C38: 新規商談予定 | D38: =I38+P38+W38+AD38 -> 9 | G38: 1 | H38: 1 | I38: =sum(E38:H38) -> 2 | J38: 1 | L38: 1 | M38: 1 | O38: 1 | P38: =SUM(J38:O38) -> 4 | Q38: 1 | W38: =sum(Q38:V38) -> 1 | X38: 2 | AD38: =sum(X38:AC38) -> 2
A39: 目標受注率 | B39: 0.2 | C39: 当日アポ目標 | D39: =I39+P39+W39+AD39 -> 34 | E39: 2 | F39: 2 | G39: 2 | H39: 2 | I39: =sum(E39:H39) -> 8 | J39: 3 | K39: 3 | L39: 3 | M39: 3 | N39: 3 | O39: 3 | P39: =SUM(J39:O39) -> 18 | R39: 2 | S39: 1 | T39: 1 | U39: 1 | W39: =sum(Q39:V39) -> 5 | X39: 1 | Y39: 2 | AD39: =sum(X39:AC39) -> 3
A40: 目標出席率 | B40: 0.7 | C40: 現状アポ数 | D40: =I40+P40+W40+AD40 -> 8 | E40: 0 | F40: 2 | G40: 1 | H40: 0 | I40: =sum(E40:H40) -> 3 | J40: 1 | K40: 1 | L40: 0 | M40: 1 | N40: 1 | O40: 0 | P40: =SUM(J40:O40) -> 4 | Q40: 0 | R40: 0 | S40: 0 | T40: 0 | U40: 1 | W40: =sum(Q40:V40) -> 1 | X40: 0 | Y40: 0 | AD40: =sum(X40:AC40) -> 0
A41: 目標アポ転換率 | B41: 0.015 | C41: 現状コール数 | D41: =I41+P41+W41+AD41 -> 2126 | E41: 130 | F41: 172 | G41: 160 | H41: 149 | I41: =sum(E41:H41) -> 611 | J41: 147 | K41: 75 | L41: 110 | M41: 92 | N41: 151 | O41: 162 | P41: =SUM(J41:O41) -> 737 | Q41: 142 | R41: 144 | S41: 108 | T41: 117 | U41: 6 | W41: =sum(Q41:V41) -> 517 | X41: 121 | Y41: 140 | AD41: =sum(X41:AC41) -> 261
A42: 1日の平均受注数 | B42: =D35/'【第一】案件管理シート'!E2 -> 0 | C42: 現状受注率 | D42: =D35/sum(D36:D37) -> 0 | E42: 1週間の平均受注数 | I42: =I35/4 -> 0 | J42: 1週間の平均受注数 | P42: =P35/6 -> 0 | Q42: 1週間の平均受注数 | W42: =W35/6 -> 0 | X42: 1週間の平均受注数 | AD42: =AD35/6 -> 0
A43: 1日の平均消化数 | B43: =D36/'【第一】案件管理シート'!E2 -> 0.4 | C43: 現状出席率 | D43: =sum(D36:D37)/D38 -> 0.66666667 | E43: 1週間の平均消化数 | I43: =I36/4 -> 0.5 | J43: 1週間の平均消化数 | P43: =P36/6 -> 0.5 | Q43: 1週間の平均消化数 | W43: =W36/6 -> 0.16666667 | X43: 1週間の平均消化数 | AD43: =AD36/6 -> 0
A44: 1日の平均アポ数 | B44: =D40/'【第一】案件管理シート'!E2 -> 0.53333333 | C44: 現状商談転換率 | D44: =SUM(D36:D37)/D40 -> 0.75 | E44: 1週間の平均アポ数 | I44: =I40/4 -> 0.75 | J44: 1週間の平均アポ数 | P44: =P40/6 -> 0.66666667 | Q44: 1週間の平均アポ数 | W44: =W40/6 -> 0.16666667 | X44: 1週間の平均アポ数 | AD44: =AD40/6 -> 0
A45: 1日の平均コール数 | B45: =D41/'【第一】案件管理シート'!E2 -> 141.73333 | C45: 現状アポ転換率 | D45: =D40/D41 -> 0.0037629351 | E45: 1週間の平均コール数 | I45: =I41/4 -> 152.75 | J45: 1週間の平均コール数 | P45: =P41/6 -> 122.83333 | Q45: 1週間の平均コール数 | W45: =W41/6 -> 86.166667 | X45: 1週間の平均コール数 | AD45: =AD41/6 -> 43.5
U46: =4/653 -> 0.0061255743

Sheet 【6月】月間進捗管理シート
A2: 縞谷 | B2: 計画値 | D2: 現状 | E2: 月 | F2: 火 | G2: 水 | H2: 木 | I2: 金 | J2: 土 | K2: 日 | L2: 月 | M2: 火 | N2: 水 | O2: 木 | P2: 金 | Q2: 土 | R2: 日 | S2: 月 | T2: 火 | U2: 水 | V2: 木 | W2: 金 | X2: 土 | Y2: 日 | Z2: 月 | AA2: 火 | AB2: 水 | AC2: 木 | AD2: 金 | AE2: 土 | AF2: 日 | AG2: 土
E3: 45810 | F3: 45811 | G3: 45812 | H3: 45813 | I3: 45814 | J3: 45815 | K3: 45816 | L3: 45817 | M3: 45818 | N3: 45819 | O3: 45820 | P3: 45821 | Q3: 45822 | R3: 45823 | S3: 45824 | T3: 45825 | U3: 45826 | V3: 45827 | W3: 45828 | X3: 45829 | Y3: 45830 | Z3: 45831 | AA3: 45832 | AB3: 45833 | AC3: 45834 | AD3: 45835 | AE3: 45836 | AF3: 45837 | AG3: 45838
A4: 売上目標 | B4: 1500000 | C4: 現状売上 | D4: =K4+R4+Y4+AF4 -> 0 | K4: =sum(E4:J4) -> 0 | R4: =sum(L4:Q4) -> 0 | Y4: =sum(S4:X4) -> 0 | AF4: =sum(Z4:AE4) -> 0
A5: 目標受注数 | B5: 7 | C5: 現状受注数 | D5: =K5+R5+Y5+AF5 -> 0 | K5: =SUM(E5:J5) -> 0 | R5: =sum(L5:Q5) -> 0 | Y5: =sum(S5:X5) -> 0 | AF5: =sum(Z5:AE5) -> 0
A6: 目標有効商談数 | B6: =B5/B9 -> 28 | C6: 現状有効商談数 | D6: =K6+R6+Y6+AF6 -> 0 | K6: =SUM(E6:J6) -> 0 | R6: =sum(L6:Q6) -> 0 | Y6: =sum(S6:X6) -> 0 | AF6: =sum(Z6:AE6) -> 0
A7: 目標アポ数 | B7: =B6/B10 -> 40 | C7: 現状無効商談数 | D7: =K7+R7+Y7+AF7 -> 0 | K7: =SUM(E7:J7) -> 0 | R7: =sum(L7:Q7) -> 0 | Y7: =sum(S7:X7) -> 0 | AF7: =sum(Z7:AE7) -> 0
A8: 目標コール数 | B8: =B7/B11 -> 2666.6667 | C8: 新規商談予定 | D8: =K8+R8+Y8+AF8 -> 0 | K8: =SUM(E8:J8) -> 0 | R8: =sum(L8:Q8) -> 0 | Y8: =sum(S8:X8) -> 0 | AF8: =sum(Z8:AE8) -> 0
A9: 目標受注率 | B9: 0.25 | C9: 当日アポ目標 | D9: =K9+R9+Y9+AF9 -> 0 | K9: =SUM(E9:J9) -> 0 | R9: =sum(L9:Q9) -> 0 | Y9: =sum(S9:X9) -> 0 | AF9: =sum(Z9:AE9) -> 0
A10: 目標出席率 | B10: 0.7 | C10: 現状アポ数 | D10: =K10+R10+Y10+AF10 -> 0 | K10: =SUM(E10:J10) -> 0 | R10: =sum(L10:Q10) -> 0 | Y10: =sum(S10:X10) -> 0 | AF10: =sum(Z10:AE10) -> 0
A11: 目標アポ転換率 | B11: 0.015 | C11: 現状コール数 | D11: =K11+R11+Y11+AF11 -> 0 | K11: =SUM(E11:J11) -> 0 | R11: =sum(L11:Q11) -> 0 | Y11: =sum(S11:X11) -> 0 | AF11: =sum(Z11:AE11) -> 0
A12: 1日の平均受注数 | B12: =D5/'【第一】案件管理シート'!E2 -> 0 | C12: 現状受注率 | D12: =D5/sum(D6:D7) -> #DIV/0! | E12: 1週間の平均受注数 | K12: =K5/6 -> 0 | L12: 1週間の平均受注数 | R12: =R5/6 -> 0 | S12: 1週間の平均受注数 | Y12: =Y5/6 -> 0 | Z12: 1週間の平均受注数 | AF12: =AF5/6 -> 0
A13: 1日の平均消化数 | B13: =D6/'【第一】案件管理シート'!E2 -> 0 | C13: 現状出席率 | D13: =sum(D6:D7)/D8 -> #DIV/0! | E13: 1週間の平均消化数 | K13: =K6/6 -> 0 | L13: 1週間の平均消化数 | R13: =R6/6 -> 0 | S13: 1週間の平均消化数 | Y13: =Y6/6 -> 0 | Z13: 1週間の平均消化数 | AF13: =AF6/6 -> 0
A14: 1日の平均アポ数 | B14: =D10/'【第一】案件管理シート'!E2 -> 0 | C14: 現状商談転換率 | D14: =SUM(D6:D7)/D10 -> #DIV/0! | E14: 1週間の平均アポ数 | K14: =K10/6 -> 0 | L14: 1週間の平均アポ数 | R14: =R10/6 -> 0 | S14: 1週間の平均アポ数 | Y14: =Y10/6 -> 0 | Z14: 1週間の平均アポ数 | AF14: =AF10/6 -> 0
A15: 1日の平均コール数 | B15: =D11/'【第一】案件管理シート'!E2 -> 0 | C15: 現状アポ転換率 | D15: =D10/D11 -> #DIV/0! | E15: 1週間の平均コール数 | K15: =K11/6 -> 0 | L15: 1週間の平均コール数 | R15: =R11/6 -> 0 | S15: 1週間の平均コール数 | Y15: =Y11/6 -> 0 | Z15: 1週間の平均コール数 | AF15: =AF11/6 -> 0
A17: 前川 | B17: 計画値 | D17: 現状 | E17: 月 | F17: 火 | G17: 水 | H17: 木 | I17: 金 | J17: 土 | K17: 日 | L17: 月 | M17: 火 | N17: 水 | O17: 木 | P17: 金 | Q17: 土 | R17: 日 | S17: 月 | T17: 火 | U17: 水 | V17: 木 | W17: 金 | X17: 土 | Y17: 日 | Z17: 月 | AA17: 火 | AB17: 水 | AC17: 木 | AD17: 金 | AE17: 土 | AF17: 日 | AG17: 土
E18: 45810 | F18: 45811 | G18: 45812 | H18: 45813 | I18: 45814 | J18: 45815 | K18: 45816 | L18: 45817 | M18: 45818 | N18: 45819 | O18: 45820 | P18: 45821 | Q18: 45822 | R18: 45823 | S18: 45824 | T18: 45825 | U18: 45826 | V18: 45827 | W18: 45828 | X18: 45829 | Y18: 45830 | Z18: 45831 | AA18: 45832 | AB18: 45833 | AC18: 45834 | AD18: 45835 | AE18: 45836 | AF18: 45837 | AG18: 45838
A19: 売上目標 | C19: 現状売上 | D19: =K19+R19+Y19+AF19 -> 0 | K19: =sum(E19:J19) -> 0 | R19: =sum(L19:Q19) -> 0 | Y19: =sum(S19:X19) -> 0 | AF19: =sum(Z19:AE19) -> 0
A20: 目標アポ数 | C20: 有効商談数 | D20: =K20+R20+Y20+AF20 -> 0 | K20: =SUM(E20:J20) -> 0 | R20: =sum(L20:Q20) -> 0 | Y20: =sum(S20:X20) -> 0 | AF20: =sum(Z20:AE20) -> 0
A21: 目標コール数 | C21: 新規商談予定 | D21: =K21+R21+Y21+AF21 -> 0 | K21: =SUM(E21:J21) -> 0 | R21: =sum(L21:Q21) -> 0 | Y21: =sum(S21:X21) -> 0 | AF21: =sum(Z21:AE21) -> 0
A22: 目標出席率 | B22: 0.7 | C22: 現状アポ数 | D22: =K22+R22+Y22+AF22 -> 2 | K22: =SUM(E22:J22) -> 0 | L22: 1 | M22: 0 | N22: 0 | O22: 1 | P22: 0 | Q22: 0 | R22: =sum(L22:Q22) -> 2 | S22: 0 | T22: 0 | Y22: =sum(S22:X22) -> 0 | AF22: =sum(Z22:AE22) -> 0
A23: 目標アポ転換率 | B23: 0.015 | C23: 現状コール数 | D23: =K23+R23+Y23+AF23 -> 624 | K23: =SUM(E23:J23) -> 0 | L23: 79 | M23: 121 | N23: 110 | O23: 58 | P23: 45 | Q23: 38 | R23: =sum(L23:Q23) -> 451 | S23: 67 | T23: 106 | Y23: =sum(S23:X23) -> 173 | AF23: =sum(Z23:AE23) -> 0
A24: 1日の平均アポ数 | B24: =D22/'【第一】案件管理シート'!E2 -> 0.13333333 | C24: 現状出席率 | D24: =D20/D21 -> #DIV/0! | E24: 1週間の平均アポ数 | K24: =K20/6 -> 0 | L24: 1週間の平均アポ数 | R24: =R20/6 -> 0 | S24: 1週間の平均アポ数 | Y24: =Y20/6 -> 0 | Z24: 1週間の平均アポ数 | AF24: =AF20/6 -> 0
A25: 1日の平均コール数 | B25: =D23/'【第一】案件管理シート'!E2 -> 41.6 | C25: 現状アポ転換率 | D25: =D22/D23 -> 0.0032051282 | E25: 1週間の平均コール数 | K25: =K21/6 -> 0 | L25: 1週間の平均コール数 | R25: =R21/6 -> 0 | S25: 1週間の平均コール数 | Y25: =Y21/6 -> 0 | Z25: 1週間の平均コール数 | AF25: =AF21/6 -> 0

Sheet 【7月】月間進捗管理シート
A2: 縞谷 | B2: 計画値 | D2: 現状 | E2: 火 | F2: 水 | G2: 木 | H2: 金 | I2: 土 | J2: 日 | K2: 月 | L2: 火 | M2: 水 | N2: 木 | O2: 金 | P2: 土 | Q2: 日 | R2: 月 | S2: 火 | T2: 水 | U2: 木 | V2: 金 | W2: 土 | X2: 日 | Y2: 月 | Z2: 火 | AA2: 水 | AB2: 木 | AC2: 金 | AD2: 土 | AE2: 日 | AF2: 月 | AG2: 火 | AH2: 水
E3: 45840 | F3: 45841 | G3: 45842 | H3: 45843 | I3: 45844 | J3: 45845 | K3: 45846 | L3: 45847 | M3: 45848 | N3: 45849 | O3: 45850 | P3: 45851 | Q3: 45852 | R3: 45853 | S3: 45854 | T3: 45855 | U3: 45856 | V3: 45857 | W3: 45858 | X3: 45859 | Y3: 45860 | Z3: 45861 | AA3: 45862 | AB3: 45863 | AC3: 45864 | AD3: 45865 | AE3: 45866 | AF3: 45867 | AG3: 45868 | AH3: 45869
A4: 売上目標 | B4: 1500000 | C4: 現状売上 | D4: =J4+Q4+X4+AE4 -> 0 | J4: =sum(E4:I4) -> 0 | Q4: =sum(K4:P4) -> 0 | X4: =sum(R4:W4) -> 0 | AE4: =sum(Y4:AD4) -> 0
A5: 目標受注数 | B5: 5 | C5: 現状受注数 | D5: =J5+Q5+X5+AE5 -> 0 | J5: =SUM(E5:I5) -> 0 | Q5: =sum(K5:P5) -> 0 | X5: =sum(R5:W5) -> 0 | AE5: =sum(Y5:AD5) -> 0
A6: 目標有効商談数 | B6: =B5/B9 -> 25 | C6: 現状有効商談数 | D6: =J6+Q6+X6+AE6 -> 0 | J6: =SUM(E6:I6) -> 0 | Q6: =sum(K6:P6) -> 0 | X6: =sum(R6:W6) -> 0 | AE6: =sum(Y6:AD6) -> 0
A7: 目標アポ数 | B7: =B6/B10 -> 41.666667 | C7: 現状無効商談数 | D7: =J7+Q7+X7+AE7 -> 0 | J7: =SUM(E7:I7) -> 0 | Q7: =sum(K7:P7) -> 0 | X7: =sum(R7:W7) -> 0 | AE7: =sum(Y7:AD7) -> 0
A8: 目標コール数 | B8: =B7/B11 -> 2777.7778 | C8: 新規商談予定 | D8: =J8+Q8+X8+AE8 -> 0 | J8: =SUM(E8:I8) -> 0 | Q8: =sum(K8:P8) -> 0 | X8: =sum(R8:W8) -> 0 | AE8: =sum(Y8:AD8) -> 0
A9: 目標受注率 | B9: 0.2 | C9: 当日アポ目標 | D9: =J9+Q9+X9+AE9 -> 0 | J9: =SUM(E9:I9) -> 0 | Q9: =sum(K9:P9) -> 0 | X9: =sum(R9:W9) -> 0 | AE9: =sum(Y9:AD9) -> 0
A10: 目標出席率 | B10: 0.6 | C10: 現状アポ数 | D10: =J10+Q10+X10+AE10 -> 0 | J10: =SUM(E10:I10) -> 0 | Q10: =sum(K10:P10) -> 0 | X10: =sum(R10:W10) -> 0 | AE10: =sum(Y10:AD10) -> 0
A11: 目標アポ転換率 | B11: 0.015 | C11: 現状コール数 | D11: =J11+Q11+X11+AE11 -> 0 | J11: =SUM(E11:I11) -> 0 | Q11: =sum(K11:P11) -> 0 | X11: =sum(R11:W11) -> 0 | AE11: =sum(Y11:AD11) -> 0
A12: 1日の平均受注数 | B12: =D5/'【第一】案件管理シート'!E2 -> 0 | C12: 現状受注率 | D12: =D5/sum(D6:D7) -> #DIV/0! | J12: =J5/6 -> 0 | K12: 1週間の平均受注数 | Q12: =Q5/6 -> 0 | R12: 1週間の平均受注数 | X12: =X5/6 -> 0 | Y12: 1週間の平均受注数 | AE12: =AE5/6 -> 0
A13: 1日の平均消化数 | B13: =D6/'【第一】案件管理シート'!E2 -> 0 | C13: 現状出席率 | D13: =sum(D6:D7)/D8 -> #DIV/0! | J13: =J6/6 -> 0 | K13: 1週間の平均消化数 | Q13: =Q6/6 -> 0 | R13: 1週間の平均消化数 | X13: =X6/6 -> 0 | Y13: 1週間の平均消化数 | AE13: =AE6/6 -> 0
A14: 1日の平均アポ数 | B14: =D10/'【第一】案件管理シート'!E2 -> 0 | C14: 現状商談転換率 | D14: =SUM(D6:D7)/D10 -> #DIV/0! | J14: =J10/6 -> 0 | K14: 1週間の平均アポ数 | Q14: =Q10/6 -> 0 | R14: 1週間の平均アポ数 | X14: =X10/6 -> 0 | Y14: 1週間の平均アポ数 | AE14: =AE10/6 -> 0
A15: 1日の平均コール数 | B15: =D11/'【第一】案件管理シート'!E2 -> 0 | C15: 現状アポ転換率 | D15: =D10/D11 -> #DIV/0! | J15: =J11/6 -> 0 | K15: 1週間の平均コール数 | Q15: =Q11/6 -> 0 | R15: 1週間の平均コール数 | X15: =X11/6 -> 0 | Y15: 1週間の平均コール数 | AE15: =AE11/6 -> 0

Sheet 【全体可視化シート】
A1: 今日の日付 | B1: =TODAY() -> 46192 | C1: 今月稼働日数 | E1: =_xlfn.NETWORKDAYS.INTL(B3, B4, "0000001", B7:B10) -> 23 | H1: 受注数 | I1: 受注率 | J1: 商談消化数 | K1: 出席率 | L1: アポ数 | M1: アポ転換率 | N1: コール数
C2: 現状稼働日数 | E2: =_xlfn.NETWORKDAYS.INTL(B3, B1, "0000001", B7:B10) -> 327 | G2: 目標 | H2: ='【5月】月間進捗管理シート'!B4 -> 14 | I2: ='【5月】月間進捗管理シート'!B8 -> 0.25 | J2: ='【5月】月間進捗管理シート'!B5 -> 56 | K2: ='【5月】月間進捗管理シート'!B9 -> 0.7 | L2: ='【5月】月間進捗管理シート'!B6 -> 80 | M2: ='【5月】月間進捗管理シート'!B10 -> 0.02 | N2: ='【5月】月間進捗管理シート'!B7 -> 4000
A3: 営業開始日 | B3: 45809 | C3: 残り稼働日数 | E3: =E1-E2+1 -> -303 | G3: 理想進捗 | H3: =H2/E1*E2 -> 199.04348 | J3: =J2/E1*E2 -> 796.17391 | L3: =L2/E1*E2 -> 1137.3913 | N3: =N2/E1*E2 -> 56869.565
A4: 営業終了日 | B4: 45838 | C4: アポ獲得日数 | E4: =_xlfn.NETWORKDAYS.INTL(B3, B5, "0000001", B7:B10) -> 17 | G4: 理想進捗率 | H4: =H3/H2 -> 14.217391 | J4: =J3/J2 -> 14.217391 | L4: =L3/L2 -> 14.217391 | N4: =N3/N2 -> 14.217391
A5: アポ獲得期限 | B5: 45829 | C5: アポ獲得期限残り日数 | E5: =E4-E2+1 -> -309 | G5: 現状 | H5: ='【5月】月間進捗管理シート'!D4 -> 120000 | I5: ='【5月】月間進捗管理シート'!D11 -> 7500 | J5: ='【5月】月間進捗管理シート'!D5 -> 16 | K5: ='【5月】月間進捗管理シート'!D12 -> 0.51612903 | L5: ='【5月】月間進捗管理シート'!D9 -> 20 | M5: ='【5月】月間進捗管理シート'!D14 -> 0.0086956522 | N5: ='【5月】月間進捗管理シート'!D10 -> 2300
A6: 商談消化期限 | B6: 45831 | C6: 消化日数 | E6: =_xlfn.NETWORKDAYS.INTL(B3, B6, "0000001", B7:B10) -> 18 | G6: 進捗率 | H6: =H5/H2 -> 8571.4286 | J6: =J5/J2 -> 0.28571429 | L6: =L5/L2 -> 0.25 | N6: =N5/N2 -> 0.575
A7: 休み | B7: 45815 | C7: 消化期限残り日数 | E7: =E6-E2+1 -> -308
B8: 45836 | C8: 受注予定 | E8: =E9+E10+E11 -> #REF! | G8: 乖離 | H8: =H5-H3 -> 119800.96 | I8: =I5-I2 -> 7499.75 | J8: =J5-J3 -> -780.17391 | K8: =K5-K2 -> -0.18387097 | L8: =L5-L3 -> -1117.3913 | M8: =M5-M2 -> -0.011304348 | N8: =N5-N3 -> -54569.565
C9: Aヨミ | E9: ='【第一】案件管理シート'!F11+'【個人案件管理シート】前川'!E9 -> 0
C10: Bヨミ | E10: ='【第一】案件管理シート'!F12+'【個人案件管理シート】前川'!E10 -> 0 | H10: 受注 | I10: 消化 | J10: アポ | K10: 架電数
C11: Cヨミ（アツイ） | E11: =#REF!+'【個人案件管理シート】前川'!E11 -> #REF! | G11: 目標 | H11: =H2 -> 14 | I11: =J2 -> 56 | J11: =L2 -> 80 | K11: =N2 -> 4000
C12: Eヨミ（残りアポ） | E12: ='【第一】案件管理シート'!F14+'【個人案件管理シート】前川'!E12 -> 0 | G12: 必要行動 | H12: =H11-E8 -> #REF! | I12: =H12/I2 -> #REF! | J12: =I12/K2-E12 -> #REF! | K12: =J12/M2 -> #REF!
D13: 45809 | E13: ='【第一】案件管理シート'!J1+'【個人案件管理シート】前川'!E13 -> 2 | G13: デイリー行動 | H13: =H12/E3 -> #REF! | I13: =I12/E7 -> #REF! | J13: =J12/E5 -> #REF! | K13: =K12/E5 -> #REF!
B14: 粗利目標
G15: 転換ループ | L15: 【週次集計用】転換ループ
B16: 現状粗利 | G16: アポ→商談 | I16: =IFERROR(__xludf.DUMMYFUNCTION("AVERAGE(FILTER(#REF!, (#REF!<>"""") * (#REF!<>""""))) "),"#REF!") -> #REF! | L16: アポ→商談 | N16: =IFERROR(__xludf.DUMMYFUNCTION("AVERAGE( FILTER( #REF!, (#REF!<>"""") * (#REF!<>"""") * ( (ROW(#REF!) <= 29) * (#REF! >= DATE(2025, 4, 14)) * (#REF! <= DATE(2025, 4, 19)) + (ROW(#REF!) > 29) ) ) ) "),"#REF!") -> #REF!
G17: アポ→受注 | I17: =IFERROR(__xludf.DUMMYFUNCTION("AVERAGE(FILTER(#REF!, (#REF!<>"""") * (#REF!<>""""))) "),"#REF!") -> #REF! | L17: アポ→受注 | N17: =IFERROR(__xludf.DUMMYFUNCTION("AVERAGE( FILTER( #REF!, (#REF!<>"""") * (#REF!<>"""") * ( (ROW(#REF!) <= 29) * (#REF! >= DATE(2025, 4, 14)) * (#REF! <= DATE(2025, 4, 19)) + (ROW(#REF!) > 29) ) ) ) "),"#REF!") -> #REF!
B18: 着地粗利(BA含)
G19: アポ→通過 | I19: =IFERROR(__xludf.DUMMYFUNCTION("AVERAGE(FILTER(#REF!, (#REF!<>"""") * (#REF!<>""""))) "),"#REF!") -> #REF! | L19: アポ→通過 | N19: =IFERROR(__xludf.DUMMYFUNCTION("AVERAGE( FILTER( #REF!, (#REF!<>"""") * (#REF!<>"""") * ( (ROW(#REF!) <= 29) * (#REF! >= DATE(2025, 4, 14)) * (#REF! <= DATE(2025, 4, 19)) + (ROW(#REF!) > 29) ) ) ) "),"#REF!") -> #REF!
B20: 平均受注粗利 | D20: =D16/E13 -> 0
G21: 商談→受注 | I21: =IFERROR(__xludf.DUMMYFUNCTION("AVERAGE(FILTER(#REF!, (#REF!<>"""") * (#REF!<>""""))) "),"#REF!") -> #REF! | L21: 商談→受注

Sheet 【8月】月間進捗管理シート
B1: 計画値 | D1: 現状 | E1: 金 | F1: 土 | G1: 日 | H1: 月 | I1: 火 | J1: 水 | K1: 木 | L1: 金 | M1: 土 | N1: 日 | O1: 月 | P1: 火 | Q1: 水 | R1: 木 | S1: 金 | T1: 土 | U1: 日 | V1: 月 | W1: 火 | X1: 水 | Y1: 木 | Z1: 金 | AA1: 土 | AB1: 日 | AC1: 月 | AD1: 火 | AE1: 水 | AF1: 木 | AG1: 金 | AH1: 土 | AI1: 日
E2: 45870 | F2: 45871 | G2: 45872 | H2: 45873 | I2: 45874 | J2: 45875 | K2: 45876 | L2: 45877 | M2: 45878 | N2: 45879 | O2: 45880 | P2: 45881 | Q2: 45882 | R2: 45883 | S2: 45884 | T2: 45885 | U2: 45886 | V2: 45887 | W2: 45888 | X2: 45889 | Y2: 45890 | Z2: 45891 | AA2: 45892 | AB2: 45893 | AC2: 45894 | AD2: 45895 | AE2: 45896 | AF2: 45897 | AG2: 45898 | AH2: 45899 | AI2: 45900
A3: 売上目標 | B3: 2200000 | C3: 現状売上 | D3: =sum(E3:M3)+sum(O3:T3)+sum(V3:AA3)+sum(AC3:AH3) -> 1615000 | N3: =sum(H3:M3) -> 0 | P3: 635000 | Q3: 235000 | R3: 235000 | U3: =sum(O3:T3) -> 1105000 | Y3: 180000 | Z3: 130000 | AB3: =sum(V3:AA3) -> 310000 | AC3: 200000 | AI3: =sum(AC3:AH3) -> 200000
A4: 目標受注数 | B4: 11 | C4: 現状受注数 | D4: =sum(E4:M4)+sum(O4:T4)+sum(V4:AA4)+sum(AC4:AH4) -> 8 | N4: =sum(H4:M4) -> 0 | P4: 3 | Q4: 1 | R4: 1 | U4: =sum(O4:T4) -> 5 | Y4: 1 | Z4: 1 | AB4: =sum(V4:AA4) -> 2 | AC4: 1 | AI4: =sum(AC4:AH4) -> 1
A5: 目標有効商談数 | B5: =B4/B8 -> 36.666667 | C5: 現状有効商談数 | D5: =sum(E5:M5)+sum(O5:T5)+sum(V5:AA5)+sum(AC5:AH5) -> 27 | F5: 1 | I5: 3 | J5: 2 | K5: 2 | L5: 2 | N5: =sum(H5:M5) -> 9 | P5: 3 | R5: 1 | U5: =sum(O5:T5) -> 4 | W5: 2 | X5: 3 | Y5: 2 | Z5: 2 | AB5: =sum(V5:AA5) -> 9 | AC5: 0 | AD5: 1 | AE5: 0 | AF5: 3 | AG5: 0 | AI5: =sum(AC5:AH5) -> 4
A6: 目標アポ数 | B6: =B5/B9 -> 56.410256 | C6: 出席率 | D6: =E6+F6+sum(H6:M6)+sum(O6:T6)+sum(V6:AA6)+sum(AC6:AH6) -> 0 | N6: =N5/N7 -> 0.81818182 | U6: =U5/U7 -> 0.8 | AB6: =AB5/AB7 -> 0.5 | AI6: =AI5/AI7 -> 0.36363636
A7: 目標コール数 | B7: =B6/B10 -> 3760.6838 | C7: 商談設定数 | D7: =sum(E7:M7)+sum(O7:T7)+sum(V7:AA7)+sum(AC7:AH7) -> 47 | E7: 0 | F7: 2 | G7: 0 | I7: 3 | J7: 2 | K7: 3 | L7: 2 | M7: 1 | N7: =sum(H7:M7) -> 11 | P7: 3 | R7: 2 | U7: =sum(O7:T7) -> 5 | W7: 4 | X7: 5 | Y7: 4 | Z7: 5 | AB7: =sum(V7:AA7) -> 18 | AC7: 3 | AD7: 2 | AE7: 1 | AF7: 3 | AG7: 2 | AI7: =sum(AC7:AH7) -> 11
A8: 目標受注率 | B8: 0.3 | C8: アポ転換率 | N8: =N9/N10 -> 0.0085348506 | U8: =U9/U10 -> 0.00089365505 | AB8: =AB9/AB10 -> 0.0083526682 | AI8: =AI9/AI10 -> 0.0067476383
A9: 目標出席率 | B9: 0.65 | C9: 現状アポ数 | D9: =sum(E9:M9)+sum(O9:T9)+sum(V9:AA9)+sum(AC9:AH9) -> 50 | E9: 4 | F9: 4 | G9: 1 | H9: 2 | I9: 1 | J9: 2 | K9: 3 | L9: 3 | M9: 1 | N9: =sum(H9:M9) -> 12 | O9: 1 | U9: =sum(O9:T9) -> 1 | V9: 3 | W9: 5 | X9: 2 | Y9: 5 | Z9: 2 | AA9: 1 | AB9: =sum(V9:AA9) -> 18 | AC9: =AC36 -> 0 | AD9: =AD36 -> 3 | AE9: =AE36 -> 2 | AF9: =AF36 -> 2 | AG9: =AG36 -> 1 | AH9: =AH36 -> 2 | AI9: =sum(AC9:AH9) -> 10
A10: 目標アポ転換率 | B10: 0.015 | C10: 現状コール数 | D10: =sum(E10:M10)+sum(O10:T10)+sum(V10:AA10)+sum(AC10:AH10) -> 6595 | E10: 141 | F10: 177 | G10: 115 | H10: 260 | I10: 204 | J10: 285 | K10: 265 | L10: 216 | M10: 176 | N10: =sum(H10:M10) -> 1406 | O10: 153 | P10: 301 | Q10: 228 | R10: 143 | T10: 294 | U10: =sum(O10:T10) -> 1119 | V10: 377 | W10: 201 | X10: 223 | Y10: 460 | Z10: 448 | AA10: 446 | AB10: =sum(V10:AA10) -> 2155 | AC10: =AC42 -> 346 | AD10: =AD42 -> 151 | AE10: =AE42 -> 63 | AF10: =AF42 -> 180 | AG10: =AG42 -> 295 | AH10: =AH42 -> 447 | AI10: =sum(AC10:AH10) -> 1482
A11: 1日の平均受注数 | C11: 現状受注率 | D11: =D4/sum(D5:D6) -> 0.2962963 | E11: 現状受注率 | N11: =N4/N5 -> 0 | O11: 現状受注率 | U11: =U4/U5 -> 1.25 | V11: 現状受注率 | AB11: =AB4/AB5 -> 0.22222222 | AC11: 現状受注率 | AI11: =AI4/AI5 -> 0.25
A12: 1日の平均消化数 | C12: 現状出席率 | D12: =sum(D5:D6)/D7 -> 0.57446809 | E12: 現状出席率 | N12: =N5/N7 -> 0.81818182 | O12: 現状出席率 | U12: =U5/U7 -> 0.8 | V12: 現状出席率 | AB12: =AB5/AB7 -> 0.5 | AC12: 現状出席率 | AI12: =AI5/AI7 -> 0.36363636
A13: 1日の平均アポ数 | C13: 現状商談転換率 | D13: =D5/D9 -> 0.54 | E13: 現状商談転換率 | N13: =N5/N9 -> 0.75 | O13: 現状商談転換率 | U13: =U5/U9 -> 4 | V13: 現状商談転換率 | AB13: =AB5/AB9 -> 0.5 | AC13: 現状商談転換率 | AI13: =AI5/AI9 -> 0.4
A14: 1日の平均コール数 | C14: 現状アポ転換率 | D14: =D9/D10 -> 0.0075815011 | E14: 現状アポ転換率 | N14: =N9/N10 -> 0.0085348506 | O14: 現状アポ転換率 | U14: =U9/U10 -> 0.00089365505 | V14: 現状アポ転換率 | AB14: =AB9/AB10 -> 0.0083526682 | AC14: 現状アポ転換率 | AI14: =AI9/AI10 -> 0.0067476383
A16: ハウスクリーニング | C16: 受注数 | N16: =sum(H16:M16) -> 0 | U16: =sum(O16:T16) -> 0 | AB16: =sum(V16:AA16) -> 0 | AI16: =sum(AC16:AH16) -> 0
A17: 受注率 | C17: 商談設定数 | N17: =sum(H17:M17) -> 0 | U17: =sum(O17:T17) -> 0 | AB17: =sum(V17:AA17) -> 0 | AI17: =sum(AC17:AH17) -> 0
A18: 出席率 | C18: アポ数 | N18: =sum(H18:M18) -> 0 | U18: =sum(O18:T18) -> 0 | AB18: =sum(V18:AA18) -> 0 | AI18: =sum(AC18:AH18) -> 0
A20: 不用品回収 | C20: 受注数 | N20: =sum(H20:M20) -> 0 | U20: =sum(O20:T20) -> 0 | AB20: =sum(V20:AA20) -> 0 | AI20: =sum(AC20:AH20) -> 0
A21: 受注率 | C21: 商談設定数 | N21: =sum(H21:M21) -> 0 | U21: =sum(O21:T21) -> 0 | AB21: =sum(V21:AA21) -> 0 | AI21: =sum(AC21:AH21) -> 0
A22: 出席率 | C22: アポ数 | N22: =sum(H22:M22) -> 0 | U22: =sum(O22:T22) -> 0 | AB22: =sum(V22:AA22) -> 0 | AI22: =sum(AC22:AH22) -> 0
A24: １時間あたりのコール数 | E24: =E42/E48 -> #DIV/0! | F24: =F42/F48 -> #DIV/0! | G24: =G42/G48 -> #DIV/0! | H24: =H42/H48 -> #DIV/0! | I24: =I42/I48 -> #DIV/0! | J24: =J42/J48 -> #DIV/0! | K24: =K42/K48 -> #DIV/0! | L24: =L42/L48 -> #DIV/0! | ... AI24: =AI42/AI48 -> #DIV/0!
A25: 縞谷 | E25: =E43/E49 -> #DIV/0! | F25: =F43/F49 -> #DIV/0! | G25: =G43/G49 -> #DIV/0! | H25: =H43/H49 -> #DIV/0! | I25: =I43/I49 -> #DIV/0! | J25: =J43/J49 -> #DIV/0! | K25: =K43/K49 -> #DIV/0! | L25: =L43/L49 -> #DIV/0! | ... AI25: =AI43/AI49 -> #DIV/0!
A26: 前川 | E26: =E44/E50 -> #DIV/0! | F26: =F44/F50 -> #DIV/0! | G26: =G44/G50 -> #DIV/0! | H26: =H44/H50 -> #DIV/0! | I26: =I44/I50 -> #DIV/0! | J26: =J44/J50 -> #DIV/0! | K26: =K44/K50 -> #DIV/0! | L26: =L44/L50 -> #DIV/0! | ... AI26: =AI44/AI50 -> #DIV/0!
A27: 高原 | E27: =E45/E51 -> #DIV/0! | F27: =F45/F51 -> #DIV/0! | G27: =G45/G51 -> #DIV/0! | H27: =H45/H51 -> #DIV/0! | I27: =I45/I51 -> #DIV/0! | J27: =J45/J51 -> #DIV/0! | K27: =K45/K51 -> #DIV/0! | L27: =L45/L51 -> #DIV/0! | ... AI27: =AI45/AI51 -> #DIV/0!
A28: 魚井 | E28: =E46/E52 -> #DIV/0! | F28: =F46/F52 -> #DIV/0! | G28: =G46/G52 -> #DIV/0! | H28: =H46/H52 -> #DIV/0! | I28: =I46/I52 -> #DIV/0! | J28: =J46/J52 -> #DIV/0! | K28: =K46/K52 -> #DIV/0! | L28: =L46/L52 -> #DIV/0! | ... AI28: =AI46/AI52 -> #DIV/0!
A30: アポ転換率 | E30: =E36/E42 -> #DIV/0! | F30: =F36/F42 -> #DIV/0! | G30: =G36/G42 -> #DIV/0! | H30: =H36/H42 -> #DIV/0! | I30: =I36/I42 -> #DIV/0! | J30: =J36/J42 -> #DIV/0! | K30: =K36/K42 -> #DIV/0! | L30: =L36/L42 -> #DIV/0! | ... AI30: =AI36/AI42 -> #DIV/0!
A31: 縞谷 | E31: =E37/E43 -> #DIV/0! | F31: =F37/F43 -> #DIV/0! | G31: =G37/G43 -> #DIV/0! | H31: =H37/H43 -> #DIV/0! | I31: =I37/I43 -> #DIV/0! | J31: =J37/J43 -> #DIV/0! | K31: =K37/K43 -> #DIV/0! | L31: =L37/L43 -> #DIV/0! | ... AI31: =AI37/AI43 -> #DIV/0!
A32: 前川 | E32: =E38/E44 -> #DIV/0! | F32: =F38/F44 -> #DIV/0! | G32: =G38/G44 -> #DIV/0! | H32: =H38/H44 -> #DIV/0! | I32: =I38/I44 -> #DIV/0! | J32: =J38/J44 -> #DIV/0! | K32: =K38/K44 -> #DIV/0! | L32: =L38/L44 -> #DIV/0! | ... AI32: =AI38/AI44 -> #DIV/0!
A33: 高原 | E33: =E39/E45 -> #DIV/0! | F33: =F39/F45 -> #DIV/0! | G33: =G39/G45 -> #DIV/0! | H33: =H39/H45 -> #DIV/0! | I33: =I39/I45 -> #DIV/0! | J33: =J39/J45 -> #DIV/0! | K33: =K39/K45 -> #DIV/0! | L33: =L39/L45 -> #DIV/0! | ... AI33: =AI39/AI45 -> #DIV/0!
A34: 魚井 | E34: =E40/E46 -> #DIV/0! | F34: =F40/F46 -> #DIV/0! | G34: =G40/G46 -> #DIV/0! | H34: =H40/H46 -> #DIV/0! | I34: =I40/I46 -> #DIV/0! | J34: =J40/J46 -> #DIV/0! | K34: =K40/K46 -> #DIV/0! | L34: =L40/L46 -> #DIV/0! | ... AI34: =AI40/AI46 -> #DIV/0!
A36: 総アポ数 | E36: =sum(E37:E40) -> 0 | F36: =sum(F37:F40) -> 0 | G36: =sum(G37:G40) -> 0 | H36: =sum(H37:H40) -> 0 | I36: =sum(I37:I40) -> 0 | J36: =sum(J37:J40) -> 0 | K36: =sum(K37:K40) -> 0 | L36: =sum(L37:L40) -> 0 | ... AI36: =sum(AI37:AI40) -> 0
A37: 縞谷
A38: 前川 | V38: 2 | W38: 1 | X38: 1 | Y38: 1 | Z38: 0 | AA38: 1 | AC38: 0 | AD38: 0 | AE38: 1 | AF38: 1 | AG38: 0 | AH38: 0
A39: 高原 | V39: 1 | W39: 4 | X39: 1 | Y39: 1 | Z39: 1 | AA39: 0 | AC39: 0 | AD39: 2 | AE39: 0 | AF39: 0 | AG39: 1 | AH39: 1
A40: 魚井 | Y40: 3 | Z40: 1 | AA40: 0 | AC40: 0 | AD40: 1 | AE40: 1 | AF40: 1 | AG40: 0 | AH40: 1
A42: 総コール数 | E42: =sum(E43:E46) -> 0 | F42: =sum(F43:F46) -> 0 | G42: =sum(G43:G46) -> 0 | H42: =sum(H43:H46) -> 0 | I42: =sum(I43:I46) -> 0 | J42: =sum(J43:J46) -> 0 | K42: =sum(K43:K46) -> 0 | L42: =sum(L43:L46) -> 0 | ... AI42: =sum(AI43:AI46) -> 0
A43: 縞谷
A44: 前川 | V44: 110 | W44: 100 | X44: 61 | Y44: 111 | Z44: 111 | AA44: 86 | AC44: 54 | AD44: 55 | AE44: 27 | AF44: 40 | AG44: 0 | AH44: 129
A45: 高原 | V45: 177 | W45: 160 | X45: 163 | Y45: 165 | Z45: 165 | AA45: 175 | AC45: 151 | AD45: 35 | AE45: 0 | AF45: 0 | AG45: 169 | AH45: 164
A46: 魚井 | Y46: 140 | Z46: 165 | AA46: 185 | AC46: 141 | AD46: 61 | AE46: 36 | AF46: 140 | AG46: 126 | AH46: 154
A48: 総架電時間 | E48: =sum(E49:E52) -> 0 | F48: =sum(F49:F52) -> 0 | G48: =sum(G49:G52) -> 0 | H48: =sum(H49:H52) -> 0 | I48: =sum(I49:I52) -> 0 | J48: =sum(J49:J52) -> 0 | K48: =sum(K49:K52) -> 0 | L48: =sum(L49:L52) -> 0 | ... AI48: =sum(AI49:AI52) -> 0
A49: 縞谷
A50: 前川 | V50: 6.5 | W50: 5.5 | X50: 3 | Y50: 7 | Z50: 5.5 | AA50: 5 | AC50: 2.5 | AD50: 2.5 | AE50: 2 | AF50: 2.5 | AG50: 0 | AH50: 6
A51: 高原 | V51: 8 | W51: 8 | X51: 8 | Y51: 8 | Z51: 8 | AA51: 8 | AC51: 7.5 | AD51: 2.5 | AE51: 0 | AF51: 0 | AG51: 8 | AH51: 8
A52: 魚井 | Y52: 8 | Z52: 8 | AA52: 8 | AC52: 7.5 | AD52: 3.5 | AE52: 3 | AF52: 7 | AG52: 7 | AH52: 8

Sheet 【9月】月間進捗管理シート
B1: 計画値 | D1: 現状 | E1: 月 | F1: 火 | G1: 水 | H1: 木 | I1: 金 | J1: 土 | K1: 日 | L1: 月 | M1: 火 | N1: 水 | O1: 木 | P1: 金 | Q1: 土 | R1: 日 | S1: 月 | T1: 火 | U1: 水 | V1: 木 | W1: 金 | X1: 土 | Y1: 日 | Z1: 月 | AA1: 火 | AB1: 水 | AC1: 木 | AD1: 金 | AE1: 土 | AF1: 日 | AG1: 月 | AH1: 火
E2: 45901 | F2: 45902 | G2: 45903 | H2: 45904 | I2: 45905 | J2: 45906 | K2: 45907 | L2: 45908 | M2: 45909 | N2: 45910 | O2: 45911 | P2: 45912 | Q2: 45913 | R2: 45914 | S2: 45915 | T2: 45916 | U2: 45917 | V2: 45918 | W2: 45919 | X2: 45920 | Y2: 45921 | Z2: 45922 | AA2: 45923 | AB2: 45924 | AC2: 45925 | AD2: 45926 | AE2: 45927 | AF2: 45928 | AG2: 45929 | AH2: 45930
A3: 売上目標 | B3: 2600000 | C3: 現状売上 | D3: =sum(E3:J3)+sum(L3:Q3)+sum(S3:X3)+sum(Z3:AE3)+SUM(AG3:AH3) -> 2180000 | E3: =E16+E23 -> 400000 | F3: =F16+F23 -> 0 | G3: =G16+G23 -> 0 | H3: =H16+H23 -> 0 | I3: =I16+I23 -> 235000 | J3: =J16+J23 -> 0 | K3: =sum(E3:J3) -> 635000 | L3: =L16+L23 -> 0 | M3: =M16+M23 -> 0 | N3: =N16+N23 -> 0 | O3: =O16+O23 -> 235000 | P3: =P16+P23 -> 235000 | Q3: =Q16+Q23 -> 0 | R3: =sum(L3:Q3) -> 470000 | S3: =S16+S23 -> 0 | T3: =T16+T23 -> 235000 | U3: =U16+U23 -> 0 | V3: =V16+V23 -> 0 | W3: =W16+W23 -> 200000 | X3: =X16+X23 -> 0 | Y3: =sum(S3:X3) -> 435000 | Z3: =Z16+Z23 -> 0 | AA3: =AA16+AA23 -> 220000 | AB3: =AB16+AB23 -> 0 | AC3: =AC16+AC23 -> 0 | AD3: =AD16+AD23 -> 0 | AE3: =AE16+AE23 -> 0 | AF3: =sum(Z3:AE3) -> 220000 | AG3: =AG16+AG23 -> 120000 | AH3: =AH16+AH23 -> 300000
A4: 目標受注数 | B4: 13 | C4: 現状受注数 | D4: =sum(E4:J4)+sum(L4:Q4)+sum(S4:X4)+sum(Z4:AE4)+sum(AG4:AH4) -> 10 | E4: =E17+E24 -> 2 | F4: =F17+F24 -> 0 | G4: =G17+G24 -> 0 | H4: =H17+H24 -> 0 | I4: =I17+I24 -> 1 | J4: =J17+J24 -> 0 | K4: =sum(E4:J4) -> 3 | L4: =L17+L24 -> 0 | M4: =M17+M24 -> 0 | N4: =N17+N24 -> 0 | O4: =O17+O24 -> 1 | P4: =P17+P24 -> 1 | Q4: =Q17+Q24 -> 0 | R4: =sum(L4:Q4) -> 2 | S4: =S17+S24 -> 0 | T4: =T17+T24 -> 1 | U4: =U17+U24 -> 0 | V4: =V17+V24 -> 0 | W4: =W17+W24 -> 0 | X4: =X17+X24 -> 0 | Y4: =sum(S4:X4) -> 1 | Z4: =Z17+Z24 -> 0 | AA4: =AA17+AA24 -> 1 | AB4: =AB17+AB24 -> 0 | AC4: =AC17+AC24 -> 0 | AD4: =AD17+AD24 -> 0 | AE4: =AE17+AE24 -> 0 | AF4: =sum(Z4:AE4) -> 1 | AG4: =AG17+AG24 -> 1 | AH4: =AH17+AH24 -> 2
A5: 目標有効商談数 | B5: =B4/B8 -> 43.333333 | C5: 現状有効商談数 | D5: =sum(E5:J5)+sum(L5:Q5)+sum(S5:X5)+sum(Z5:AE5)+sum(AG5:AH5) -> 36 | E5: =E18+E25 -> 2 | F5: =F18+F25 -> 0 | G5: =G18+G25 -> 2 | H5: =H18+H25 -> 3 | I5: =I18+I25 -> 2 | J5: =J18+J25 -> 0 | K5: =sum(E5:J5) -> 9 | L5: =L18+L25 -> 0 | M5: =M18+M25 -> 1 | N5: =N18+N25 -> 2 | O5: =O18+O25 -> 1 | P5: =P18+P25 -> 1 | Q5: =Q18+Q25 -> 1 | R5: =sum(L5:Q5) -> 6 | S5: =S18+S25 -> 1 | T5: =T18+T25 -> 2 | U5: =U18+U25 -> 0 | V5: =V18+V25 -> 1 | W5: =W18+W25 -> 1 | X5: =X18+X25 -> 2 | Y5: =sum(S5:X5) -> 7 | Z5: =Z18+Z25 -> 1 | AA5: =AA18+AA25 -> 2 | AB5: =AB18+AB25 -> 0 | AC5: =AC18+AC25 -> 2 | AD5: =AD18+AD25 -> 2 | AE5: =AE18+AE25 -> 1 | AF5: =sum(Z5:AE5) -> 8 | AG5: =AG18+AG25 -> 2 | AH5: =AH18+AH25 -> 4
A6: 目標アポ数 | B6: =B5/B9 -> 66.666667 | E6: 出席率 | K6: =K5/K7 -> 0.64285714 | L6: 出席率 | R6: =R5/R7 -> 0.35294118 | S6: 出席率 | Y6: =Y5/Y7 -> 0.41176471 | Z6: 出席率 | AF6: =AF5/AF7 -> 0.57142857
A7: 目標コール数 | B7: =B6/B10 -> 8333.3333 | C7: 商談設定数 | D7: =sum(E7:J7)+sum(L7:Q7)+sum(S7:X7)+sum(Z7:AE7)+sum(AG7:AH7) -> 75 | E7: =E19+E26 -> 4 | F7: =F19+F26 -> 2 | G7: =G19+G26 -> 2 | H7: =H19+H26 -> 3 | I7: =I19+I26 -> 3 | J7: =J19+J26 -> 0 | K7: =sum(E7:J7) -> 14 | L7: =L19+L26 -> 1 | M7: =M19+M26 -> 2 | N7: =N19+N26 -> 4 | O7: =O19+O26 -> 3 | P7: =P19+P26 -> 4 | Q7: =Q19+Q26 -> 3 | R7: =sum(L7:Q7) -> 17 | S7: =S19+S26 -> 1 | T7: =T19+T26 -> 5 | U7: =U19+U26 -> 3 | V7: =V19+V26 -> 4 | W7: =W19+W26 -> 2 | X7: =X19+X26 -> 2 | Y7: =sum(S7:X7) -> 17 | Z7: =Z19+Z26 -> 3 | AA7: =AA19+AA26 -> 2 | AB7: =AB19+AB26 -> 1 | AC7: =AC19+AC26 -> 3 | AD7: =AD19+AD26 -> 3 | AE7: =AE19+AE26 -> 2 | AF7: =sum(Z7:AE7) -> 14 | AG7: =AG19+AG26 -> 4 | AH7: =AH19+AH26 -> 9
A8: 目標受注率 | B8: 0.3 | E8: アポ転換率 | K8: =K9/K10 -> 0.0053495007 | L8: アポ転換率 | R8: =R9/R10 -> 0.0089507708 | S8: アポ転換率 | Y8: =Y9/Y10 -> 0.0075987842 | Z8: アポ転換率 | AF8: =AF9/AF10 -> 0.0032711809
A9: 目標出席率 | B9: 0.65 | C9: 現状アポ数 | D9: =sum(E9:J9)+sum(L9:Q9)+sum(S9:X9)+sum(Z9:AE9)+sum(AG9:AH9) -> 62 | E9: =E54 -> 2 | F9: =F54 -> 2 | G9: =G54 -> 5 | H9: =H54 -> 1 | I9: =I54 -> 3 | J9: =J54 -> 2 | K9: =sum(E9:J9) -> 15 | L9: =L54 -> 2 | M9: =M54 -> 2 | N9: =N54 -> 3 | O9: =O54 -> 5 | P9: =P54 -> 3 | Q9: =Q54 -> 3 | R9: =sum(L9:Q9) -> 18 | S9: =S54 -> 4 | T9: =T54 -> 0 | U9: =U54 -> 3 | V9: =V54 -> 1 | W9: =W54 -> 1 | X9: =X54 -> 1 | Y9: =sum(S9:X9) -> 10 | Z9: =Z54 -> 1 | AA9: =AA54 -> 1 | AB9: =AB54 -> 1 | AC9: =AC54 -> 1 | AD9: =AD54 -> 4 | AE9: =AE54 -> 2 | AF9: =sum(Z9:AE9) -> 10 | AG9: =AG54 -> 7 | AH9: =AH54 -> 2
A10: 目標アポ転換率 | B10: 0.008 | C10: 現状コール数 | D10: =sum(E10:J10)+sum(L10:Q10)+sum(S10:X10)+sum(Z10:AE10)+sum(AG10:AH10) -> 10323 | E10: =E61 -> 393 | F10: =F61 -> 418 | G10: =G61 -> 517 | H10: =H61 -> 568 | I10: =I61 -> 441 | J10: =J61 -> 467 | K10: =sum(E10:J10) -> 2804 | L10: =L61 -> 398 | M10: =M61 -> 420 | N10: =N61 -> 276 | O10: =O61 -> 286 | P10: =P61 -> 399 | Q10: =Q61 -> 232 | R10: =sum(L10:Q10) -> 2011 | S10: =S61 -> 161 | T10: =T61 -> 257 | U10: =U61 -> 365 | V10: =V61 -> 134 | W10: =W61 -> 225 | X10: =X61 -> 174 | Y10: =sum(S10:X10) -> 1316 | Z10: =Z61 -> 557 | AA10: =AA61 -> 466 | AB10: =AB61 -> 391 | AC10: =AC61 -> 647 | AD10: =AD61 -> 503 | AE10: =AE61 -> 493 | AF10: =sum(Z10:AE10) -> 3057 | AG10: =AG61 -> 608 | AH10: =AH61 -> 527
A11: 1日の平均受注数 | B11: =D4/'【第一】案件管理シート'!E2 -> 0.66666667 | C11: 現状受注率 | D11: =D4/D5 -> 0.27777778 | E11: 現状受注率 | K11: =K4/K5 -> 0.33333333 | L11: 現状受注率 | R11: =R4/R5 -> 0.33333333 | S11: 現状受注率 | Y11: =Y4/Y5 -> 0.14285714 | Z11: 現状受注率 | AF11: =AF4/AF5 -> 0.125
A12: 1日の平均消化数 | B12: =D5/'【第一】案件管理シート'!E2 -> 2.4 | C12: 現状出席率 | D12: =D5/D7 -> 0.48 | E12: 現状出席率 | K12: =K5/K7 -> 0.64285714 | L12: 現状出席率 | R12: =R5/R7 -> 0.35294118 | S12: 現状出席率 | Y12: =Y5/Y7 -> 0.41176471 | Z12: 現状出席率 | AF12: =AF5/AF7 -> 0.57142857
A13: 1日の平均アポ数 | B13: =D9/'【第一】案件管理シート'!E2 -> 4.1333333 | C13: 現状商談転換率 | D13: =D5/D9 -> 0.58064516 | E13: 現状商談転換率 | K13: =K5/K9 -> 0.6 | L13: 現状商談転換率 | R13: =R5/R9 -> 0.33333333 | S13: 現状商談転換率 | Y13: =Y5/Y9 -> 0.7 | Z13: 現状商談転換率 | AF13: =AF5/AF9 -> 0.8
A14: 1日の平均コール数 | B14: =D10/'【第一】案件管理シート'!E2 -> 688.2 | C14: 現状アポ転換率 | D14: =D9/D10 -> 0.006006006 | E14: 現状アポ転換率 | K14: =K9/K10 -> 0.0053495007 | L14: 現状アポ転換率 | R14: =R9/R10 -> 0.0089507708 | S14: 現状アポ転換率 | Y14: =Y9/Y10 -> 0.0075987842 | Z14: 現状アポ転換率 | AF14: =AF9/AF10 -> 0.0032711809
A16: ハウスクリーニング | C16: 売上 | D16: =sum(E16:J16)+sum(L16:Q16)+sum(S16:X16)+sum(Z16:AE16)+SUM(AG16:AH16) -> 1710000 | E16: 400000 | K16: =sum(E16:J16) -> 400000 | O16: 235000 | R16: =sum(L16:Q16) -> 235000 | T16: 235000 | W16: 200000 | Y16: =sum(S16:X16) -> 435000 | AA16: 220000 | AF16: =sum(Z16:AE16) -> 220000 | AG16: 120000 | AH16: 300000
C17: 受注数 | D17: =sum(E17:J17)+sum(L17:Q17)+sum(S17:X17)+sum(Z17:AE17)+sum(AG17:AH17) -> 8 | E17: 2 | K17: =sum(E17:J17) -> 2 | O17: 1 | R17: =sum(L17:Q17) -> 1 | T17: 1 | Y17: =sum(S17:X17) -> 1 | AA17: 1 | AF17: =sum(Z17:AE17) -> 1 | AG17: 1 | AH17: 2
A18: 受注率 | B18: =D17/D18 -> 0.36363636 | C18: 有効商談数 | D18: =sum(E18:J18)+sum(L18:Q18)+sum(S18:X18)+sum(Z18:AE18)+sum(AG18:AH18) -> 22 | E18: 2 | G18: 1 | I18: 1 | K18: =sum(E18:J18) -> 4 | M18: 1 | N18: 1 | P18: 1 | Q18: 1 | R18: =sum(L18:Q18) -> 4 | T18: 2 | V18: 1 | Y18: =sum(S18:X18) -> 3 | AA18: 1 | AC18: 1 | AD18: 2 | AE18: 1 | AF18: =sum(Z18:AE18) -> 5 | AG18: 2 | AH18: 4
A19: 出席率 | B19: =D18/D19 -> 0.53658537 | C19: 商談設定数 | D19: =sum(E19:J19)+sum(L19:Q19)+sum(S19:X19)+sum(Z19:AE19)+sum(AG19:AH19) -> 41 | E19: 2 | F19: 1 | G19: 1 | I19: 2 | K19: =sum(E19:J19) -> 6 | M19: 1 | N19: 1 | P19: 2 | Q19: 3 | R19: =sum(L19:Q19) -> 7 | T19: 4 | U19: 1 | V19: 2 | Y19: =sum(S19:X19) -> 7 | Z19: 2 | AA19: 1 | AC19: 2 | AD19: 3 | AE19: 2 | AF19: =sum(Z19:AE19) -> 10 | AG19: 4 | AH19: 7
E20: 現状受注率 | K20: =K17/K18 -> 0.5 | L20: 現状受注率 | R20: =R17/R18 -> 0.25 | S20: 現状受注率 | Y20: =Y17/Y18 -> 0.33333333 | Z20: 現状受注率 | AF20: =AF17/AF18 -> 0.2
E21: 現状出席率 | K21: =K18/K19 -> 0.66666667 | L21: 現状出席率 | R21: =R18/R19 -> 0.57142857 | S21: 現状出席率 | Y21: =Y18/Y19 -> 0.42857143 | Z21: 現状出席率 | AF21: =AF18/AF19 -> 0.5
A23: 不用品回収 | C23: 売上 | D23: =sum(E23:J23)+sum(L23:Q23)+sum(S23:X23)+sum(Z23:AE23)+SUM(AG23:AH23) -> 470000 | I23: 235000 | K23: =sum(E23:J23) -> 235000 | P23: 235000 | R23: =sum(L23:Q23) -> 235000 | Y23: =sum(S23:X23) -> 0 | AF23: =sum(Z23:AE23) -> 0
C24: 受注数 | D24: =sum(E24:J24)+sum(L24:Q24)+sum(S24:X24)+sum(Z24:AE24)+sum(AG24:AH24) -> 2 | I24: 1 | K24: =sum(E24:J24) -> 1 | P24: 1 | R24: =sum(L24:Q24) -> 1 | Y24: =sum(S24:X24) -> 0 | AF24: =sum(Z24:AE24) -> 0
A25: 受注率 | B25: =D24/D25 -> 0.14285714 | C25: 有効商談数 | D25: =sum(E25:J25)+sum(L25:Q25)+sum(S25:X25)+sum(Z25:AE25)+sum(AG25:AH25) -> 14 | G25: 1 | H25: 3 | I25: 1 | K25: =sum(E25:J25) -> 5 | N25: 1 | O25: 1 | R25: =sum(L25:Q25) -> 2 | S25: 1 | W25: 1 | X25: 2 | Y25: =sum(S25:X25) -> 4 | Z25: 1 | AA25: 1 | AC25: 1 | AF25: =sum(Z25:AE25) -> 3
A26: 出席率 | B26: =D25/D26 -> 0.41176471 | C26: 商談設定数 | D26: =sum(E26:J26)+sum(L26:Q26)+sum(S26:X26)+sum(Z26:AE26)+sum(AG26:AH26) -> 34 | E26: 2 | F26: 1 | G26: 1 | H26: 3 | I26: 1 | K26: =sum(E26:J26) -> 8 | L26: 1 | M26: 1 | N26: 3 | O26: 3 | P26: 2 | R26: =sum(L26:Q26) -> 10 | S26: 1 | T26: 1 | U26: 2 | V26: 2 | W26: 2 | X26: 2 | Y26: =sum(S26:X26) -> 10 | Z26: 1 | AA26: 1 | AB26: 1 | AC26: 1 | AF26: =sum(Z26:AE26) -> 4 | AH26: 2
E27: 現状受注率 | K27: =K24/K25 -> 0.2 | L27: 現状受注率 | R27: =R24/R25 -> 0.5 | S27: 現状受注率 | Y27: =Y24/Y25 -> 0 | Z27: 現状受注率 | AF27: =AF24/AF25 -> 0
E28: 現状出席率 | K28: =K25/K26 -> 0.625 | L28: 現状出席率 | R28: =R25/R26 -> 0.2 | S28: 現状出席率 | Y28: =Y25/Y26 -> 0.4 | Z28: 現状出席率 | AF28: =AF25/AF26 -> 0.75
A30: 縞谷 | C30: 売上 | D30: =sum(E30:J30)+sum(L30:Q30)+sum(S30:X30)+sum(Z30:AE30)+SUM(AG30:AH30) -> 0 | K30: =sum(E30:J30) -> 0 | R30: =sum(L30:Q30) -> 0 | Y30: =sum(S30:X30) -> 0 | AF30: =sum(Z30:AE30) -> 0
C31: 受注数 | D31: =sum(E31:J31)+sum(L31:Q31)+sum(S31:X31)+sum(Z31:AE31)+sum(AG31:AH31) -> 0 | K31: =sum(E31:J31) -> 0 | R31: =sum(L31:Q31) -> 0 | Y31: =sum(S31:X31) -> 0 | AF31: =sum(Z31:AE31) -> 0
A32: 受注率 | B32: =D31/D32 -> #DIV/0! | C32: 有効商談数 | D32: =sum(E32:J32)+sum(L32:Q32)+sum(S32:X32)+sum(Z32:AE32)+sum(AG32:AH32) -> 0 | K32: =sum(E32:J32) -> 0 | R32: =sum(L32:Q32) -> 0 | Y32: =sum(S32:X32) -> 0 | AF32: =sum(Z32:AE32) -> 0
A33: 出席率 | B33: =D32/D33 -> #DIV/0! | C33: 商談設定数 | D33: =sum(E33:J33)+sum(L33:Q33)+sum(S33:X33)+sum(Z33:AE33)+sum(AG33:AH33) -> 0 | K33: =sum(E33:J33) -> 0 | R33: =sum(L33:Q33) -> 0 | Y33: =sum(S33:X33) -> 0 | AF33: =sum(Z33:AE33) -> 0
A35: 魚井 | C35: 売上 | D35: =sum(E35:J35)+sum(L35:Q35)+sum(S35:X35)+sum(Z35:AE35)+SUM(AG35:AH35) -> 0 | K35: =sum(E35:J35) -> 0 | R35: =sum(L35:Q35) -> 0 | Y35: =sum(S35:X35) -> 0 | AF35: =sum(Z35:AE35) -> 0
C36: 受注数 | D36: =sum(E36:J36)+sum(L36:Q36)+sum(S36:X36)+sum(Z36:AE36)+sum(AG36:AH36) -> 0 | K36: =sum(E36:J36) -> 0 | R36: =sum(L36:Q36) -> 0 | Y36: =sum(S36:X36) -> 0 | AF36: =sum(Z36:AE36) -> 0
A37: 受注率 | B37: =D36/D37 -> #DIV/0! | C37: 有効商談数 | D37: =sum(E37:J37)+sum(L37:Q37)+sum(S37:X37)+sum(Z37:AE37)+sum(AG37:AH37) -> 0 | K37: =sum(E37:J37) -> 0 | R37: =sum(L37:Q37) -> 0 | Y37: =sum(S37:X37) -> 0 | AF37: =sum(Z37:AE37) -> 0
A38: 出席率 | B38: =D37/D38 -> #DIV/0! | C38: 商談設定数 | D38: =sum(E38:J38)+sum(L38:Q38)+sum(S38:X38)+sum(Z38:AE38)+sum(AG38:AH38) -> 0 | K38: =sum(E38:J38) -> 0 | R38: =sum(L38:Q38) -> 0 | Y38: =sum(S38:X38) -> 0 | AF38: =sum(Z38:AE38) -> 0
A40: １時間あたりのコール数 | E40: =E61/E68 -> 18.714286 | F40: =F61/F68 -> 19.904762 | G40: =G61/G68 -> 19.148148 | H40: =H61/H68 -> 20.285714 | I40: =I61/I68 -> 18 | J40: =J61/J68 -> 21.227273 | K40: =sum(E40:J40)/6 -> 19.546697 | L40: =L61/L68 -> 18.090909 | M40: =M61/M68 -> 16.153846 | N40: =N61/N68 -> 15.333333 | O40: =O61/O68 -> 14.481013 | P40: =P61/P68 -> 17.733333 | Q40: =Q61/Q68 -> 16 | R40: =sum(L40:Q40)/6 -> 16.298739 | S40: =S61/S68 -> 15.333333 | T40: =T61/T68 -> 17.133333 | U40: =U61/U68 -> 20.277778 | V40: =V61/V68 -> 14.888889 | W40: =W61/W68 -> 18.75 | X40: =X61/X68 -> 17.4 | Y40: =sum(S40:X40)/6 -> 17.297222 | Z40: =Z61/Z68 -> 22.734694 | AA40: =AA61/AA68 -> 31.066667 | AB40: =AB61/AB68 -> 22.342857 | AC40: =AC61/AC68 -> 23.107143 | AD40: =AD61/AD68 -> 19.72549 | AE40: =AE61/AE68 -> 20.541667 | AF40: =sum(Z40:AE40)/6 -> 23.253086 | AG40: =AG61/AG68 -> 19.301587 | AH40: =AH61/AH68 -> 16.730159
A41: 縞谷 | D41: =D62/D69 -> 23.333333 | K41: =sum(E41:J41)/6 -> 0 | R41: =sum(L41:Q41)/6 -> 0 | Y41: =sum(S41:X41)/6 -> 0 | AB41: =AB62/AB69 -> 23.333333 | AF41: =sum(Z41:AE41)/6 -> 3.8888889
A42: 前川 | D42: =D63/D70 -> 22.647619 | E42: =E63/E70 -> 19.571429 | F42: =F63/F70 -> 22.5 | G42: =G63/G70 -> 21 | H42: =H63/H70 -> 22.833333 | I42: =I63/I70 -> 17.714286 | J42: =J63/J70 -> 20.285714 | K42: =sum(E42:J42)/6 -> 20.650794 | L42: =L63/L70 -> 24.666667 | M42: =M63/M70 -> 24.6 | N42: =N63/N70 -> 23.6 | R42: =sum(L42:Q42)/6 -> 12.144444 | Y42: =sum(S42:X42)/6 -> 0 | Z42: =Z63/Z70 -> 28.222222 | AA42: =AA63/AA70 -> 28 | AB42: =AB63/AB70 -> 24.125 | AC42: =AC63/AC70 -> 24.375 | AD42: =AD63/AD70 -> 25.142857 | AF42: =sum(Z42:AE42)/6 -> 21.64418 | AG42: =AG63/AG70 -> 20.625 | AH42: =AH63/AH70 -> 19.375
A43: 高原 | D43: =D64/D71 -> 18.816901 | E43: =E64/E71 -> 16 | F43: =F64/F71 -> 21.285714 | G43: =G64/G71 -> 21.142857 | H43: =H64/H71 -> 24.266667 | I43: =I64/I71 -> 15.285714 | J43: =J64/J71 -> 23.571429 | K43: =sum(E43:J43)/6 -> 20.25873 | L43: =L64/L71 -> 14.857143 | M43: =M64/M71 -> 14.285714 | N43: =N64/N71 -> 14.6 | O43: =O64/O71 -> 15.5 | P43: =P64/P71 -> 18.666667 | Q43: =Q64/Q71 -> 16.933333 | R43: =sum(L43:Q43)/6 -> 15.807143 | S43: =S64/S71 -> 13.2 | T43: =T64/T71 -> 17.8 | U43: =U64/U71 -> 22.857143 | V43: =V64/V71 -> 8.5 | W43: =W64/W71 -> 20 | X43: =X64/X71 -> 20.333333 | Y43: =sum(S43:X43)/6 -> 17.115079 | Z43: =Z64/Z71 -> 20 | AA43: =AA64/AA71 -> 20.285714 | AB43: =AB64/AB71 -> 20.375 | AC43: =AC64/AC71 -> 24.571429 | AD43: =AD64/AD71 -> 21 | AF43: =sum(Z43:AE43)/6 -> 17.705357 | AG43: =AG64/AG71 -> 18.875 | AH43: =AH64/AH71 -> 15.75
A44: 魚井 | D44: =D65/D72 -> 18.599665 | E44: =E65/E72 -> 20 | F44: =F65/F72 -> 18.166667 | G44: =G65/G72 -> 20 | H44: =H65/H72 -> 20.133333 | I44: =I65/I72 -> 20.142857 | J44: =J65/J72 -> 20 | K44: =sum(E44:J44)/6 -> 19.740476 | L44: =L65/L72 -> 16 | M44: =M65/M72 -> 15.666667 | O44: =O65/O72 -> 16.148148 | P44: =P65/P72 -> 21.333333 | Q44: =Q65/Q72 -> 15 | R44: =sum(L44:Q44)/6 -> 14.024691 | S44: =S65/S72 -> 17.272727 | T44: =T66/T72 -> 20.666667 | U44: =U65/U72 -> 20 | V44: =V65/V72 -> 20 | W44: =W65/W72 -> 17 | X44: =X65/X72 -> 13 | Y44: =sum(S44:X44)/6 -> 17.989899 | Z44: =Z65/Z72 -> 21.666667 | AA44: =AA65/AA72 -> 12.5 | AC44: =AC65/AC72 -> 22.833333 | AD44: =AD65/AD72 -> 22 | AF44: =sum(Z44:AE44)/6 -> 13.166667 | AG44: =AG65/AG72 -> 19 | AH44: =AH65/AH72 -> 14.375
A45: 長島 | D45: =D66/D73 -> 16.162162 | F45: =F66/F73 -> 12.5 | G45: =G66/G73 -> 14.857143 | H45: =H66/H73 -> 14 | I45: =I66/I73 -> 18.714286 | K45: =sum(E45:J45)/6 -> 10.011905 | L45: 20 | M45: =M66/M73 -> 12.875 | N45: =N66/N73 -> 10.625 | O45: =O66/O73 -> 12 | P45: =P66/P73 -> 13.2 | R45: =sum(L45:Q45)/6 -> 11.45 | U45: =U66/U73 -> 16.25 | Y45: =sum(S45:X45)/6 -> 2.7083333 | Z45: =Z66/Z73 -> 23.333333 | AC45: =AC66/AC73 -> 20.428571 | AD45: =AD66/AD73 -> 11.714286 | AF45: =sum(Z45:AE45)/6 -> 9.2460317 | AG45: =AG66/AG73 -> 18.666667 | AH45: =AH66/AH73 -> 17.466667
A47: アポ転換率 | E47: =E54/E61 -> 0.0050890585 | F47: =F54/F61 -> 0.004784689 | G47: =G54/G61 -> 0.0096711799 | H47: =H54/H61 -> 0.0017605634 | I47: =I54/I61 -> 0.0068027211 | J47: =J54/J61 -> 0.0042826552 | K47: =sum(E47:J47)/6 -> 0.0053984779 | L47: =L54/L61 -> 0.0050251256 | M47: =M54/M61 -> 0.0047619048 | N47: =N54/N61 -> 0.010869565 | O47: =O54/O61 -> 0.017482517 | P47: =P54/P61 -> 0.007518797 | Q47: =Q54/Q61 -> 0.012931034 | R47: =sum(L47:Q47)/6 -> 0.0097648241 | S47: =S54/S61 -> 0.024844721 | T47: =T54/T61 -> 0 | U47: =U54/U61 -> 0.0082191781 | V47: =V54/V61 -> 0.0074626866 | W47: =W54/W61 -> 0.0044444444 | X47: =X54/X61 -> 0.0057471264 | Y47: =sum(S47:X47)/6 -> 0.008453026 | Z47: =Z54/Z61 -> 0.0017953321 | AA47: =AA54/AA61 -> 0.0021459227 | AB47: =AB54/AB61 -> 0.0025575448 | AC47: =AC54/AC61 -> 0.0015455951 | AD47: =AD54/AD61 -> 0.0079522863 | AE47: =AE54/AE61 -> 0.0040567951 | AF47: =sum(Z47:AE47)/6 -> 0.003342246 | AG47: =AG54/AG61 -> 0.011513158 | AH47: =AH54/AH61 -> 0.0037950664
A48: 縞谷 | D48: =D55/D62 -> 0 | K48: =sum(E48:J48)/6 -> 0 | R48: =sum(L48:Q48)/6 -> 0 | Y48: =sum(S48:X48)/6 -> 0 | AB48: =AB55/AB62 -> 0 | AF48: =sum(Z48:AE48)/6 -> 0
A49: 前川 | D49: =D56/D63 -> 0.0063078217 | E49: =E56/E63 -> 0.0072992701 | F49: =F56/F63 -> 0 | G49: =G56/G63 -> 0.019047619 | H49: =H56/H63 -> 0 | I49: =I56/I63 -> 0.016129032 | J49: =J56/J63 -> 0 | K49: =sum(E49:J49)/6 -> 0.0070793202 | L49: =L56/L63 -> 0.013513514 | M49: =M56/M63 -> 0.0081300813 | N49: =N56/N63 -> 0.0084745763 | R49: =sum(L49:Q49)/6 -> 0.0050196952 | Y49: =sum(S49:X49)/6 -> 0 | Z49: =Z56/Z63 -> 0.0078740157 | AA49: =AA56/AA63 -> 0 | AB49: =AB56/AB63 -> 0.0051813471 | AC49: =AC56/AC63 -> 0.0051282051 | AD49: =AD56/AD63 -> 0.011363636 | AF49: =sum(Z49:AE49)/6 -> 0.0049245341 | AG49: =AG56/AG63 -> 0.018181818 | AH49: =AH56/AH63 -> 0
A50: 高原 | D50: =D57/D64 -> 0.0041916168 | E50: =E57/E64 -> 0 | F50: =F57/F64 -> 0.0067114094 | G50: =G57/G64 -> 0.0067567568 | H50: =H57/H64 -> 0 | I50: =I57/I64 -> 0 | J50: =J57/J64 -> 0 | K50: =sum(E50:J50)/6 -> 0.0022446944 | L50: =L57/L64 -> 0.0096153846 | M50: =M57/M64 -> 0 | N50: =N57/N64 -> 0 | O50: =O57/O64 -> 0.010752688 | P50: =P57/P64 -> 0.0071428571 | Q50: =Q57/Q64 -> 0.015748031 | R50: =sum(L50:Q50)/6 -> 0.0072098269 | S50: =S57/S64 -> 0.03030303 | T50: =T57/T64 -> 0 | U50: =U57/U64 -> 0.00625 | V50: =V57/V64 -> 0 | W50: =W57/W64 -> 0 | X50: =X57/X64 -> 0 | Y50: =sum(S50:X50)/6 -> 0.0060921717 | Z50: =Z57/Z64 -> 0 | AA50: =AA57/AA64 -> 0.0070422535 | AB50: =AB57/AB64 -> 0 | AC50: =AC57/AC64 -> 0 | AD50: =AD57/AD64 -> 0 | AF50: =sum(Z50:AE50)/6 -> 0.0011737089 | AG50: =AG57/AG64 -> 0.013245033 | AH50: =AH57/AH64 -> 0
A51: 魚井 | D51: =D58/D65 -> 0.0068443804 | E51: =E58/E65 -> 0 | F51: =F58/F65 -> 0 | G51: =G58/G65 -> 0.0125 | H51: =H58/H65 -> 0 | I51: =I58/I65 -> 0.0070921986 | J51: =J58/J65 -> 0.0125 | K51: =sum(E51:J51)/6 -> 0.0053486998 | L51: =L58/L65 -> 0 | M51: =M58/M65 -> 0 | O51: =O58/O65 -> 0.027522936 | P51: =P58/P65 -> 0.00625 | Q51: =Q58/Q65 -> 0.0095238095 | R51: =sum(L51:Q51)/6 -> 0.0072161242 | S51: =S58/S65 -> 0.021052632 | T51: =T58/T66 -> 0 | U51: =U58/U65 -> 0.0071428571 | V51: =V58/V65 -> 0.01 | W51: =W58/W65 -> 0.011764706 | X51: =X58/X65 -> 0.019230769 | Y51: =sum(S51:X51)/6 -> 0.011531827 | Z51: =Z58/Z65 -> 0 | AA51: =AA58/AA65 -> 0 | AC51: =AC58/AC65 -> 0 | AD51: =AD58/AD65 -> 0 | AF51: =sum(Z51:AE51)/6 -> 0 | AG51: =AG58/AG65 -> 0.013157895 | AH51: =AH58/AH65 -> 0
A52: 長島 | D52: =D59/D66 -> 0.0078037904 | F52: =F59/F66 -> 0.04 | G52: =G59/G66 -> 0 | H52: =H59/H66 -> 0.010204082 | I52: =I59/I66 -> 0.0076335878 | K52: =sum(E52:J52)/6 -> 0.0096396116 | L52: =L59/L66 -> 0 | M52: =M59/M66 -> 0.0097087379 | N52: =N59/N66 -> 0.023529412 | O52: =O59/O66 -> 0.011904762 | P52: =P59/P66 -> 0.01010101 | R52: =sum(L52:Q52)/6 -> 0.0092073203 | U52: =U59/U66 -> 0.015384615 | Y52: =sum(S52:X52)/6 -> 0.0025641026 | Z52: =Z59/Z66 -> 0 | AA52: =AA59/AA66 -> 0 | AC52: =AC59/AC66 -> 0 | AD52: =AD59/AD66 -> 0.024390244 | AF52: =sum(Z52:AE52)/6 -> 0.0040650406 | AG52: =AG59/AG66 -> 0 | AH52: =AH59/AH66 -> 0.015267176
A54: 総アポ数 | E54: =sum(E55:E59) -> 2 | F54: =sum(F55:F59) -> 2 | G54: =sum(G55:G59) -> 5 | H54: =sum(H55:H59) -> 1 | I54: =sum(I55:I59) -> 3 | J54: =sum(J55:J59) -> 2 | K54: =sum(E54:J54)/6 -> 2.5 | L54: =sum(L55:L59) -> 2 | M54: =sum(M55:M59) -> 2 | N54: =sum(N55:N59) -> 3 | O54: =sum(O55:O59) -> 5 | P54: =sum(P55:P59) -> 3 | Q54: =sum(Q55:Q59) -> 3 | R54: =sum(L54:Q54)/6 -> 3 | S54: =sum(S55:S59) -> 4 | T54: =sum(T55:T59) -> 0 | U54: =sum(U55:U59) -> 3 | V54: =sum(V55:V59) -> 1 | W54: =sum(W55:W59) -> 1 | X54: =sum(X55:X59) -> 1 | Y54: =sum(S54:X54)/6 -> 1.6666667 | Z54: =sum(Z55:Z59) -> 1 | AA54: =sum(AA55:AA59) -> 1 | AB54: =sum(AB55:AB59) -> 1 | AC54: =sum(AC55:AC59) -> 1 | AD54: =sum(AD55:AD59) -> 4 | AE54: =sum(AE55:AE59) -> 2 | AF54: =sum(Z54:AE54)/6 -> 1.6666667 | AG54: =sum(AG55:AG59) -> 7 | AH54: =sum(AH55:AH59) -> 2
A55: 縞谷 | D55: =sum(E55:J55)+sum(L55:Q55)+sum(S55:X55)+sum(Z55:AE55)+sum(AG55:AH55) -> 0 | K55: =sum(E55:J55)/6 -> 0 | R55: =sum(L55:Q55)/6 -> 0 | Y55: =sum(S55:X55)/6 -> 0 | AB55: 0 | AF55: =sum(Z55:AE55)/6 -> 0
A56: 前川 | D56: =sum(E56:J56)+sum(L56:Q56)+sum(S56:X56)+sum(Z56:AE56)+sum(AG56:AH56) -> 15 | E56: 1 | F56: 0 | G56: 2 | H56: 0 | I56: 1 | J56: 0 | K56: =sum(E56:J56)/6 -> 0.66666667 | L56: 1 | M56: 1 | N56: 1 | O56: 0 | P56: 0 | Q56: 0 | R56: =sum(L56:Q56)/6 -> 0.5 | Y56: =sum(S56:X56)/6 -> 0 | Z56: 1 | AA56: 0 | AB56: 1 | AC56: 1 | AD56: 2 | AE56: 0 | AF56: =sum(Z56:AE56)/6 -> 0.83333333 | AG56: 3 | AH56: 0
A57: 高原 | D57: =sum(E57:J57)+sum(L57:Q57)+sum(S57:X57)+sum(Z57:AE57)+sum(AG57:AH57) -> 14 | E57: 0 | F57: 1 | G57: 1 | H57: 0 | I57: 0 | J57: 0 | K57: =sum(E57:J57)/6 -> 0.33333333 | L57: 1 | M57: 0 | N57: 0 | O57: 1 | P57: 1 | Q57: 2 | R57: =sum(L57:Q57)/6 -> 0.83333333 | S57: 2 | T57: 0 | U57: 1 | V57: 0 | W57: 0 | X57: 0 | Y57: =sum(S57:X57)/6 -> 0.5 | Z57: 0 | AA57: 1 | AB57: 0 | AC57: 0 | AD57: 0 | AE57: 1 | AF57: =sum(Z57:AE57)/6 -> 0.33333333 | AG57: 2 | AH57: 0
A58: 魚井 | D58: =sum(E58:J58)+sum(L58:Q58)+sum(S58:X58)+sum(Z58:AE58)+sum(AG58:AH58) -> 19 | E58: 0 | F58: 0 | G58: 2 | H58: 0 | I58: 1 | J58: 2 | K58: =sum(E58:J58)/6 -> 0.83333333 | L58: 0 | M58: 0 | N58: 0 | O58: 3 | P58: 1 | Q58: 1 | R58: =sum(L58:Q58)/6 -> 0.83333333 | S58: 2 | T58: 0 | U58: 1 | V58: 1 | W58: 1 | X58: 1 | Y58: =sum(S58:X58)/6 -> 1 | Z58: 0 | AA58: 0 | AB58: 0 | AC58: 0 | AD58: 0 | AE58: 1 | AF58: =sum(Z58:AE58)/6 -> 0.16666667 | AG58: 2 | AH58: 0
A59: 長島 | D59: =sum(E59:J59)+sum(L59:Q59)+sum(S59:X59)+sum(Z59:AE59)+sum(AG59:AH59) -> 14 | E59: 1 | F59: 1 | G59: 0 | H59: 1 | I59: 1 | J59: 0 | K59: =sum(E59:J59)/6 -> 0.66666667 | L59: 0 | M59: 1 | N59: 2 | O59: 1 | P59: 1 | Q59: 0 | R59: =sum(L59:Q59)/6 -> 0.83333333 | S59: 0 | T59: 0 | U59: 1 | V59: 0 | W59: 0 | X59: 0 | Y59: =sum(S59:X59)/6 -> 0.16666667 | Z59: 0 | AA59: 0 | AB59: 0 | AC59: 0 | AD59: 2 | AE59: 0 | AF59: =sum(Z59:AE59)/6 -> 0.33333333 | AG59: 0 | AH59: 2
A61: 総コール数 | E61: =sum(E62:E66) -> 393 | F61: =sum(F62:F66) -> 418 | G61: =sum(G62:G66) -> 517 | H61: =sum(H62:H66) -> 568 | I61: =sum(I62:I66) -> 441 | J61: =sum(J62:J66) -> 467 | K61: =sum(E61:J61)/6 -> 467.33333 | L61: =sum(L62:L66) -> 398 | M61: =sum(M62:M66) -> 420 | N61: =sum(N62:N66) -> 276 | O61: =sum(O62:O66) -> 286 | P61: =sum(P62:P66) -> 399 | Q61: =sum(Q62:Q66) -> 232 | R61: =sum(L61:Q61)/6 -> 335.16667 | S61: =sum(S62:S66) -> 161 | T61: =sum(T62:T66) -> 257 | U61: =sum(U62:U66) -> 365 | V61: =sum(V62:V66) -> 134 | W61: =sum(W62:W66) -> 225 | X61: =sum(X62:X66) -> 174 | Y61: =sum(S61:X61)/6 -> 219.33333 | Z61: =sum(Z62:Z66) -> 557 | AA61: =sum(AA62:AA66) -> 466 | AB61: =sum(AB62:AB66) -> 391 | AC61: =sum(AC62:AC66) -> 647 | AD61: =sum(AD62:AD66) -> 503 | AE61: =sum(AE62:AE66) -> 493 | AF61: =sum(Z61:AE61)/6 -> 509.5 | AG61: =sum(AG62:AG66) -> 608 | AH61: =sum(AH62:AH66) -> 527
A62: 縞谷 | D62: =sum(E62:J62)+sum(L62:Q62)+sum(S62:X62)+sum(Z62:AE62)+sum(AG62:AH62) -> 35 | K62: =sum(E62:J62)/6 -> 0 | R62: =sum(L62:Q62)/6 -> 0 | Y62: =sum(S62:X62)/6 -> 0 | AB62: 35 | AF62: =sum(Z62:AE62)/6 -> 5.8333333
A63: 前川 | D63: =sum(E63:J63)+sum(L63:Q63)+sum(S63:X63)+sum(Z63:AE63)+sum(AG63:AH63) -> 2378 | E63: 137 | F63: 135 | G63: 105 | H63: 137 | I63: 62 | J63: 142 | K63: =sum(E63:J63)/6 -> 119.66667 | L63: 74 | M63: 123 | N63: 118 | O63: 0 | P63: 0 | Q63: 0 | R63: =sum(L63:Q63)/6 -> 52.5 | Y63: =sum(S63:X63)/6 -> 0 | Z63: 127 | AA63: 168 | AB63: 193 | AC63: 195 | AD63: 176 | AE63: 166 | AF63: =sum(Z63:AE63)/6 -> 170.83333 | AG63: 165 | AH63: 155
A64: 高原 | D64: =sum(E64:J64)+sum(L64:Q64)+sum(S64:X64)+sum(Z64:AE64)+sum(AG64:AH64) -> 3340 | E64: 96 | F64: 149 | G64: 148 | H64: 182 | I64: 107 | J64: 165 | K64: =sum(E64:J64)/6 -> 141.16667 | L64: 104 | M64: 100 | N64: 73 | O64: 93 | P64: 140 | Q64: 127 | R64: =sum(L64:Q64)/6 -> 106.16667 | S64: 66 | T64: 89 | U64: 160 | V64: 34 | W64: 140 | X64: 122 | Y64: =sum(S64:X64)/6 -> 101.83333 | Z64: 160 | AA64: 142 | AB64: 163 | AC64: 172 | AD64: 168 | AE64: 163 | AF64: =sum(Z64:AE64)/6 -> 161.33333 | AG64: 151 | AH64: 126
A65: 魚井 | D65: =sum(E65:J65)+sum(L65:Q65)+sum(S65:X65)+sum(Z65:AE65)+sum(AG65:AH65) -> 2776 | E65: 160 | F65: 109 | G65: 160 | H65: 151 | I65: 141 | J65: 160 | K65: =sum(E65:J65)/6 -> 146.83333 | L65: 80 | M65: 94 | N65: 0 | O65: 109 | P65: 160 | Q65: 105 | R65: =sum(L65:Q65)/5 -> 109.6 | S65: 95 | T65: 75 | U65: 140 | V65: 100 | W65: 85 | X65: 52 | Y65: =sum(S65:X65)/6 -> 91.166667 | Z65: 130 | AA65: 25 | AB65: 0 | AC65: 137 | AD65: 77 | AE65: 164 | AF65: =sum(Z65:AE65)/6 -> 88.833333 | AG65: 152 | AH65: 115
A66: 長島 | D66: =sum(E66:J66)+sum(L66:Q66)+sum(S66:X66)+sum(Z66:AE66)+sum(AG66:AH66) -> 1794 | E66: 0 | F66: 25 | G66: 104 | H66: 98 | I66: 131 | J66: 0 | K66: =sum(E66:J66)/6 -> 59.666667 | L66: 140 | M66: 103 | N66: 85 | O66: 84 | P66: 99 | Q66: 0 | R66: =sum(L66:Q66)/6 -> 85.166667 | S66: 0 | T66: 93 | U66: 65 | V66: 0 | W66: 0 | X66: 0 | Y66: =sum(S66:X66)/6 -> 26.333333 | Z66: 140 | AA66: 131 | AB66: 0 | AC66: 143 | AD66: 82 | AE66: 0 | AF66: =sum(Z66:AE66)/6 -> 82.666667 | AG66: 140 | AH66: 131
A68: 総架電時間 | E68: =sum(E69:E73) -> 21 | F68: =sum(F69:F73) -> 21 | G68: =sum(G69:G73) -> 27 | H68: =sum(H69:H73) -> 28 | I68: =sum(I69:I73) -> 24.5 | J68: =sum(J69:J73) -> 22 | K68: =sum(E68:J68)/6 -> 23.916667 | L68: =sum(L69:L73) -> 22 | M68: =sum(M69:M73) -> 26 | N68: =sum(N69:N73) -> 18 | O68: =sum(O69:O73) -> 19.75 | P68: =sum(P69:P73) -> 22.5 | Q68: =sum(Q69:Q73) -> 14.5 | R68: =sum(L68:Q68)/6 -> 20.458333 | S68: =sum(S69:S73) -> 10.5 | T68: =sum(T69:T73) -> 15 | U68: =sum(U69:U73) -> 18 | V68: =sum(V69:V73) -> 9 | W68: =sum(W69:W73) -> 12 | X68: =sum(X69:X73) -> 10 | Y68: =sum(S68:X68)/6 -> 12.416667 | Z68: =sum(Z69:Z73) -> 24.5 | AA68: =sum(AA69:AA72) -> 15 | AB68: =sum(AB69:AB73) -> 17.5 | AC68: =sum(AC69:AC73) -> 28 | AD68: =sum(AD69:AD73) -> 25.5 | AE68: =sum(AE69:AE73) -> 24 | AF68: =sum(Z68:AE68)/6 -> 22.416667 | AG68: =sum(AG69:AG73) -> 31.5 | AH68: =sum(AH69:AH73) -> 31.5
A69: 縞谷 | D69: =sum(E69:J69)+sum(L69:Q69)+sum(S69:X69)+sum(Z69:AE69)+sum(AG69:AH69) -> 1.5 | K69: =sum(E69:J69)/6 -> 0 | R69: =sum(L69:Q69)/6 -> 0 | Y69: =sum(S69:X69)/6 -> 0 | AB69: 1.5 | AF69: =sum(Z69:AE69)/6 -> 0.25
A70: 前川 | D70: =sum(E70:J70)+sum(L70:Q70)+sum(S70:X70)+sum(Z70:AE70)+sum(AG70:AH70) -> 105 | E70: 7 | F70: 6 | G70: 5 | H70: 6 | I70: 3.5 | J70: 7 | K70: =sum(E70:J70)/6 -> 5.75 | L70: 3 | M70: 5 | N70: 5 | O70: 0 | P70: 0 | Q70: 0 | R70: =sum(L70:Q70)/6 -> 2.1666667 | Y70: =sum(S70:X70)/6 -> 0 | Z70: 4.5 | AA70: 6 | AB70: 8 | AC70: 8 | AD70: 7 | AE70: 8 | AF70: =sum(Z70:AE70)/6 -> 6.9166667 | AG70: 8 | AH70: 8
A71: 高原 | D71: =sum(E71:J71)+sum(L71:Q71)+sum(S71:X71)+sum(Z71:AE71)+sum(AG71:AH71) -> 177.5 | E71: 6 | F71: 7 | G71: 7 | H71: 7.5 | I71: 7 | J71: 7 | K71: =sum(E71:J71)/6 -> 6.9166667 | L71: 7 | M71: 7 | N71: 5 | O71: 6 | P71: 7.5 | Q71: 7.5 | R71: =sum(L71:Q71)/6 -> 6.6666667 | S71: 5 | T71: 5 | U71: 7 | V71: 4 | W71: 7 | X71: 6 | Y71: =sum(S71:X71)/6 -> 5.6666667 | Z71: 8 | AA71: 7 | AB71: 8 | AC71: 7 | AD71: 8 | AE71: 8 | AF71: =sum(Z71:AE71)/6 -> 7.6666667 | AG71: 8 | AH71: 8
A72: 魚井 | D72: =sum(E72:J72)+sum(L72:Q72)+sum(S72:X72)+sum(Z72:AE72)+sum(AG72:AH72) -> 149.25 | E72: 8 | F72: 6 | G72: 8 | H72: 7.5 | I72: 7 | J72: 8 | K72: =sum(E72:J72)/6 -> 7.4166667 | L72: 5 | M72: 6 | N72: 0 | O72: 6.75 | P72: 7.5 | Q72: 7 | R72: =sum(L72:Q72)/6 -> 5.375 | S72: 5.5 | T72: 4.5 | U72: 7 | V72: 5 | W72: 5 | X72: 4 | Y72: =sum(S72:X72)/6 -> 5.1666667 | Z72: 6 | AA72: 2 | AB72: 0 | AC72: 6 | AD72: 3.5 | AE72: 8 | AF72: =sum(Z72:AE72)/6 -> 4.25 | AG72: 8 | AH72: 8
A73: 長島 | D73: =sum(E73:J73)+sum(L73:Q73)+sum(S73:X73)+sum(Z73:AE73)+sum(AG73:AH73) -> 111 | E73: 0 | F73: 2 | G73: 7 | H73: 7 | I73: 7 | J73: 0 | K73: =sum(E73:J73)/6 -> 3.8333333 | L73: 7 | M73: 8 | N73: 8 | O73: 7 | P73: 7.5 | Q73: 0 | R73: =sum(L73:Q73)/6 -> 6.25 | S73: 0 | T73: 5.5 | U73: 4 | V73: 0 | W73: 0 | X73: 0 | Y73: =sum(S73:X73)/6 -> 1.5833333 | Z73: 6 | AA73: 6 | AB73: 0 | AC73: 7 | AD73: 7 | AE73: 0 | AF73: =sum(Z73:AE73)/6 -> 4.3333333 | AG73: 7.5 | AH73: 7.5

Sheet 【10月】月間進捗管理シート
B1: 計画値 | D1: 現状 | E1: 水 | F1: 木 | G1: 金 | H1: 土 | I1: 日 | J1: 月 | K1: 火 | L1: 水 | M1: 木 | N1: 金 | O1: 土 | P1: 日 | Q1: 月 | R1: 火 | S1: 水 | T1: 木 | U1: 金 | V1: 土 | W1: 日 | X1: 月 | Y1: 火 | Z1: 水 | AA1: 木 | AB1: 金 | AC1: 土 | AD1: 日 | AE1: 月 | AF1: 火 | AG1: 水 | AH1: 木 | AI1: 金 | AJ1: 土
E2: 45931 | F2: 45932 | G2: 45933 | H2: 45934 | I2: 45935 | J2: 45936 | K2: 45937 | L2: 45938 | M2: 45939 | N2: 45940 | O2: 45941 | P2: 45942 | Q2: 45943 | R2: 45944 | S2: 45945 | T2: 45946 | U2: 45947 | V2: 45948 | W2: 45949 | X2: 45950 | Y2: 45951 | Z2: 45952 | AA2: 45953 | AB2: 45954 | AC2: 45955 | AD2: 45956 | AE2: 45957 | AF2: 45958 | AG2: 45959 | AH2: 45960 | AI2: 45961 | AJ2: 45962
A3: 売上目標 | B3: 1600000 | C3: 現状売上 | D3: =sum(E3:H3)+sum(J3:O3)+sum(Q3:V3)+sum(X3:AC3)+SUM(AE3:AF3) -> 0 | E3: =E16+E23+E30 -> 0 | F3: =F16+F23+F30 -> 0 | G3: =G16+G23+G30 -> 0 | H3: =H16+H23+H30 -> 0 | I3: =sum(E3:H3) -> 0 | J3: =J16+J23+J30 -> 0 | K3: =K16+K23+K30 -> 0 | L3: =L16+L23+L30 -> 0 | M3: =M16+M23+M30 -> 0 | N3: =N16+N23+N30 -> 0 | O3: =O16+O23+O30 -> 0 | P3: =sum(J3:O3) -> 0 | Q3: =Q16+Q23+Q30 -> 0 | R3: =R16+R23+R30 -> 0 | S3: =S16+S23+S30 -> 0 | T3: =T16+T23+T30 -> 0 | U3: =U16+U23+U30 -> 0 | V3: =V16+V23+V30 -> 0 | W3: =sum(Q3:V3) -> 0 | X3: =X16+X23+X30 -> 0 | Y3: =Y16+Y23+Y30 -> 0 | Z3: =Z16+Z23+Z30 -> 0 | AA3: =AA16+AA23+AA30 -> 0 | AB3: =AB16+AB23+AB30 -> 0 | AC3: =AC16+AC23+AC30 -> 0 | AD3: =sum(X3:AC3) -> 0 | AE3: =AE16+AE23+AE30 -> 0 | AF3: =AF16+AF23+AF30 -> 0 | AG3: =AG16+AG23+AG30 -> 0 | AH3: =AH16+AH23+AH30 -> 0 | AI3: =AI16+AI23+AI30 -> 0 | AJ3: =AJ16+AJ23+AJ30 -> 0
A4: 目標受注数 | B4: 8 | C4: 現状受注数 | D4: =sum(E4:H4)+sum(J4:O4)+sum(Q4:V4)+sum(X4:AC4)+sum(AE4:AF4) -> 0 | E4: =E17+E24+E31 -> 0 | F4: =F17+F24+F31 -> 0 | G4: =G17+G24+G31 -> 0 | H4: =H17+H24+H31 -> 0 | I4: =sum(E4:H4) -> 0 | J4: =J17+J24+J31 -> 0 | K4: =K17+K24+K31 -> 0 | L4: =L17+L24+L31 -> 0 | M4: =M17+M24+M31 -> 0 | N4: =N17+N24+N31 -> 0 | O4: =O17+O24+O31 -> 0 | P4: =sum(J4:O4) -> 0 | Q4: =Q17+Q24+Q31 -> 0 | R4: =R17+R24+R31 -> 0 | S4: =S17+S24+S31 -> 0 | T4: =T17+T24+T31 -> 0 | U4: =U17+U24+U31 -> 0 | V4: =V17+V24+V31 -> 0 | W4: =sum(Q4:V4) -> 0 | X4: =X17+X24+X31 -> 0 | Y4: =Y17+Y24+Y31 -> 0 | Z4: =Z17+Z24+Z31 -> 0 | AA4: =AA17+AA24+AA31 -> 0 | AB4: =AB17+AB24+AB31 -> 0 | AC4: =AC17+AC24+AC31 -> 0 | AD4: =sum(X4:AC4) -> 0 | AE4: =AE17+AE24+AE31 -> 0 | AF4: =AF17+AF24+AF31 -> 0 | AG4: =AG17+AG24+AG31 -> 0 | AH4: =AH17+AH24+AH31 -> 0 | AI4: =AI17+AI24+AI31 -> 0 | AJ4: =AJ17+AJ24+AJ31 -> 0
A5: 目標有効商談数 | B5: =B4/B8 -> 26.666667 | C5: 現状有効商談数 | D5: =sum(E5:H5)+sum(J5:O5)+sum(Q5:V5)+sum(X5:AC5)+sum(AE5:AF5) -> 6 | E5: =E18+E25+E32 -> 1 | F5: =F18+F25+F32 -> 1 | G5: =G18+G25+G32 -> 1 | H5: =H18+H25+H32 -> 0 | I5: =sum(E5:H5) -> 3 | J5: =J18+J25+J32 -> 0 | K5: =K18+K25+K32 -> 0 | L5: =L18+L25+L32 -> 0 | M5: =M18+M25+M32 -> 0 | N5: =N18+N25+N32 -> 0 | O5: =O18+O25+O32 -> 0 | P5: =sum(J5:O5) -> 0 | Q5: =Q18+Q25+Q32 -> 0 | R5: =R18+R25+R32 -> 0 | S5: =S18+S25+S32 -> 0 | T5: =T18+T25+T32 -> 0 | U5: =U18+U25+U32 -> 0 | V5: =V18+V25+V32 -> 0 | W5: =sum(Q5:V5) -> 0 | X5: =X18+X25+X32 -> 0 | Y5: =Y18+Y25+Y32 -> 1 | Z5: =Z18+Z25+Z32 -> 1 | AA5: =AA18+AA25+AA32 -> 0 | AB5: =AB18+AB25+AB32 -> 0 | AC5: =AC18+AC25+AC32 -> 0 | AD5: =sum(X5:AC5) -> 2 | AE5: =AE18+AE25+AE32 -> 0 | AF5: =AF18+AF25+AF32 -> 1 | AG5: =AG18+AG25+AG32 -> 1 | AH5: =AH18+AH25+AH32 -> 2 | AI5: =AI18+AI25+AI32 -> 1 | AJ5: =AJ18+AJ25+AJ32 -> 0
A6: 目標アポ数 | B6: =B5/B9 -> 53.333333 | E6: 出席率 | I6: =I5/I7 -> 0.3 | J6: 出席率 | P6: =P5/P7 -> 0 | Q6: 出席率 | W6: =W5/W7 -> 0 | X6: 出席率 | AD6: =AD5/AD7 -> 0.25
A7: 目標コール数 | B7: =B6/B10 -> 8888.8889 | C7: 商談設定数 | D7: =sum(E7:H7)+sum(J7:O7)+sum(Q7:V7)+sum(X7:AC7)+sum(AE7:AF7) -> 38 | E7: =E19+E26+E33 -> 4 | F7: =F19+F26+F33 -> 2 | G7: =G19+G26+G33 -> 3 | H7: =H19+H26+H33 -> 1 | I7: =sum(E7:H7) -> 10 | J7: =J19+J26+J33 -> 3 | K7: =K19+K26+K33 -> 1 | L7: =L19+L26+L33 -> 2 | M7: =M19+M26+M33 -> 1 | N7: =N19+N26+N33 -> 2 | O7: =O19+O26+O33 -> 0 | P7: =sum(J7:O7) -> 9 | Q7: =Q19+Q26+Q33 -> 0 | R7: =R19+R26+R33 -> 2 | S7: =S19+S26+S33 -> 2 | T7: =T19+T26+T33 -> 1 | U7: =U19+U26+U33 -> 2 | V7: =V19+V26+V33 -> 0 | W7: =sum(Q7:V7) -> 7 | X7: =X19+X26+X33 -> 1 | Y7: =Y19+Y26+Y33 -> 3 | Z7: =Z19+Z26+Z33 -> 1 | AA7: =AA19+AA26+AA33 -> 1 | AB7: =AB19+AB26+AB33 -> 2 | AC7: =AC19+AC26+AC33 -> 0 | AD7: =sum(X7:AC7) -> 8 | AE7: =AE19+AE26+AE33 -> 2 | AF7: =AF19+AF26+AF33 -> 2 | AG7: =AG19+AG26+AG33 -> 2 | AH7: =AH19+AH26+AH33 -> 3 | AI7: =AI19+AI26+AI33 -> 1 | AJ7: =AJ19+AJ26+AJ33 -> 0
A8: 目標受注率 | B8: 0.3 | E8: アポ転換率 | I8: =I9/I10 -> 0.0023612751 | J8: アポ転換率 | P8: =P9/P10 -> 0.0028436019 | Q8: アポ転換率 | W8: =W9/W10 -> 0.0044108381 | X8: アポ転換率 | AD8: =AD9/AD10 -> 0.0040387722
A9: 目標出席率 | B9: 0.5 | C9: 現状アポ数 | D9: =sum(E9:H9)+sum(J9:O9)+sum(Q9:V9)+sum(X9:AC9)+sum(AE9:AF9) -> 28 | E9: =E61 -> 0 | F9: =F61 -> 0 | G9: =G61 -> 1 | H9: =H61 -> 1 | I9: =sum(E9:H9) -> 2 | J9: =J61 -> 0 | K9: =K61 -> 3 | L9: =L61 -> 2 | M9: =M61 -> 1 | N9: =N61 -> 0 | O9: =O61 -> 0 | P9: =sum(J9:O9) -> 6 | Q9: =Q61 -> 0 | R9: =R61 -> 2 | S9: =S61 -> 1 | T9: =T61 -> 3 | U9: =U61 -> 0 | V9: =V61 -> 1 | W9: =sum(Q9:V9) -> 7 | X9: =X61 -> 3 | Y9: =Y61 -> 0 | Z9: =Z61 -> 4 | AA9: =AA61 -> 0 | AB9: =AB61 -> 1 | AC9: =AC61 -> 2 | AD9: =sum(X9:AC9) -> 10 | AE9: =AE61 -> 2 | AF9: =AF61 -> 1 | AG9: =AG61 -> 3 | AH9: =AH61 -> 2 | AI9: =AI61 -> 0 | AJ9: =AJ61
A10: 目標アポ転換率 | B10: 0.006 | C10: 現状コール数 | D10: =sum(E10:H10)+sum(J10:O10)+sum(Q10:V10)+sum(X10:AC10)+sum(AE10:AF10) -> 7792 | E10: =E68 -> 201 | F10: =F68 -> 215 | G10: =G68 -> 184 | H10: =H68 -> 247 | I10: =sum(E10:H10) -> 847 | J10: =J68 -> 243 | K10: =K68 -> 361 | L10: =L68 -> 359 | M10: =M68 -> 414 | N10: =N68 -> 452 | O10: =O68 -> 281 | P10: =sum(J10:O10) -> 2110 | Q10: =Q68 -> 0 | R10: =R68 -> 339 | S10: =S68 -> 354 | T10: =T68 -> 228 | U10: =U68 -> 344 | V10: =V68 -> 322 | W10: =sum(Q10:V10) -> 1587 | X10: =X68 -> 435 | Y10: =Y68 -> 375 | Z10: =Z68 -> 431 | AA10: =AA68 -> 352 | AB10: =AB68 -> 419 | AC10: =AC68 -> 464 | AD10: =sum(X10:AC10) -> 2476 | AE10: =AE68 -> 478 | AF10: =AF68 -> 294 | AG10: =AG68 -> 274 | AH10: =AH68 -> 341 | AI10: =AI68 -> 210 | AJ10: =AJ68
A11: 1日の平均受注数 | B11: =D4/'【第一】案件管理シート'!E2 -> 0 | C11: 現状受注率 | D11: =D4/D5 -> 0 | E11: 現状受注率 | I11: =I4/I5 -> 0 | J11: 現状受注率 | P11: =P4/P5 -> #DIV/0! | Q11: 現状受注率 | W11: =W4/W5 -> #DIV/0! | X11: 現状受注率 | AD11: =AD4/AD5 -> 0
A12: 1日の平均消化数 | B12: =D5/'【第一】案件管理シート'!E2 -> 0.4 | C12: 現状出席率 | D12: =D5/D7 -> 0.15789474 | E12: 現状出席率 | I12: =I5/I7 -> 0.3 | J12: 現状出席率 | P12: =P5/P7 -> 0 | Q12: 現状出席率 | W12: =W5/W7 -> 0 | X12: 現状出席率 | AD12: =AD5/AD7 -> 0.25
A13: 1日の平均アポ数 | B13: =D9/'【第一】案件管理シート'!E2 -> 1.8666667 | C13: 現状商談転換率 | D13: =D5/D9 -> 0.21428571 | E13: 現状商談転換率 | I13: =I5/I9 -> 1.5 | J13: 現状商談転換率 | P13: =P5/P9 -> 0 | Q13: 現状商談転換率 | W13: =W5/W9 -> 0 | X13: 現状商談転換率 | AD13: =AD5/AD9 -> 0.2
A14: 1日の平均コール数 | B14: =D10/'【第一】案件管理シート'!E2 -> 519.46667 | C14: 現状アポ転換率 | D14: =D9/D10 -> 0.0035934292 | E14: 現状アポ転換率 | I14: =I9/I10 -> 0.0023612751 | J14: 現状アポ転換率 | P14: =P9/P10 -> 0.0028436019 | Q14: 現状アポ転換率 | W14: =W9/W10 -> 0.0044108381 | X14: 現状アポ転換率 | AD14: =AD9/AD10 -> 0.0040387722
A16: ハウスクリーニング | C16: 売上 | D16: =sum(E16:H16)+sum(J16:O16)+sum(Q16:V16)+sum(X16:AC16)+SUM(AE16:AF16) -> 0 | I16: =sum(E16:H16) -> 0 | P16: =sum(J16:O16) -> 0 | W16: =sum(Q16:V16) -> 0 | AD16: =sum(X16:AC16) -> 0
C17: 受注数 | D17: =sum(E17:H17)+sum(J17:O17)+sum(Q17:V17)+sum(X17:AC17)+sum(AE17:AF17) -> 0 | I17: =sum(E17:H17) -> 0 | P17: =sum(J17:O17) -> 0 | W17: =sum(Q17:V17) -> 0 | AD17: =sum(X17:AC17) -> 0
A18: 受注率 | B18: =D17/D18 -> 0 | C18: 有効商談数 | D18: =sum(E18:H18)+sum(J18:O18)+sum(Q18:V18)+sum(X18:AC18)+sum(AE18:AF18) -> 3 | E18: 1 | F18: 1 | G18: 1 | I18: =sum(E18:H18) -> 3 | P18: =sum(J18:O18) -> 0 | W18: =sum(Q18:V18) -> 0 | AD18: =sum(X18:AC18) -> 0 | AI18: 1
A19: 出席率 | B19: =D18/D19 -> 0.15789474 | C19: 商談設定数 | D19: =sum(E19:H19)+sum(J19:O19)+sum(Q19:V19)+sum(X19:AC19)+sum(AE19:AF19) -> 19 | E19: 3 | F19: 2 | G19: 2 | H19: 1 | I19: =sum(E19:H19) -> 8 | J19: 2 | N19: 2 | P19: =sum(J19:O19) -> 4 | R19: 1 | S19: 1 | U19: 1 | W19: =sum(Q19:V19) -> 3 | X19: 1 | AD19: =sum(X19:AC19) -> 1 | AE19: 2 | AF19: 1 | AG19: 1 | AI19: 1
E20: 現状受注率 | I20: =I17/I18 -> 0 | J20: 現状受注率 | P20: =P17/P18 -> #DIV/0! | Q20: 現状受注率 | W20: =W17/W18 -> #DIV/0! | X20: 現状受注率 | AD20: =AD17/AD18 -> #DIV/0!
E21: 現状出席率 | I21: =I18/I19 -> 0.375 | J21: 現状出席率 | P21: =P18/P19 -> 0 | Q21: 現状出席率 | W21: =W18/W19 -> 0 | X21: 現状出席率 | AD21: =AD18/AD19 -> 0
A23: 不用品回収/買取 | C23: 売上 | D23: =sum(E23:H23)+sum(J23:O23)+sum(Q23:V23)+sum(X23:AC23)+SUM(AE23:AF23) -> 0 | I23: =sum(E23:H23) -> 0 | P23: =sum(J23:O23) -> 0 | W23: =sum(Q23:V23) -> 0 | AD23: =sum(X23:AC23) -> 0
C24: 受注数 | D24: =sum(E24:H24)+sum(J24:O24)+sum(Q24:V24)+sum(X24:AC24)+sum(AE24:AF24) -> 0 | I24: =sum(E24:H24) -> 0 | P24: =sum(J24:O24) -> 0 | W24: =sum(Q24:V24) -> 0 | AD24: =sum(X24:AC24) -> 0
A25: 受注率 | B25: =D24/D25 -> 0 | C25: 有効商談数 | D25: =sum(E25:H25)+sum(J25:O25)+sum(Q25:V25)+sum(X25:AC25)+sum(AE25:AF25) -> 1 | I25: =sum(E25:H25) -> 0 | P25: =sum(J25:O25) -> 0 | W25: =sum(Q25:V25) -> 0 | Y25: 1 | AD25: =sum(X25:AC25) -> 1 | AH25: 1
A26: 出席率 | B26: =D25/D26 -> 0.125 | C26: 商談設定数 | D26: =sum(E26:H26)+sum(J26:O26)+sum(Q26:V26)+sum(X26:AC26)+sum(AE26:AF26) -> 8 | E26: 1 | G26: 1 | I26: =sum(E26:H26) -> 2 | J26: 1 | K26: 1 | L26: 1 | P26: =sum(J26:O26) -> 3 | W26: =sum(Q26:V26) -> 0 | Y26: 1 | AB26: 2 | AD26: =sum(X26:AC26) -> 3 | AH26: 1
E27: 現状受注率 | I27: =I24/I25 -> #DIV/0! | J27: 現状受注率 | P27: =P24/P25 -> #DIV/0! | Q27: 現状受注率 | W27: =W24/W25 -> #DIV/0! | X27: 現状受注率 | AD27: =AD24/AD25 -> 0
E28: 現状出席率 | I28: =I25/I26 -> 0 | J28: 現状出席率 | P28: =P25/P26 -> 0 | Q28: 現状出席率 | W28: =W25/W26 -> #DIV/0! | X28: 現状出席率 | AD28: =AD25/AD26 -> 0.33333333
A30: 宿泊 | C30: 売上 | D30: =sum(E30:H30)+sum(J30:O30)+sum(Q30:V30)+sum(X30:AC30)+SUM(AE30:AF30) -> 0 | I30: =sum(E30:H30) -> 0 | P30: =sum(J30:O30) -> 0 | W30: =sum(Q30:V30) -> 0 | AD30: =sum(X30:AC30) -> 0
C31: 受注数 | D31: =sum(E31:H31)+sum(J31:O31)+sum(Q31:V31)+sum(X31:AC31)+sum(AE31:AF31) -> 0 | I31: =sum(E31:H31) -> 0 | P31: =sum(J31:O31) -> 0 | W31: =sum(Q31:V31) -> 0 | AD31: =sum(X31:AC31) -> 0
A32: 受注率 | B32: =D31/D32 -> 0 | C32: 有効商談数 | D32: =sum(E32:H32)+sum(J32:O32)+sum(Q32:V32)+sum(X32:AC32)+sum(AE32:AF32) -> 2 | I32: =sum(E32:H32) -> 0 | P32: =sum(J32:O32) -> 0 | W32: =sum(Q32:V32) -> 0 | Z32: 1 | AD32: =sum(X32:AC32) -> 1 | AF32: 1 | AG32: 1 | AH32: 1
A33: 出席率 | B33: =D32/D33 -> 0.18181818 | C33: 商談設定数 | D33: =sum(E33:H33)+sum(J33:O33)+sum(Q33:V33)+sum(X33:AC33)+sum(AE33:AF33) -> 11 | I33: =sum(E33:H33) -> 0 | L33: 1 | M33: 1 | P33: =sum(J33:O33) -> 2 | R33: 1 | S33: 1 | T33: 1 | U33: 1 | W33: =sum(Q33:V33) -> 4 | Y33: 2 | Z33: 1 | AA33: 1 | AD33: =sum(X33:AC33) -> 4 | AF33: 1 | AG33: 1 | AH33: 2
E34: 現状受注率 | I34: =I31/I32 -> #DIV/0! | J34: 現状受注率 | P34: =P31/P32 -> #DIV/0! | Q34: 現状受注率 | W34: =W31/W32 -> #DIV/0! | X34: 現状受注率 | AD34: =AD31/AD32 -> 0
E35: 現状出席率 | I35: =I32/I33 -> #DIV/0! | J35: 現状出席率 | P35: =P32/P33 -> 0 | Q35: 現状出席率 | W35: =W32/W33 -> 0 | X35: 現状出席率 | AD35: =AD32/AD33 -> 0.25
A37: 縞谷 | C37: 売上 | D37: =sum(E37:H37)+sum(J37:O37)+sum(Q37:V37)+sum(X37:AC37)+SUM(AE37:AF37) -> 0 | I37: =sum(E37:H37) -> 0 | P37: =sum(J37:O37) -> 0 | W37: =sum(Q37:V37) -> 0 | AD37: =sum(X37:AC37) -> 0
C38: 受注数 | D38: =sum(E38:H38)+sum(J38:O38)+sum(Q38:V38)+sum(X38:AC38)+sum(AE38:AF38) -> 0 | I38: =sum(E38:H38) -> 0 | P38: =sum(J38:O38) -> 0 | W38: =sum(Q38:V38) -> 0 | AD38: =sum(X38:AC38) -> 0
A39: 受注率 | B39: =D38/D39 -> #DIV/0! | C39: 有効商談数 | D39: =sum(E39:H39)+sum(J39:O39)+sum(Q39:V39)+sum(X39:AC39)+sum(AE39:AF39) -> 0 | I39: =sum(E39:H39) -> 0 | P39: =sum(J39:O39) -> 0 | W39: =sum(Q39:V39) -> 0 | AD39: =sum(X39:AC39) -> 0
A40: 出席率 | B40: =D39/D40 -> #DIV/0! | C40: 商談設定数 | D40: =sum(E40:H40)+sum(J40:O40)+sum(Q40:V40)+sum(X40:AC40)+sum(AE40:AF40) -> 0 | I40: =sum(E40:H40) -> 0 | P40: =sum(J40:O40) -> 0 | W40: =sum(Q40:V40) -> 0 | AD40: =sum(X40:AC40) -> 0
A42: 魚井 | C42: 売上 | D42: =sum(E42:H42)+sum(J42:O42)+sum(Q42:V42)+sum(X42:AC42)+SUM(AE42:AF42) -> 0 | I42: =sum(E42:H42) -> 0 | P42: =sum(J42:O42) -> 0 | W42: =sum(Q42:V42) -> 0 | AD42: =sum(X42:AC42) -> 0
C43: 受注数 | D43: =sum(E43:H43)+sum(J43:O43)+sum(Q43:V43)+sum(X43:AC43)+sum(AE43:AF43) -> 0 | I43: =sum(E43:H43) -> 0 | P43: =sum(J43:O43) -> 0 | W43: =sum(Q43:V43) -> 0 | AD43: =sum(X43:AC43) -> 0
A44: 受注率 | B44: =D43/D44 -> #DIV/0! | C44: 有効商談数 | D44: =sum(E44:H44)+sum(J44:O44)+sum(Q44:V44)+sum(X44:AC44)+sum(AE44:AF44) -> 0 | I44: =sum(E44:H44) -> 0 | P44: =sum(J44:O44) -> 0 | W44: =sum(Q44:V44) -> 0 | AD44: =sum(X44:AC44) -> 0
A45: 出席率 | B45: =D44/D45 -> #DIV/0! | C45: 商談設定数 | D45: =sum(E45:H45)+sum(J45:O45)+sum(Q45:V45)+sum(X45:AC45)+sum(AE45:AF45) -> 0 | I45: =sum(E45:H45) -> 0 | P45: =sum(J45:O45) -> 0 | W45: =sum(Q45:V45) -> 0 | AD45: =sum(X45:AC45) -> 0
A47: １時間あたりのコール数 | E47: =E68/E75 -> 11.823529 | F47: =F68/F75 -> 11.315789 | G47: =G68/G75 -> 12.266667 | H47: =H68/H75 -> 13.722222 | I47: =sum(E47:H47)/6 -> 8.1880346 | J47: =J68/J75 -> 17.357143 | K47: =K68/K75 -> 14.44 | L47: =L68/L75 -> 16.318182 | M47: =M68/M75 -> 18.818182 | N47: =N68/N75 -> 20.545455 | O47: =O68/O75 -> 18.733333 | P47: =sum(J47:O47)/6 -> 17.702049 | Q47: =Q68/Q75 -> #DIV/0! | R47: =R68/R75 -> 16.142857 | S47: =S68/S75 -> 17.7 | T47: =T68/T75 -> 17.538462 | U47: =U68/U75 -> 21.5 | V47: =V68/V75 -> 21.466667 | W47: =sum(Q47:V47)/6 -> #DIV/0! | X47: =X68/X75 -> 17.755102 | Y47: =Y68/Y75 -> 22.058824 | Z47: =Z68/Z75 -> 20.046512 | AA47: =AA68/AA75 -> 21.333333 | AB47: =AB68/AB75 -> 19.952381 | AC47: =AC68/AC75 -> 20.173913 | AD47: =sum(X47:AC47)/6 -> 20.220011 | AE47: =AE68/AE75 -> 20.782609 | AF47: =AF68/AF75 -> 21 | AG47: =AG68/AG75 -> 17.677419 | AH47: =AH68/AH75 -> 19.485714 | AI47: =AI68/AI75 -> 20
A48: 縞谷 | D48: =D69/D76 -> #DIV/0! | I48: =sum(E48:H48)/6 -> 0 | P48: =sum(J48:O48)/6 -> 0 | W48: =sum(Q48:V48)/6 -> 0 | Z48: =Z69/Z76 -> #DIV/0! | AD48: =sum(X48:AC48)/6 -> #DIV/0!
A49: 前川 | D49: =D70/D77 -> 20.021164 | E49: =E70/E77 -> #DIV/0! | F49: =F70/F77 -> #DIV/0! | G49: =G70/G77 -> #DIV/0! | H49: =H70/H77 -> #DIV/0! | I49: =sum(E49:H49)/6 -> #DIV/0! | J49: =J70/J77 -> #DIV/0! | K49: =K70/K77 -> 18.8 | L49: =L70/L77 -> #DIV/0! | P49: =sum(J49:O49)/6 -> #DIV/0! | W49: =sum(Q49:V49)/6 -> 0 | X49: =X70/X77 -> 19.066667 | Y49: =Y70/Y77 -> 21.6 | Z49: =Z70/Z77 -> 19.333333 | AA49: =AA70/AA77 -> 18.857143 | AB49: =AB70/AB77 -> 21.2 | AD49: =sum(X49:AC49)/6 -> 16.67619 | AE49: =AE70/AE77 -> 21 | AF49: =AF70/AF77 -> 19.428571 | AG49: =AG70/AG77 -> 14.6 | AH49: =AH70/AH77 -> 20 | AI49: =AI70/AI77 -> #DIV/0!
A50: 高原 | D50: =D71/D78 -> 16.342679 | E50: =E71/E78 -> 13.6 | F50: =F71/F78 -> 10 | G50: =G71/G78 -> 11.8 | H50: =H71/H78 -> 11.833333 | I50: =sum(E50:H50)/6 -> 7.8722222 | J50: =J71/J78 -> 17.428571 | K50: =K71/K78 -> 14.166667 | L50: =L71/L78 -> 15.142857 | M50: =M71/M78 -> 20.25 | N50: =N71/N78 -> 20.875 | O50: =O71/O78 -> #DIV/0! | P50: =sum(J50:O50)/6 -> #DIV/0! | Q50: =Q71/Q78 -> #DIV/0! | R50: =R71/R78 -> 12.75 | S50: =S71/S78 -> 12.571429 | T50: =T71/T78 -> 13.571429 | U50: =U71/U78 -> 20.375 | V50: =V71/V78 -> 17 | W50: =sum(Q50:V50)/6 -> #DIV/0! | X50: =X71/X78 -> 15.75 | Y50: =Y71/Y78 -> 16.285714 | Z50: =Z71/Z78 -> 15.375 | AA50: =AA71/AA78 -> #DIV/0! | AB50: =AB71/AB78 -> 18.4 | AD50: =sum(X50:AC50)/6 -> #DIV/0! | AE50: =AE71/AE78 -> 19.5 | AF50: =AF71/AF78 -> 20 | AG50: =AG71/AG78 -> 14.666667 | AH50: =AH71/AH78 -> 18 | AI50: =AI71/AI78 -> 20
A51: 魚井 | D51: =D72/D79 -> 18.638158 | E51: =E72/E79 -> 7.2 | F51: =F72/F79 -> 10.333333 | G51: =G72/G79 -> 6.2 | H51: =H72/H79 -> 13.333333 | I51: =sum(E51:H51)/6 -> 6.1777778 | J51: =J72/J79 -> 17.285714 | K51: =K72/K79 -> 10.714286 | L51: =L72/L79 -> 20.625 | M51: =M72/M79 -> 17.857143 | N51: =N72/N79 -> 20.285714 | O51: =O72/O79 -> 20 | P51: =sum(J51:O51)/6 -> 17.794643 | Q51: =Q72/Q79 -> #DIV/0! | R51: =R73/R79 -> 10.2 | S51: =S72/S79 -> 20.4 | T51: =T72/T79 -> #DIV/0! | U51: =U72/U79 -> #DIV/0! | V51: =V72/V79 -> 23 | W51: =sum(Q51:V51)/6 -> #DIV/0! | X51: =X72/X79 -> 19.375 | Y51: =Y72/Y79 -> 22 | Z51: =Z72/Z79 -> 20 | AA51: =AA72/AA79 -> 24 | AB51: =AB72/AB79 -> 20.75 | AC51: =AC72/AC79 -> 21.25 | AD51: =sum(X51:AC51)/6 -> 21.229167 | AE51: =AE72/AE79 -> 21.875 | AF51: =AF72/AF79 -> 22.666667 | AG51: =AG72/AG79 -> 30.333333 | AH51: =AH72/AH79 -> 20.133333 | AI51: =AI72/AI79 -> 21.2
A52: 長島 | D52: =D73/D80 -> 17.148649 | F52: =F73/F80 -> 13.285714 | G52: =G73/G80 -> 18.8 | H52: =H73/H80 -> 16 | I52: =sum(E52:H52)/6 -> 8.0142857 | J52: 20 | K52: =K73/K80 -> 15.285714 | L52: =L73/L80 -> 12.571429 | M52: =M73/M80 -> 18.142857 | N52: =N73/N80 -> 20.428571 | P52: =sum(J52:O52)/6 -> 14.404762 | S52: =S73/S80 -> 22 | W52: =sum(Q52:V52)/6 -> 3.6666667 | X52: =X73/X80 -> 11 | AA52: =AA73/AA80 -> 20 | AB52: =AB73/AB80 -> 18.333333 | AD52: =sum(X52:AC52)/6 -> 8.2222222 | AE52: =AE73/AE80 -> #DIV/0! | AF52: =AF73/AF80 -> #DIV/0! | AG52: =AG73/AG80 -> #DIV/0! | AH52: =AH73/AH80 -> #DIV/0! | AI52: =AI73/AI80 -> 17
A54: アポ転換率 | E54: =E61/E68 -> 0 | F54: =F61/F68 -> 0 | G54: =G61/G68 -> 0.0054347826 | H54: =H61/H68 -> 0.004048583 | I54: =sum(E54:H54)/6 -> 0.0015805609 | J54: =J61/J68 -> 0 | K54: =K61/K68 -> 0.0083102493 | L54: =L61/L68 -> 0.0055710306 | M54: =M61/M68 -> 0.0024154589 | N54: =N61/N68 -> 0 | O54: =O61/O68 -> 0 | P54: =sum(J54:O54)/6 -> 0.0027161231 | Q54: =Q61/Q68 -> #DIV/0! | R54: =R61/R68 -> 0.005899705 | S54: =S61/S68 -> 0.0028248588 | T54: =T61/T68 -> 0.013157895 | U54: =U61/U68 -> 0 | V54: =V61/V68 -> 0.0031055901 | W54: =sum(Q54:V54)/6 -> #DIV/0! | X54: =X61/X68 -> 0.0068965517 | Y54: =Y61/Y68 -> 0 | Z54: =Z61/Z68 -> 0.0092807425 | AA54: =AA61/AA68 -> 0 | AB54: =AB61/AB68 -> 0.0023866348 | AC54: =AC61/AC68 -> 0.0043103448 | AD54: =sum(X54:AC54)/6 -> 0.003812379 | AE54: =AE61/AE68 -> 0.0041841004 | AF54: =AF61/AF68 -> 0.0034013605 | AG54: =AG61/AG68 -> 0.010948905 | AH54: =AH61/AH68 -> 0.0058651026 | AI54: =AI61/AI68 -> 0
A55: 縞谷 | D55: =D62/D69 -> #DIV/0! | I55: =sum(E55:H55)/6 -> 0 | P55: =sum(J55:O55)/6 -> 0 | W55: =sum(Q55:V55)/6 -> 0 | Z55: =Z62/Z69 -> #DIV/0! | AD55: =sum(X55:AC55)/6 -> #DIV/0!
A56: 前川 | D56: =D63/D70 -> 0.0052854123 | E56: =E63/E70 -> #DIV/0! | F56: =F63/F70 -> #DIV/0! | G56: =G63/G70 -> #DIV/0! | H56: =H63/H70 -> #DIV/0! | I56: =sum(E56:H56)/6 -> #DIV/0! | J56: =J63/J70 -> #DIV/0! | K56: =K63/K70 -> 0.010638298 | L56: =L63/L70 -> #DIV/0! | P56: =sum(J56:O56)/6 -> #DIV/0! | W56: =sum(Q56:V56)/6 -> 0 | X56: =X63/X70 -> 0.006993007 | Y56: =Y63/Y70 -> 0 | Z56: =Z63/Z70 -> 0 | AA56: =AA63/AA70 -> 0 | AB56: =AB63/AB70 -> 0 | AD56: =sum(X56:AC56)/6 -> 0.0011655012 | AE56: =AE63/AE70 -> 0.013605442 | AF56: =AF63/AF70 -> 0 | AG56: =AG63/AG70 -> 0.01369863 | AH56: =AH63/AH70 -> 0.01 | AI56: =AI63/AI70 -> #DIV/0!
A57: 高原 | D57: =D64/D71 -> 0.0030499428 | E57: =E64/E71 -> 0 | F57: =F64/F71 -> 0 | G57: =G64/G71 -> 0 | H57: =H64/H71 -> 0 | I57: =sum(E57:H57)/6 -> 0 | J57: =J64/J71 -> 0 | K57: =K64/K71 -> 0.011764706 | L57: =L64/L71 -> 0 | M57: =M64/M71 -> 0 | N57: =N64/N71 -> 0 | O57: =O64/O71 -> #DIV/0! | P57: =sum(J57:O57)/6 -> #DIV/0! | Q57: =Q64/Q71 -> #DIV/0! | R57: =R64/R71 -> 0.0098039216 | S57: =S64/S71 -> 0 | T57: =T64/T71 -> 0.021052632 | U57: =U64/U71 -> 0 | V57: =V64/V71 -> 0 | W57: =sum(Q57:V57)/6 -> #DIV/0! | X57: =X64/X71 -> 0.0079365079 | Y57: =Y64/Y71 -> 0 | Z57: =Z64/Z71 -> 0 | AA57: =AA64/AA71 -> #DIV/0! | AB57: =AB64/AB71 -> 0.010869565 | AD57: =sum(X57:AC57)/6 -> #DIV/0! | AE57: =AE64/AE71 -> 0 | AF57: =AF64/AF71 -> 0.011111111 | AG57: =AG64/AG71 -> 0.0090909091 | AH57: =AH64/AH71 -> 0 | AI57: =AI64/AI71 -> 0
A58: 魚井 | D58: =D65/D72 -> 0.0042357924 | E58: =E65/E72 -> 0 | F58: =F65/F72 -> 0 | G58: =G65/G72 -> 0 | H58: =H65/H72 -> 0.0125 | I58: =sum(E58:H58)/6 -> 0.0020833333 | J58: =J65/J72 -> 0 | K58: =K65/K72 -> 0 | M58: =M65/M72 -> 0.008 | N58: =N65/N72 -> 0 | O58: =O65/O72 -> 0 | P58: =sum(J58:O58)/6 -> 0.0013333333 | Q58: =Q65/Q72 -> #DIV/0! | R58: =R65/R73 -> 0.019607843 | S58: =S65/S72 -> 0 | T58: =T65/T72 -> #DIV/0! | U58: =U65/U72 -> #DIV/0! | V58: =V65/V72 -> 0 | W58: =sum(Q58:V58)/6 -> #DIV/0! | X58: =X65/X72 -> 0.0064516129 | Y58: =Y65/Y72 -> 0 | AA58: =AA65/AA72 -> 0 | AB58: =AB65/AB72 -> 0 | AD58: =sum(X58:AC58)/6 -> 0.0010752688 | AE58: =AE65/AE72 -> 0 | AF58: =AF65/AF72 -> 0 | AG58: =AG65/AG72 -> 0.010989011 | AH58: =AH65/AH72 -> 0.0066225166 | AI58: =AI65/AI72 -> 0
A59: 長島 | D59: =D66/D73 -> 0.0023640662 | F59: =F66/F73 -> 0 | G59: =G66/G73 -> 0.010638298 | H59: =H66/H73 -> 0 | I59: =sum(E59:H59)/6 -> 0.0017730496 | J59: =J66/J73 -> #DIV/0! | K59: =K66/K73 -> 0.0093457944 | L59: =L66/L73 -> 0.011363636 | M59: =M66/M73 -> 0 | N59: =N66/N73 -> 0 | P59: =sum(J59:O59)/6 -> #DIV/0! | S59: =S66/S73 -> 0 | W59: =sum(Q59:V59)/6 -> 0 | X59: =X66/X73 -> 0 | Y59: =Y66/Y73 -> 0 | AA59: =AA66/AA73 -> 0 | AB59: =AB66/AB73 -> 0 | AD59: =sum(X59:AC59)/6 -> 0 | AE59: =AE66/AE73 -> #DIV/0! | AF59: =AF66/AF73 -> #DIV/0! | AG59: =AG66/AG73 -> #DIV/0! | AH59: =AH66/AH73 -> #DIV/0! | AI59: =AI66/AI73 -> 0
A61: 総アポ数 | E61: =sum(E62:E66) -> 0 | F61: =sum(F62:F66) -> 0 | G61: =sum(G62:G66) -> 1 | H61: =sum(H62:H66) -> 1 | I61: =sum(E61:H61)/6 -> 0.33333333 | J61: =sum(J62:J66) -> 0 | K61: =sum(K62:K66) -> 3 | L61: =sum(L62:L66) -> 2 | M61: =sum(M62:M66) -> 1 | N61: =sum(N62:N66) -> 0 | O61: =sum(O62:O66) -> 0 | P61: =sum(J61:O61)/6 -> 1 | Q61: =sum(Q62:Q66) -> 0 | R61: =sum(R62:R66) -> 2 | S61: =sum(S62:S66) -> 1 | T61: =sum(T62:T66) -> 3 | U61: =sum(U62:U66) -> 0 | V61: =sum(V62:V66) -> 1 | W61: =sum(Q61:V61)/6 -> 1.1666667 | X61: =sum(X62:X66) -> 3 | Y61: =sum(Y62:Y66) -> 0 | Z61: =sum(Z62:Z66) -> 4 | AA61: =sum(AA62:AA66) -> 0 | AB61: =sum(AB62:AB66) -> 1 | AC61: =sum(AC62:AC66) -> 2 | AD61: =sum(X61:AC61)/6 -> 1.6666667 | AE61: =sum(AE62:AE66) -> 2 | AF61: =sum(AF62:AF66) -> 1 | AG61: =sum(AG62:AG66) -> 3 | AH61: =sum(AH62:AH66) -> 2 | AI61: =sum(AI62:AI66) -> 0
A62: 縞谷 | D62: =sum(E62:H62)+sum(J62:O62)+sum(Q62:V62)+sum(X62:AC62)+sum(AE62:AI62) -> 0 | I62: =sum(E62:H62)/6 -> 0 | P62: =sum(J62:O62)/6 -> 0 | W62: =sum(Q62:V62)/6 -> 0 | AD62: =sum(X62:AC62)/6 -> 0
A63: 前川 | D63: =sum(E63:H63)+sum(J63:O63)+sum(Q63:V63)+sum(X63:AC63)+sum(AE63:AI63) -> 10 | I63: =sum(E63:H63)/6 -> 0 | K63: 1 | P63: =sum(J63:O63)/6 -> 0.16666667 | Q63: 0 | R63: 0 | S63: 1 | T63: 1 | U63: 0 | V63: 1 | W63: =sum(Q63:V63)/6 -> 0.5 | X63: 1 | Y63: 0 | Z63: 0 | AA63: 0 | AB63: 0 | AC63: 1 | AD63: =sum(X63:AC63)/6 -> 0.33333333 | AE63: 2 | AF63: 0 | AG63: 1 | AH63: 1
A64: 高原 | D64: =sum(E64:H64)+sum(J64:O64)+sum(Q64:V64)+sum(X64:AC64)+sum(AE64:AI64) -> 8 | E64: 0 | F64: 0 | G64: 0 | H64: 0 | I64: =sum(E64:H64)/6 -> 0 | J64: 0 | K64: 1 | L64: 0 | M64: 0 | N64: 0 | O64: 0 | P64: =sum(J64:O64)/6 -> 0.16666667 | Q64: 0 | R64: 1 | S64: 0 | T64: 2 | U64: 0 | V64: 0 | W64: =sum(Q64:V64)/6 -> 0.5 | X64: 1 | Y64: 0 | Z64: 0 | AA64: 0 | AB64: 1 | AC64: 0 | AD64: =sum(X64:AC64)/6 -> 0.33333333 | AE64: 0 | AF64: 1 | AG64: 1 | AH64: 0 | AI64: 0
A65: 魚井 | D65: =sum(E65:H65)+sum(J65:O65)+sum(Q65:V65)+sum(X65:AC65)+sum(AE65:AI65) -> 12 | E65: 0 | F65: 0 | G65: 0 | H65: 1 | I65: =sum(E65:H65)/6 -> 0.16666667 | J65: 0 | K65: 0 | L65: 1 | M65: 1 | N65: 0 | O65: 0 | P65: =sum(J65:O65)/6 -> 0.33333333 | Q65: 0 | R65: 1 | S65: 0 | T65: 0 | U65: 0 | V65: 0 | W65: =sum(Q65:V65)/6 -> 0.16666667 | X65: 1 | Y65: 0 | Z65: 4 | AA65: 0 | AB65: 0 | AC65: 1 | AD65: =sum(X65:AC65)/6 -> 1 | AE65: 0 | AF65: 0 | AG65: 1 | AH65: 1 | AI65: 0
A66: 長島 | D66: =sum(E66:H66)+sum(J66:O66)+sum(Q66:V66)+sum(X66:AC66)+sum(AE66:AI66) -> 3 | E66: 0 | F66: 0 | G66: 1 | H66: 0 | I66: =sum(E66:H66)/6 -> 0.16666667 | J66: 0 | K66: 1 | L66: 1 | M66: 0 | N66: 0 | O66: 0 | P66: =sum(J66:O66)/6 -> 0.33333333 | Q66: 0 | R66: 0 | S66: 0 | T66: 0 | U66: 0 | V66: 0 | W66: =sum(Q66:V66)/6 -> 0 | X66: 0 | Y66: 0 | Z66: 0 | AA66: 0 | AB66: 0 | AC66: 0 | AD66: =sum(X66:AC66)/6 -> 0 | AE66: 0 | AF66: 0 | AG66: 0 | AH66: 0 | AI66: 0
A68: 総コール数 | E68: =sum(E69:E73) -> 201 | F68: =sum(F69:F73) -> 215 | G68: =sum(G69:G73) -> 184 | H68: =sum(H69:H73) -> 247 | I68: =sum(E68:H68)/6 -> 141.16667 | J68: =sum(J69:J73) -> 243 | K68: =sum(K69:K73) -> 361 | L68: =sum(L69:L73) -> 359 | M68: =sum(M69:M73) -> 414 | N68: =sum(N69:N73) -> 452 | O68: =sum(O69:O73) -> 281 | P68: =sum(J68:O68)/6 -> 351.66667 | Q68: =sum(Q69:Q73) -> 0 | R68: =sum(R69:R73) -> 339 | S68: =sum(S69:S73) -> 354 | T68: =sum(T69:T73) -> 228 | U68: =sum(U69:U73) -> 344 | V68: =sum(V69:V73) -> 322 | W68: =sum(Q68:V68)/6 -> 264.5 | X68: =sum(X69:X73) -> 435 | Y68: =sum(Y69:Y73) -> 375 | Z68: =sum(Z69:Z73) -> 431 | AA68: =sum(AA69:AA73) -> 352 | AB68: =sum(AB69:AB73) -> 419 | AC68: =sum(AC69:AC73) -> 464 | AD68: =sum(X68:AC68)/6 -> 412.66667 | AE68: =sum(AE69:AE73) -> 478 | AF68: =sum(AF69:AF73) -> 294 | AG68: =sum(AG69:AG73) -> 274 | AH68: =sum(AH69:AH73) -> 341 | AI68: =sum(AI69:AI73) -> 210
A69: 縞谷 | D69: =sum(E69:H69)+sum(J69:O69)+sum(Q69:V69)+sum(X69:AC69)+sum(AE69:AI69) -> 0 | I69: =sum(E69:H69)/6 -> 0 | P69: =sum(J69:O69)/6 -> 0 | W69: =sum(Q69:V69)/6 -> 0 | AD69: =sum(X69:AC69)/6 -> 0
A70: 前川 | D70: =sum(E70:H70)+sum(J70:O70)+sum(Q70:V70)+sum(X70:AC70)+sum(AE70:AI70) -> 1892 | I70: =sum(E70:H70)/6 -> 0 | K70: 94 | P70: =sum(J70:O70)/6 -> 15.666667 | Q70: 0 | R70: 104 | S70: 120 | T70: 133 | U70: 181 | V70: 122 | W70: =sum(Q70:V70)/6 -> 110 | X70: 143 | Y70: 108 | Z70: 116 | AA70: 132 | AB70: 106 | AC70: 145 | AD70: =sum(X70:AC70)/6 -> 125 | AE70: 147 | AF70: 68 | AG70: 73 | AH70: 100
A71: 高原 | D71: =sum(E71:H71)+sum(J71:O71)+sum(Q71:V71)+sum(X71:AC71)+sum(AE71:AI71) -> 2623 | E71: 68 | F71: 60 | G71: 59 | H71: 71 | I71: =sum(E71:H71)/6 -> 43 | J71: 122 | K71: 85 | L71: 106 | M71: 162 | N71: 167 | O71: 0 | P71: =sum(J71:O71)/6 -> 107 | Q71: 0 | R71: 102 | S71: 88 | T71: 95 | U71: 163 | V71: 85 | W71: =sum(Q71:V71)/6 -> 88.833333 | X71: 126 | Y71: 114 | Z71: 123 | AA71: 0 | AB71: 92 | AC71: 149 | AD71: =sum(X71:AC71)/6 -> 100.66667 | AE71: 156 | AF71: 90 | AG71: 110 | AH71: 90 | AI71: 140
A72: 魚井 | D72: =sum(E72:H72)+sum(J72:O72)+sum(Q72:V72)+sum(X72:AC72)+sum(AE72:AI72) -> 2833 | E72: 36 | F72: 62 | G72: 31 | H72: 80 | I72: =sum(E72:H72)/6 -> 34.833333 | J72: 121 | K72: 75 | L72: 165 | M72: 125 | N72: 142 | O72: 160 | P72: =sum(J72:O72)/5 -> 157.6 | Q72: 0 | R72: 82 | S72: 102 | T72: 0 | U72: 0 | V72: 115 | W72: =sum(Q72:V72)/6 -> 49.833333 | X72: 155 | Y72: 110 | Z72: 150 | AA72: 180 | AB72: 166 | AC72: 170 | AD72: =sum(X72:AC72)/6 -> 155.16667 | AE72: 175 | AF72: 136 | AG72: 91 | AH72: 151 | AI72: 53
A73: 長島 | D73: =sum(E73:H73)+sum(J73:O73)+sum(Q73:V73)+sum(X73:AC73)+sum(AE73:AI73) -> 1269 | E73: 97 | F73: 93 | G73: 94 | H73: 96 | I73: =sum(E73:H73)/6 -> 63.333333 | J73: 0 | K73: 107 | L73: 88 | M73: 127 | N73: 143 | O73: 121 | P73: =sum(J73:O73)/6 -> 97.666667 | Q73: 0 | R73: 51 | S73: 44 | T73: 0 | U73: 0 | V73: 0 | W73: =sum(Q73:V73)/6 -> 15.833333 | X73: 11 | Y73: 43 | Z73: 42 | AA73: 40 | AB73: 55 | AC73: 0 | AD73: =sum(X73:AC73)/6 -> 31.833333 | AE73: 0 | AF73: 0 | AG73: 0 | AH73: 0 | AI73: 17
A75: 総架電時間 | E75: =sum(E76:E80) -> 17 | F75: =sum(F76:F80) -> 19 | G75: =sum(G76:G80) -> 15 | H75: =sum(H76:H80) -> 18 | I75: =sum(E75:H75)/6 -> 11.5 | J75: =sum(J76:J80) -> 14 | K75: =sum(K76:K80) -> 25 | L75: =sum(L76:L80) -> 22 | M75: =sum(M76:M80) -> 22 | N75: =sum(N76:N80) -> 22 | O75: =sum(O76:O80) -> 15 | P75: =sum(J75:O75)/6 -> 20 | Q75: =sum(Q76:Q80) -> 0 | R75: =sum(R76:R80) -> 21 | S75: =sum(S76:S80) -> 20 | T75: =sum(T76:T80) -> 13 | U75: =sum(U76:U80) -> 16 | V75: =sum(V76:V80) -> 15 | W75: =sum(Q75:V75)/6 -> 14.166667 | X75: =sum(X76:X80) -> 24.5 | Y75: =sum(Y76:Y79) -> 17 | Z75: =sum(Z76:Z80) -> 21.5 | AA75: =sum(AA76:AA80) -> 16.5 | AB75: =sum(AB76:AB80) -> 21 | AC75: =sum(AC76:AC80) -> 23 | AD75: =sum(X75:AC75)/6 -> 20.583333 | AE75: =sum(AE76:AE80) -> 23 | AF75: =sum(AF76:AF80) -> 14 | AG75: =sum(AG76:AG80) -> 15.5 | AH75: =sum(AH76:AH80) -> 17.5 | AI75: =sum(AI76:AI80) -> 10.5
A76: 縞谷 | D76: =sum(E76:H76)+sum(J76:O76)+sum(Q76:V76)+sum(X76:AC76)+sum(AE76:AI76) -> 0 | I76: =sum(E76:H76)/6 -> 0 | P76: =sum(J76:O76)/6 -> 0 | W76: =sum(Q76:V76)/6 -> 0 | AD76: =sum(X76:AC76)/6 -> 0
A77: 前川 | D77: =sum(E77:H77)+sum(J77:O77)+sum(Q77:V77)+sum(X77:AC77)+sum(AE77:AI77) -> 94.5 | I77: =sum(E77:H77)/6 -> 0 | K77: 5 | P77: =sum(J77:O77)/6 -> 0.83333333 | Q77: 0 | R77: 6 | S77: 6 | T77: 6 | U77: 8 | V77: 5 | W77: =sum(Q77:V77)/6 -> 5.1666667 | X77: 7.5 | Y77: 5 | Z77: 6 | AA77: 7 | AB77: 5 | AC77: 7.5 | AD77: =sum(X77:AC77)/6 -> 6.3333333 | AE77: 7 | AF77: 3.5 | AG77: 5 | AH77: 5
A78: 高原 | D78: =sum(E78:H78)+sum(J78:O78)+sum(Q78:V78)+sum(X78:AC78)+sum(AE78:AI78) -> 160.5 | E78: 5 | F78: 6 | G78: 5 | H78: 6 | I78: =sum(E78:H78)/6 -> 3.6666667 | J78: 7 | K78: 6 | L78: 7 | M78: 8 | N78: 8 | O78: 0 | P78: =sum(J78:O78)/6 -> 6 | Q78: 0 | R78: 8 | S78: 7 | T78: 7 | U78: 8 | V78: 5 | W78: =sum(Q78:V78)/6 -> 5.8333333 | X78: 8 | Y78: 7 | Z78: 8 | AA78: 0 | AB78: 5 | AC78: 7.5 | AD78: =sum(X78:AC78)/6 -> 5.9166667 | AE78: 8 | AF78: 4.5 | AG78: 7.5 | AH78: 5 | AI78: 7
A79: 魚井 | D79: =sum(E79:H79)+sum(J79:O79)+sum(Q79:V79)+sum(X79:AC79)+sum(AE79:AI79) -> 152 | E79: 5 | F79: 6 | G79: 5 | H79: 6 | I79: =sum(E79:H79)/6 -> 3.6666667 | J79: 7 | K79: 7 | L79: 8 | M79: 7 | N79: 7 | O79: 8 | P79: =sum(J79:O79)/6 -> 7.3333333 | Q79: 0 | R79: 5 | S79: 5 | T79: 0 | U79: 0 | V79: 5 | W79: =sum(Q79:V79)/6 -> 2.5 | X79: 8 | Y79: 5 | Z79: 7.5 | AA79: 7.5 | AB79: 8 | AC79: 8 | AD79: =sum(X79:AC79)/6 -> 7.3333333 | AE79: 8 | AF79: 6 | AG79: 3 | AH79: 7.5 | AI79: 2.5
A80: 長島 | D80: =sum(E80:H80)+sum(J80:O80)+sum(Q80:V80)+sum(X80:AC80)+sum(AE80:AI80) -> 74 | E80: 7 | F80: 7 | G80: 5 | H80: 6 | I80: =sum(E80:H80)/6 -> 4.1666667 | J80: 0 | K80: 7 | L80: 7 | M80: 7 | N80: 7 | O80: 7 | P80: =sum(J80:O80)/6 -> 5.8333333 | Q80: 0 | R80: 2 | S80: 2 | T80: 0 | U80: 0 | V80: 0 | W80: =sum(Q80:V80)/6 -> 0.66666667 | X80: 1 | Y80: 3 | Z80: 2 | AA80: 2 | AB80: 3 | AC80: 0 | AD80: =sum(X80:AC80)/6 -> 1.5 | AE80: 0 | AF80: 0 | AG80: 0 | AH80: 0 | AI80: 1

Sheet 【全体】ダッシュボード
A1: 46174 | B1: 理想進捗 | C1: ='【第一】案件管理シート'!E2/'【第一】案件管理シート'!E1 -> 0.68181818
A2: 売上ダッシュボード
A4: ◾️全体サマリー | I4: 全体残り営業日
A5: 項目 | B5: 目標売上 | C5: 確定売上 | D5: 理想進捗 | E5: 見込売上 | F5: 現状達成率 | G5: 乖離 | I5: 残り営業日 | J5: ='【第一】案件管理シート'!E3 -> 8 | K5: 日
A6: 全体 | B6: =sum(B8:B9) -> 10560000 | C6: =sum(C8:C9) -> 3048000 | D6: =sum(D8:D9) -> 7200000 | E6: =sum(E8:E9) -> 4425000 | F6: =C6/B6 -> 0.28863636 | G6: =B6-C6 -> 7512000
A8: 第一営業部 | B8: ='【第一】案件管理シート'!I2 -> 4800000 | C8: =SUMIFS('【第一】案件管理シート'!M20:M10036,'【第一】案件管理シート'!F20:F10036,A1,'【第一】案件管理シート'!D20:D10036,"AA課金") -> 764000 | D8: =B8/'【第一】案件管理シート'!E1*'【第一】案件管理シート'!E2 -> 3272727.3 | E8: ='【第一】案件管理シート'!I4 -> 764000 | F8: =C8/B8 -> 0.15916667 | G8: =B8-C8 -> 4036000
A9: HD | B9: ='【HD】案件管理シート'!I2 -> 5760000 | C9: =SUMIFS('【HD】案件管理シート'!M20:M10030,'【HD】案件管理シート'!F20:F10030,A1,'【HD】案件管理シート'!D20:D10030,"AA課金") -> 2284000 | D9: =B9/'【第一】案件管理シート'!E1*'【第一】案件管理シート'!E2 -> 3927272.7 | E9: ='【HD】案件管理シート'!I4 -> 3661000 | F9: =C9/B9 -> 0.39652778 | G9: =B9-C9 -> 3476000
A11: 高原 | B11: 1800000 | C11: =SUMIFS( '【HD】案件管理シート'!M16:M11895, '【HD】案件管理シート'!D16:D11895, "AA課金", '【HD】案件管理シート'!F16:F11895, '【全体】ダッシュボード'!A1, '【HD】案件管理シート'!B16:B11895, '【全体】ダッシュボード'!A11 ) / 2+SUMIFS( '【HD】案件管理シート'!M16:M11895, '【HD】案件管理シート'!D16:D11895, "AA課金", '【HD】案件管理シート'!F16:F11895, '【全体】ダッシュボード'!A1, '【HD】案件管理シート'!C16:C11895, '【全体】ダッシュボード'!A11 ) / 2+(SUMIFS('【第一】案件管理シート'!$M:$M, '【第一】案件管理シート'!$D:$D, "AA課金", '【第一】案件管理シート'!$F:$F, $A$1, '【第一】案件管理シート'!$B:$B, $A11) + SUMIFS('【第一】案件管理シート'!$M:$M, '【第一】案件管理シート'!$D:$D, "AA課金", '【第一】案件管理シート'!$F:$F, $A$1, '【第一】案件管理シート'!$C:$C, $A11)) / 2 -> 382000 | D11: =B11/'【第一】案件管理シート'!E1*'【第一】案件管理シート'!E2 -> 1227272.7 | E11: ='【HD】案件管理シート'!Z3+'【第一】案件管理シート'!Z3 -> 772000 | F11: =C11/B11 -> 0.21222222 | G11: =B11-C11 -> 1418000 | I11: HDアポ獲得期日
A12: 魚井 | B12: 1320000 | C12: =SUMIFS( '【HD】案件管理シート'!M16:M11894, '【HD】案件管理シート'!D16:D11894, "AA課金", '【HD】案件管理シート'!F16:F11894, '【全体】ダッシュボード'!A1, '【HD】案件管理シート'!B16:B11894, '【全体】ダッシュボード'!A12 ) / 2+SUMIFS( '【HD】案件管理シート'!M16:M11894, '【HD】案件管理シート'!D16:D11894, "AA課金", '【HD】案件管理シート'!F16:F11894, '【全体】ダッシュボード'!A1, '【HD】案件管理シート'!C16:C11894, '【全体】ダッシュボード'!A12 ) / 2 -> 890000 | D12: =B12/'【第一】案件管理シート'!E1*'【第一】案件管理シート'!E2 -> 900000 | E12: ='【HD】案件管理シート'!Z4 -> 1331000 | F12: =C12/B12 -> 0.67424242 | G12: =B12-C12 -> 430000 | I12: 残り営業日 | J12: ='【HD】案件管理シート'!E5 -> 2 | K12: 日
A13: 今福 | B13: 1320000 | C13: =SUMIFS( '【HD】案件管理シート'!M16:M11894, '【HD】案件管理シート'!D16:D11894, "AA課金", '【HD】案件管理シート'!F16:F11894, '【全体】ダッシュボード'!A1, '【HD】案件管理シート'!B16:B11894, '【全体】ダッシュボード'!A13 ) / 2+SUMIFS( '【HD】案件管理シート'!M16:M11894, '【HD】案件管理シート'!D16:D11894, "AA課金", '【HD】案件管理シート'!F16:F11894, '【全体】ダッシュボード'!A1, '【HD】案件管理シート'!C16:C11894, '【全体】ダッシュボード'!A13 ) / 2 -> 252000 | D13: =B13/'【第一】案件管理シート'!E1*'【第一】案件管理シート'!E2 -> 900000 | E13: ='【HD】案件管理シート'!Z6 -> 518000 | F13: =C13/B13 -> 0.19090909 | G13: =B13-C13 -> 1068000
A14: 坂本 | B14: 880000 | C14: =SUMIFS( '【HD】案件管理シート'!M16:M11894, '【HD】案件管理シート'!D16:D11894, "AA課金", '【HD】案件管理シート'!F16:F11894, '【全体】ダッシュボード'!A1, '【HD】案件管理シート'!B16:B11894, '【全体】ダッシュボード'!A14 ) / 2+SUMIFS( '【HD】案件管理シート'!M16:M11894, '【HD】案件管理シート'!D16:D11894, "AA課金", '【HD】案件管理シート'!F16:F11894, '【全体】ダッシュボード'!A1, '【HD】案件管理シート'!C16:C11894, '【全体】ダッシュボード'!A14 ) / 2 -> 360000 | D14: =B14/'【第一】案件管理シート'!E1*'【第一】案件管理シート'!E2 -> 600000 | E14: ='【HD】案件管理シート'!Z5 -> 636000 | F14: =C14/B14 -> 0.40909091 | G14: =B14-C14 -> 520000
A15: 岩井 | B15: 880000 | C15: =SUMIFS( '【HD】案件管理シート'!M16:M11894, '【HD】案件管理シート'!D16:D11894, "AA課金", '【HD】案件管理シート'!F16:F11894, '【全体】ダッシュボード'!A1, '【HD】案件管理シート'!B16:B11894, '【全体】ダッシュボード'!A15 ) / 2+SUMIFS( '【HD】案件管理シート'!M16:M11894, '【HD】案件管理シート'!D16:D11894, "AA課金", '【HD】案件管理シート'!F16:F11894, '【全体】ダッシュボード'!A1, '【HD】案件管理シート'!C16:C11894, '【全体】ダッシュボード'!A15 ) / 2 -> 60000 | D15: =B15/'【第一】案件管理シート'!E1*'【第一】案件管理シート'!E2 -> 600000 | E15: ='【HD】案件管理シート'!Z7 -> 196000 | F15: =C15/B15 -> 0.068181818 | G15: =B15-C15 -> 820000 | I15: 第一アポ獲得期日
A16: 橋本 | B16: 880000 | C16: =SUMIFS( '【HD】案件管理シート'!M16:M11894, '【HD】案件管理シート'!D16:D11894, "AA課金", '【HD】案件管理シート'!F16:F11894, '【全体】ダッシュボード'!A1, '【HD】案件管理シート'!B16:B11894, '【全体】ダッシュボード'!A16 ) / 2+SUMIFS( '【HD】案件管理シート'!M16:M11894, '【HD】案件管理シート'!D16:D11894, "AA課金", '【HD】案件管理シート'!F16:F11894, '【全体】ダッシュボード'!A1, '【HD】案件管理シート'!C16:C11894, '【全体】ダッシュボード'!A16 ) / 2 -> 298000 | D16: =B16/'【第一】案件管理シート'!E1*'【第一】案件管理シート'!E2 -> 600000 | E16: ='【HD】案件管理シート'!Z8 -> 470000 | F16: =C16/B16 -> 0.33863636 | G16: =B16-C16 -> 582000 | I16: 残り営業日 | J16: ='【第一】案件管理シート'!E5 -> 3 | K16: 日
A17: 松岡 | B17: 3000000 | C17: =(SUMIFS('【第一】案件管理シート'!$M:$M, '【第一】案件管理シート'!$D:$D, "AA課金", '【第一】案件管理シート'!$F:$F, $A$1, '【第一】案件管理シート'!$B:$B, $A17) + SUMIFS('【第一】案件管理シート'!$M:$M, '【第一】案件管理シート'!$D:$D, "AA課金", '【第一】案件管理シート'!$F:$F, $A$1, '【第一】案件管理シート'!$C:$C, $A17)) / 2 -> 382000 | D17: =B17/'【第一】案件管理シート'!E1*'【第一】案件管理シート'!E2 -> 2045454.5 | E17: ='【第一】案件管理シート'!Z2 -> 382000 | F17: =C17/B17 -> 0.12733333 | G17: =B17-C17 -> 2618000
C18: =SUMIFS( '【HD】案件管理シート'!M16:M11895, '【HD】案件管理シート'!D16:D11895, "AA課金", '【HD】案件管理シート'!F16:F11895, '【全体】ダッシュボード'!A1, '【HD】案件管理シート'!B16:B11895, '【全体】ダッシュボード'!A18 ) / 2+SUMIFS( '【HD】案件管理シート'!M16:M11895, '【HD】案件管理シート'!D16:D11895, "AA課金", '【HD】案件管理シート'!F16:F11895, '【全体】ダッシュボード'!A1, '【HD】案件管理シート'!C16:C11895, '【全体】ダッシュボード'!A18 ) / 2+(SUMIFS('【第一】案件管理シート'!$M:$M, '【第一】案件管理シート'!$D:$D, "AA課金", '【第一】案件管理シート'!$F:$F, $A$1, '【第一】案件管理シート'!$B:$B, $A18) + SUMIFS('【第一】案件管理シート'!$M:$M, '【第一】案件管理シート'!$D:$D, "AA課金", '【第一】案件管理シート'!$F:$F, $A$1, '【第一】案件管理シート'!$C:$C, $A18)) / 2 -> 0 | D18: =B18/'【第一】案件管理シート'!E1*'【第一】案件管理シート'!E2 -> 0 | E18: ='【第一】案件管理シート'!Z4 -> 0 | F18: =C18/B18 -> #DIV/0! | G18: =B18-C18 -> 0
A21: 行動管理ダッシュボード
A22: 第一営業部 | G22: HD
A23: 5月1日〜5月31日 | B23: 20営業日 | C23: =J5 -> 8 | D23: 5月売上 | E23: =B8 -> 4800000 | F23: =E23-'【第一】案件管理シート'!L9 -> 4036000 | G23: 6月1日〜6月31日 | H23: 17営業日 | I23: =J5 -> 8 | J23: 5月売上 | K23: 5280000 | L23: =K23-'【HD】案件管理シート'!I4 -> 1619000
A24: コール〜アポ化 | B24: 0.02 | C24: ='【2026年6月】月間進捗管理シート（第一）'!D8/'【2026年6月】月間進捗管理シート（第一）'!D12 -> 0.021603184 | D24: 受注件数 | E24: =E23/B25 -> 13.926486 | F24: =F23/C25 -> 10.565445 | G24: コール〜アポ化 | H24: 0.01 | I24: ='【2026年6月】IS管理シート（HD）'!AI7/'【2026年6月】IS管理シート（HD）'!AI3 -> 0.0055147059 | J24: 受注件数 | K24: =K23/H25 -> 58.479532 | L24: =L23/I25 -> 18.429947
A25: 5月平均売上 | B25: 344667 | C25: ='【第一】案件管理シート'!P12 -> 382000 | D25: 有効商談数 | E25: =E24/B32 -> 139.26486 | F25: =F24/C30 -> 63.39267 | G25: 6月平均売上 | H25: 90288 | I25: ='【HD】案件管理シート'!I5 -> 87846.154 | J25: 有効商談数 | K25: =K24/H31 -> 77.97271 | L25: =L24/I31 -> 36.09198
A26: 初回商談→受注 | B26: 5 | C26: ='【第一】案件管理シート'!T12 -> 4 | D26: 商談設定 | E26: =E25/B28 -> 163.84101 | F26: =F25/C28 -> 89.806283 | G26: アポ→受注（回収） | I26: ='【HD】案件管理シート'!L10 -> 6.6875 | J26: 商談設定 | K26: =K25/H29 -> 97.465887 | L26: =L25/I29 -> 43.003211
D27: アポ数 | E27: =E26/B29 -> 176.17313 | F27: =F26/C29-'【第一】案件管理シート'!K14-'【第一】案件管理シート'!K17 -> 95.937173 | G27: 回収→課金 | I27: ='【HD】案件管理シート'!K10 -> 11.59375 | J27: アポ数 | K27: =K26/H30 -> 121.83236 | L27: =L26/I30-'【HD】案件管理シート'!E12 -> 27.437355
A28: 有効商談 | B28: 0.85 | C28: ='【2026年6月】月間進捗管理シート（第一）'!A6 -> 0.70588235 | D28: コール数 | E28: =E27/B24 -> 8808.6563 | F28: =F27/C24 -> 4440.8812 | G28: アポ→課金 | H28: 15 | I28: ='【HD】案件管理シート'!N10 -> 17.46875 | J28: コール数 | K28: =K27/H24 -> 12183.236 | L28: =L27/I24 -> 4975.307
A29: 出席率 | B29: 0.93 | C29: ='【2026年6月】月間進捗管理シート（第一）'!A8 -> 0.80952381 | G29: 有効商談 | H29: 0.8 | I29: ='【2026年6月】月間進捗管理シート（HD）'!A6 -> 0.83928571
A30: 受注率 | B30: 0.16 | C30: ='【2026年6月】月間進捗管理シート（第一）'!A4 -> 0.16666667 | D30: 日割り受注数 | F30: =F24/'【第一】案件管理シート'!E3 -> 1.3206806 | G30: 出席率 | H30: 0.8 | I30: ='【2026年6月】月間進捗管理シート（HD）'!A8 -> 0.94642857 | J30: 日割り受注数 | L30: =L24/'【HD】案件管理シート'!E3 -> 2.3037434
A31: 架電→接続 | B31: 0.63 | C31: ='【2026年6月】月間進捗管理シート（第一）'!B13 -> 0.61455372 | D31: 日割り商談数 | F31: =F25/'【第一】案件管理シート'!E7 -> 12.678534 | G31: 受注率 | H31: 0.75 | I31: ='【2026年6月】月間進捗管理シート（HD）'!A4 -> 0.5106383 | J31: 日割り商談数 | L31: =L25/'【HD】案件管理シート'!E7 -> 12.03066
A32: 接続→オーナー数 | B32: 0.1 | C32: ='【2026年6月】月間進捗管理シート（第一）'!B12 -> 0.07400555 | D32: 日割りアポ数 | F32: =F27/'【第一】案件管理シート'!E5 -> 31.979058 | G32: 架電→接続 | H32: 0.35 | I32: ='【2026年6月】IS管理シート（HD）'!AI10 -> 0.34007353 | J32: 日割りアポ数 | L32: =L27/'【HD】案件管理シート'!E5 -> 13.718677
A33: オーナー→フル | B33: 0.68 | C33: ='【2026年6月】月間進捗管理シート（第一）'!B11 -> 0.7625 | D33: 日割りコール数 | F33: =F28/'【第一】案件管理シート'!E5 -> 1480.2937 | G33: 接続→オーナー数 | H33: 0.39 | I33: ='【2026年6月】IS管理シート（HD）'!AI11 -> 0.27094595 | J33: 日割りコール数 | L33: =L28/'【HD】案件管理シート'!E5 -> 2487.6535
A34: フル→アポ | B34: 0.5 | C34: ='【2026年6月】月間進捗管理シート（第一）'!B10 -> 0.62295082 | D34: 一人当たりコール数 | F34: =F33/2 -> 740.14687 | G34: オーナー→フル | H34: 0.09 | I34: ='【2026年6月】IS管理シート（HD）'!AI12 -> 0.19700748 | J34: 一人当たりコール数 | L34: =L33/4 -> 621.91337
G35: フル→アポ | H35: 0.59 | I35: ='【2026年6月】IS管理シート（HD）'!AI13 -> 0.30379747
A36: 【修正】最新ＫＰＩ
A37: 6月1日〜6月31日 | B37: 20営業日 | C37: =J5 -> 8 | D37: 5月売上 | E37: =B8 -> 4800000 | F37: =E23-592000-'【第一】案件管理シート'!L9 -> 3444000 | G37: 6月1日〜6月31日 | H37: 17営業日 | I37: =J5 -> 8 | J37: 5月売上 | K37: 5280000 | L37: =K37-'【HD】案件管理シート'!I4 -> 1619000
A38: コール〜アポ化 | B38: 0.02 | C38: ='【2026年6月】月間進捗管理シート（第一）'!D8/'【2026年6月】月間進捗管理シート（第一）'!D12 -> 0.021603184 | D38: 受注件数 | E38: =E37/B39 -> 13.926486 | F38: =F37/C39 -> 9.0157068 | G38: コール〜アポ化 | H38: 0.01 | I38: =1/(1/I46/I47/I48/I49) -> 0.0072084014 | J38: 受注件数 | K38: =K23/H25 -> 58.479532 | L38: =L37/I39 -> 17.387828
A39: 5月平均売上 | B39: 344667 | C39: ='【第一】案件管理シート'!P12 -> 382000 | D39: 有効商談数 | E39: =E38/B46 -> 139.26486 | F39: =F38/C44 -> 25.759162 | G39: 6月平均売上 | H39: 90288 | I39: 93111.111 | J39: 有効商談数 | K39: =K24/H31 -> 77.97271 | L39: =L38/I45 -> 23.183771
A40: 初回商談→受注 | B40: 5 | C40: ='【第一】案件管理シート'!T12 -> 4 | D40: 商談設定 | E40: =E39/B42 -> 163.84101 | F40: =F39/C42 -> 34.34555 | G40: アポ→受注（回収） | I40: ='【HD】案件管理シート'!L10 -> 6.6875 | J40: 商談設定 | K40: =K25/H29 -> 97.465887 | L40: =L39/I43 -> 28.979714
D41: アポ数 | E41: =E40/B43 -> 176.17313 | F41: =F40/C43-'【第一】案件管理シート'!K14-'【第一】案件管理シート'!K17 -> 27.931937 | G41: 回収→課金 | I41: ='【HD】案件管理シート'!K10 -> 11.59375 | J41: アポ数 | K41: =K26/H30 -> 121.83236 | L41: =L40/I44/I43-'【HD】案件管理シート'!E12 -> 22.249602
A42: 有効商談 | B42: 0.85 | C42: 0.75 | D42: コール数 | E42: =E41/B38 -> 8808.6563 | F42: =F41/C38 -> 1292.9547 | G42: アポ→課金 | H42: 15 | I42: ='【HD】案件管理シート'!N10 -> 17.46875 | J42: コール数 | K42: =K27/H24 -> 12183.236 | L42: =L41/I38 -> 3086.6209
A43: 出席率 | B43: 0.93 | C43: 0.8 | G43: 有効商談 | H43: 0.8 | I43: 0.8
A44: 受注率 | B44: 0.16 | C44: 0.35 | D44: 日割り受注数 | F44: =F38/'【第一】案件管理シート'!E3 -> 1.1269634 | G44: 出席率 | H44: 0.8 | I44: 0.9 | J44: 日割り受注数 | L44: =L38/'【HD】案件管理シート'!E3 -> 2.1734785
A45: 架電→接続 | B45: 0.63 | C45: ='【2026年6月】月間進捗管理シート（第一）'!B13 -> 0.61455372 | D45: 日割り商談数 | F45: =F39/'【第一】案件管理シート'!E7 -> 5.1518325 | G45: 受注率 | H45: 0.75 | I45: 0.75 | J45: 日割り商談数 | L45: =L39/'【HD】案件管理シート'!E7 -> 7.7279236
A46: 接続→オーナー数 | B46: 0.1 | C46: ='【2026年6月】月間進捗管理シート（第一）'!B12 -> 0.07400555 | D46: 日割りアポ数 | F46: =F41/'【第一】案件管理シート'!E5 -> 9.3106457 | G46: 架電→接続 | H46: 0.35 | I46: 0.3862 | J46: 日割りアポ数 | L46: =L40/'【HD】案件管理シート'!E5 -> 14.489857
A47: オーナー→フル | B47: 0.68 | C47: ='【2026年6月】月間進捗管理シート（第一）'!B11 -> 0.7625 | D47: 日割りコール数 | F47: =F42/'【第一】案件管理シート'!E5 -> 430.98489 | G47: 接続→オーナー数 | H47: 0.39 | I47: 0.3 | J47: 日割りコール数 | L47: =L42/'【HD】案件管理シート'!E5 -> 1543.3104
A48: フル→アポ | B48: 0.5 | C48: ='【2026年6月】月間進捗管理シート（第一）'!B10 -> 0.62295082 | D48: 一人当たりコール数 | F48: =F47/2 -> 215.49245 | G48: オーナー→フル | H48: 0.09 | I48: 0.1912 | J48: 一人当たりコール数 | L48: =L47/4 -> 385.82761
G49: フル→アポ | H49: 0.59 | I49: 0.3254
A51: 達成のために | G51: 達成のために
A52: ① | B52: 学園前きたにクリニックを必ず月額5万円で受注 | G52: ① | H52: IS接続率＋2％(曜日フィルタリング徹底・再コール徹底)
A53: ② | B53: 受注率35% | G53: ② | H53: オーナー数の増加（オーナー戻り聞く）
A54: ③ | B54: 上記コール数担保 | G54: ③ | H54: FS：デイリーのヨミ会（翔さんマスト参加）→Cヨミ以下のデリバリー案件の受注化
A55: ④ | B55: アポ率を下げない動き | G55: ④ | H55: FS：魚井のトークスクリプト完成・ロープレの実施→受注率75%担保
A56: ⑤ | B56: 出席率の向上 | G56: ⑤ | H56: FS：クレカの提案をRNにべた付けで実施（RNのみに90%付帯で94,000円）

Sheet 【第一】案件管理シート
A1: 今日の日付 | B1: =TODAY() -> 46192 | C1: 今月稼働日数 | E1: =_xlfn.NETWORKDAYS.INTL(B3, B4, "0000011", B8:B11) -> 22 | G1: 46174 | I1: 受注数 | J1: =COUNTIFS(F20:F10107, G1, D20:D10107, "AA課金") -> 2 | M1: クリニック | O1: 累計 | P1: 平均単価 | Q1: 受注率 | R1: アポ→商談 | S1: 商談→受注 | T1: アポ→受注 | U1: アポ→課金 | Z1: 見込み売上
C2: 現状稼働日数 | E2: =_xlfn.NETWORKDAYS.INTL(B3, B1, "0000011", B9:B13) -> 15 | G2: 粗利目標 | I2: 4800000 | K2: - | M2: 4800000 | P2: =IFERROR(AVERAGEIFS($M$20:$M$1123, $D$20:$D$1123, "AA課金"), 0) -> 272804.35 | Q2: =IFERROR(COUNTIFS($D$20:$D$1123, "AA課金") / COUNTIFS($D$20:$D$1123, "<>", $D$20:$D$1123, "<>無効商談", $D$20:$D$1123, "<>E商談", $D$20:$D$1123, "<>XCアポ失注", $D$20:$D$1123, "<>F日程変更中"), 0) -> 0.16546763 | R2: =IFERROR(AVERAGEIFS($W$20:$W$1123, $D$20:$D$1123, "<>", $W$20:$W$1123, ">=0", $D$20:$D$1123, "<>無効商談", $D$20:$D$1123, "<>E商談", $D$20:$D$1123, "<>XCアポ失注", $D$20:$D$1123, "<>F日程変更中"), 0) -> 5.7898833 | S2: =IFERROR(AVERAGEIFS($AA$20:$AA$1123, $Y$20:$Y$1123, "<>"), 0) -> 6.6818182 | T2: =IFERROR(AVERAGEIFS($Z$20:$Z$1123, $Y$20:$Y$1123, "<>"), 0) -> 11.386364 | U2: =IFERROR(AVERAGEIFS($AC$20:$AC$1123, $AB$20:$AB$1123, "<>"), 0) -> 14.136364 | Y2: 松岡 | Z2: =( ( SUMIFS(M19:M10518, B19:B10518, Y2, F19:F10518, G1, D19:D10518, "AA課金") + SUMIFS(M19:M10518, B19:B10518, Y2, F19:F10518, G1, D19:D10518, "A受注") + SUMIFS(M19:M10518, B19:B10518, Y2, F19:F10518, G1, D19:D10518, "B商談済み回答待ち") ) / 2 ) + ( ( SUMIFS(M19:M10518, C19:C10518, Y2, F19:F10518, G1, D19:D10518, "AA課金") + SUMIFS(M19:M10518, C19:C10518, Y2, F19:F10518, G1, D19:D10518, "A受注") + SUMIFS(M19:M10518, C19:C10518, Y2, F19:F10518, G1, D19:D10518, "B商談済み回答待ち") ) / 2 ) -> 382000
A3: 営業開始日 | B3: 46174 | C3: 残り稼働日数 | E3: =MAX(0,E1-E2+1) -> 8 | G3: 現状粗利 | I3: =SUMIFS(M20:M10107, F20:F10107, G1, D20:D10107, "AA課金") -> 764000 | K3: =SUMIFS(M20:M10107, F20:F10107, G1, D20:D10107, "AA課金", E20:E10107, K1) -> 0 | M3: =SUMIFS(M20:M10107, F20:F10107, G1, D20:D10107, "AA課金", E20:E10107, M1) -> 764000 | O3: ハウスクリーニング | P3: =IFERROR(AVERAGEIFS($M$20:$M$1123, $D$20:$D$1123, "AA課金", $E$20:$E$1123, $O3), 0) -> 238043.48 | Q3: =IFERROR(COUNTIFS($D$20:$D$1123, "AA課金", $E$20:$E$1123, $O3) / COUNTIFS($E$20:$E$1123, $O3, $D$20:$D$1123, "<>", $D$20:$D$1123, "<>無効商談", $D$20:$D$1123, "<>E商談", $D$20:$D$1123, "<>XCアポ失注", $D$20:$D$1123, "<>F日程変更中"), 0) -> 0.25842697 | R3: =IFERROR(AVERAGEIFS($W$20:$W$1123, $E$20:$E$1123, $O3, $D$20:$D$1123, "<>", $W$20:$W$1123, ">=0", $D$20:$D$1123, "<>無効商談", $D$20:$D$1123, "<>E商談", $D$20:$D$1123, "<>XCアポ失注", $D$20:$D$1123, "<>F日程変更中"), 0) -> 5.0348837 | S3: =IFERROR(AVERAGEIFS($AA$20:$AA$1123, $Y$20:$Y$1123, "<>", $E$20:$E$1123, $O3), 0) -> 6.0869565 | T3: =IFERROR(AVERAGEIFS($Z$20:$Z$1123, $Y$20:$Y$1123, "<>", $E$20:$E$1123, $O3), 0) -> 10.913043 | U3: =IFERROR(AVERAGEIFS($AC$20:$AC$1123, $AB$20:$AB$1123, "<>", $E$20:$E$1123, $O3), 0) -> 11.608696 | Y3: 高原 | Z3: =( ( SUMIFS(M19:M10518, B19:B10518, Y3, F19:F10518, G1, D19:D10518, "AA課金") + SUMIFS(M19:M10518, B19:B10518, Y3, F19:F10518, G1, D19:D10518, "A受注") + SUMIFS(M19:M10518, B19:B10518, Y3, F19:F10518, G1, D19:D10518, "B商談済み回答待ち") ) / 2 ) + ( ( SUMIFS(M19:M10518, C19:C10518, Y3, F19:F10518, G1, D19:D10518, "AA課金") + SUMIFS(M19:M10518, C19:C10518, Y3, F19:F10518, G1, D19:D10518, "A受注") + SUMIFS(M19:M10518, C19:C10518, Y3, F19:F10518, G1, D19:D10518, "B商談済み回答待ち") ) / 2 ) -> 382000
A4: 営業終了日 | B4: 46203 | C4: アポ獲得日数 | E4: =_xlfn.NETWORKDAYS.INTL(B3, B5, "0000011", B9:B13) -> 17 | G4: 着地粗利(BA含) | I4: =IFERROR(__xludf.DUMMYFUNCTION("SUM(FILTER(M20:M957, ((D20:D957=""B商談済み回答待ち"")+(D20:D957=""AA課金"")+(D20:D957=""A受注"")), F20:F957=G1))"),764000.0) -> 764000 | K4: =IFERROR(__xludf.DUMMYFUNCTION("SUM( FILTER( M20:M10122, ((D20:D10122=""B商談済み回答待ち"")+(D20:D10122=""AA課金"")+(D20:D10122=""A受注"")), F20:F10122=G1, E20:E100122=K1 ) )"),"#N/A") -> #N/A | M4: =IFERROR(__xludf.DUMMYFUNCTION("SUM( FILTER( M20:M10122, ((D20:D10122=""B商談済み回答待ち"")+(D20:D10122=""AA課金"")+(D20:D10122=""A受注"")), F20:F10122=G1, E20:E100122=M1 ) )"),764000.0) -> 764000 | O4: クリニック | P4: =IFERROR(AVERAGEIFS($M$20:$M$1123, $D$20:$D$1123, "AA課金", $E$20:$E$1123, $O4), 0) -> 354937.5 | Q4: =IFERROR(COUNTIFS($D$20:$D$1123, "AA課金", $C$20:$C$1123, $O6) / COUNTIFS($C$20:$C$1123, $O6, $D$20:$D$1123, "<>", $D$20:$D$1123, "<>無効商談", $D$20:$D$1123, "<>E商談", $D$20:$D$1123, "<>XCアポ失注", $D$20:$D$1123, "<>F日程変更中"), 0) -> 0.13445378 | R4: =IFERROR(AVERAGEIFS($W$20:$W$1123, $E$20:$E$1123, $O4, $D$20:$D$1123, "<>", $W$20:$W$1123, ">=0", $D$20:$D$1123, "<>無効商談", $D$20:$D$1123, "<>E商談", $D$20:$D$1123, "<>XCアポ失注", $D$20:$D$1123, "<>F日程変更中"), 0) -> 7.3505155 | S4: =IFERROR(AVERAGEIFS($AA$20:$AA$1123, $Y$20:$Y$1123, "<>", $E$20:$E$1123, $O4), 0) -> 8.5625 | T4: =IFERROR(AVERAGEIFS($Z$20:$Z$1123, $Y$20:$Y$1123, "<>", $E$20:$E$1123, $O4), 0) -> 13.9375 | U4: =IFERROR(AVERAGEIFS($AC$20:$AC$1123, $AB$20:$AB$1123, "<>", $E$20:$E$1123, $O4), 0) -> 14.5 | Y4: 熊本 | Z4: =( ( SUMIFS(M19:M10518, B19:B10518, Y4, F19:F10518, G1, D19:D10518, "AA課金") + SUMIFS(M19:M10518, B19:B10518, Y4, F19:F10518, G1, D19:D10518, "A受注") + SUMIFS(M19:M10518, B19:B10518, Y4, F19:F10518, G1, D19:D10518, "B商談済み回答待ち") ) / 2 ) + ( ( SUMIFS(M19:M10518, C19:C10518, Y4, F19:F10518, G1, D19:D10518, "AA課金") + SUMIFS(M19:M10518, C19:C10518, Y4, F19:F10518, G1, D19:D10518, "A受注") + SUMIFS(M19:M10518, C19:C10518, Y4, F19:F10518, G1, D19:D10518, "B商談済み回答待ち") ) / 2 ) -> 0
A5: アポ獲得期限 | B5: 46196 | C5: アポ獲得期限残り日数 | E5: =MAX(0,E4-E2+1) -> 3 | G5: 平均受注粗利 | I5: =I3/J1 -> 382000 | K5: =K3/F10 -> #DIV/0! | M5: =M3/K10 -> 382000 | P5: =IFERROR(AVERAGEIFS($M$20:$M$1123, $D$20:$D$1123, "AA課金", $C$20:$C$1123, $O5), 0) -> 0 | Q5: =IFERROR(COUNTIFS($D$20:$D$1123, "AA課金", $C$20:$C$1123, $O5) / COUNTIFS($C$20:$C$1123, $O5, $D$20:$D$1123, "<>", $D$20:$D$1123, "<>無効商談", $D$20:$D$1123, "<>E商談", $D$20:$D$1123, "<>XCアポ失注", $D$20:$D$1123, "<>F日程変更中"), 0) -> 0 | R5: =IFERROR(AVERAGEIFS($W$20:$W$1123, $C$20:$C$1123, $O5, $D$20:$D$1123, "<>", $W$20:$W$1123, ">=0", $D$20:$D$1123, "<>無効商談", $D$20:$D$1123, "<>E商談", $D$20:$D$1123, "<>XCアポ失注", $D$20:$D$1123, "<>F日程変更中"), 0) -> 0 | S5: =IFERROR(AVERAGEIFS($AA$20:$AA$1123, $Y$20:$Y$1123, "<>", $C$20:$C$1123, $O5), 0) -> 0 | T5: =IFERROR(AVERAGEIFS($Z$20:$Z$1123, $Y$20:$Y$1123, "<>", $C$20:$C$1123, $O5), 0) -> 0 | U5: =IFERROR(AVERAGEIFS($AC$20:$AC$1123, $AB$20:$AB$1123, "<>", $C$20:$C$1123, $O5), 0) -> 0
A6: 商談消化期限 | B6: 46198 | C6: 消化日数 | E6: =_xlfn.NETWORKDAYS.INTL(B3, B6, "0000011", B9:B13) -> 19 | O6: 松岡 | P6: =IFERROR(AVERAGEIFS($M$20:$M$1123, $D$20:$D$1123, "AA課金", $C$20:$C$1123, $O6), 0) -> 354937.5 | Q6: =IFERROR(COUNTIFS($D$20:$D$1123, "AA課金", $C$20:$C$1123, $O6) / COUNTIFS($C$20:$C$1123, $O6, $D$20:$D$1123, "<>", $D$20:$D$1123, "<>無効商談", $D$20:$D$1123, "<>E商談", $D$20:$D$1123, "<>XCアポ失注", $D$20:$D$1123, "<>F日程変更中"), 0) -> 0.13445378 | R6: =IFERROR(AVERAGEIFS($W$20:$W$1123, $C$20:$C$1123, $O6, $D$20:$D$1123, "<>", $W$20:$W$1123, ">=0", $D$20:$D$1123, "<>無効商談", $D$20:$D$1123, "<>E商談", $D$20:$D$1123, "<>XCアポ失注", $D$20:$D$1123, "<>F日程変更中"), 0) -> 7.0594059 | S6: =IFERROR(AVERAGEIFS($AA$20:$AA$1123, $Y$20:$Y$1123, "<>", $C$20:$C$1123, $O6), 0) -> 8.5625 | T6: =IFERROR(AVERAGEIFS($Z$20:$Z$1123, $Y$20:$Y$1123, "<>", $C$20:$C$1123, $O6), 0) -> 13.9375 | U6: =IFERROR(AVERAGEIFS($AC$20:$AC$1123, $AB$20:$AB$1123, "<>", $C$20:$C$1123, $O6), 0) -> 14.5
C7: 消化期限残り日数 | E7: =MAX(0,E6-E2+1) -> 5
A9: 休み | E9: 受注予定 | F9: =F11+F12+F10+F13 -> 0 | G9: =G11+G12+G10+G13 -> 0 | H9: クリニック | I9: 受注予定 | K9: =K11+K12+K10 -> 2 | L9: =L11+L12+L10+L13 -> 764000 | O9: 月間 | P9: 平均単価 | Q9: 受注率 | R9: アポ→商談 | S9: 商談→受注 | T9: アポ→受注 | U9: アポ→課金
E10: AA課金 | F10: =COUNTIFS(F20:F10107, G1, D20:D10107, "AA課金", E20:E10107, D9) -> 0 | G10: =SUMIFS( M20:M10107, F20:F10107, G1, D20:D10107, "AA課金", E20:E10107, D9 ) -> 0 | I10: AA課金 | K10: =COUNTIFS(F20:F10107, G1, D20:D10107, "AA課金", E20:E10107, H9) -> 2 | L10: =SUMIFS( M20:M10107, F20:F10107, G1, D20:D10107, "AA課金", E20:E10107, H9 ) -> 764000 | O10: 46174 | P10: =IFERROR(AVERAGEIFS($M$20:$M$1123, $D$20:$D$1123, "AA課金", $F$20:$F$1123, $O$10), 0) -> 382000 | Q10: =IFERROR(COUNTIFS($D$20:$D$1123, "AA課金", $F$20:$F$1123, $O$10) / COUNTIFS($F$20:$F$1123, $O$10, $D$20:$D$1123, "<>", $D$20:$D$1123, "<>無効商談", $D$20:$D$1123, "<>E商談", $D$20:$D$1123, "<>XCアポ失注", $D$20:$D$1123, "<>F日程変更中"), 0) -> 0.071428571 | R10: =IFERROR(AVERAGEIFS($W$20:$W$1123, $F$20:$F$1123, $O$10, $D$20:$D$1123, "<>", $W$20:$W$1123, ">=0", $D$20:$D$1123, "<>無効商談", $D$20:$D$1123, "<>E商談", $D$20:$D$1123, "<>XCアポ失注", $D$20:$D$1123, "<>F日程変更中"), 0) -> 9.3571429 | S10: =IFERROR(AVERAGEIFS($AA$20:$AA$1123, $F$20:$F$1123, $O$10, $Y$20:$Y$1123, "<>"), 0) -> 1 | T10: =IFERROR(AVERAGEIFS($Z$20:$Z$1123, $F$20:$F$1123, $O$10, $Y$20:$Y$1123, "<>"), 0) -> 4 | U10: =IFERROR(AVERAGEIFS($AC$20:$AC$1123, $F$20:$F$1123, $O$10, $AB$20:$AB$1123, "<>"), 0) -> 4
E11: Aヨミ | F11: =COUNTIFS(F20:F10107, G1, D20:D10107, "A受注", E20:E10107, D9) -> 0 | G11: =SUMIFS( M20:M10107, F20:F10107, G1, D20:D10107, "A受注", E20:E10107, D9 ) -> 0 | I11: Aヨミ | K11: =COUNTIFS(F20:F10107, G1, D20:D10107, "A受注", E20:E10107, H9) -> 0 | L11: =SUMIFS( M20:M10107, F20:F10107, G1, D20:D10107, "A受注", E20:E10107, H9 ) -> 0 | O11: ハウスクリーニング | P11: =IFERROR(AVERAGEIFS($M$20:$M$1123, $D$20:$D$1123, "AA課金", $F$20:$F$1123, $O$10, $E$20:$E$1123, $O11), 0) -> 0 | Q11: =IFERROR(COUNTIFS($F$20:$F$1123, $O$10, $E$20:$E$1123, $O11, $D$20:$D$1123, "AA課金") / COUNTIFS($F$20:$F$1123, $O$10, $E$20:$E$1123, $O11, $D$20:$D$1123, "<>", $D$20:$D$1123, "<>無効商談", $D$20:$D$1123, "<>E商談", $D$20:$D$1123, "<>XCアポ失注", $D$20:$D$1123, "<>F日程変更中"), 0) -> 0 | R11: =IFERROR(AVERAGEIFS($W$20:$W$1123, $F$20:$F$1123, $O$10, $E$20:$E$1123, $O11, $D$20:$D$1123, "<>", $W$20:$W$1123, ">=0", $D$20:$D$1123, "<>無効商談", $D$20:$D$1123, "<>E商談", $D$20:$D$1123, "<>XCアポ失注", $D$20:$D$1123, "<>F日程変更中"), 0) -> 0 | S11: =IFERROR(AVERAGEIFS($AA$20:$AA$1123, $F$20:$F$1123, $O$10, $Y$20:$Y$1123, "<>", $E$20:$E$1123, $O11), 0) -> 0 | T11: =IFERROR(AVERAGEIFS($Z$20:$Z$1123, $F$20:$F$1123, $O$10, $Y$20:$Y$1123, "<>", $E$20:$E$1123, $O11), 0) -> 0 | U11: =IFERROR(AVERAGEIFS($AC$20:$AC$1123, $F$20:$F$1123, $O$10, $AB$20:$AB$1123, "<>", $E$20:$E$1123, $O11), 0) -> 0
E12: Bヨミ | F12: =COUNTIFS(F20:F10107, G1, D20:D10107, "B商談済み回答待ち", E20:E10107, D9) -> 0 | G12: =SUMIFS( M20:M10107, F20:F10107, G1, D20:D10107, "B商談済み回答待ち", E20:E10107, D9 ) -> 0 | I12: Bヨミ | K12: =COUNTIFS(F20:F10107, G1, D20:D10107, "B商談済み回答待ち", E20:E10107, H9) -> 0 | L12: =SUMIFS( M20:M10107, F20:F10107, G1, D20:D10107, "B商談済み回答待ち", E20:E10107, H9 ) -> 0 | O12: クリニック | P12: =IFERROR(AVERAGEIFS($M$20:$M$1123, $D$20:$D$1123, "AA課金", $F$20:$F$1123, $O$10, $E$20:$E$1123, $O12), 0) -> 382000 | Q12: =IFERROR(COUNTIFS($F$20:$F$1123, $O$10, $E$20:$E$1123, $O12, $D$20:$D$1123, "AA課金") / COUNTIFS($F$20:$F$1123, $O$10, $E$20:$E$1123, $O12, $D$20:$D$1123, "<>", $D$20:$D$1123, "<>無効商談", $D$20:$D$1123, "<>E商談", $D$20:$D$1123, "<>XCアポ失注", $D$20:$D$1123, "<>F日程変更中"), 0) -> 0.074074074 | R12: =IFERROR(AVERAGEIFS($W$20:$W$1123, $F$20:$F$1123, $O$10, $E$20:$E$1123, $O12, $D$20:$D$1123, "<>", $W$20:$W$1123, ">=0", $D$20:$D$1123, "<>無効商談", $D$20:$D$1123, "<>E商談", $D$20:$D$1123, "<>XCアポ失注", $D$20:$D$1123, "<>F日程変更中"), 0) -> 9.6923077 | S12: =IFERROR(AVERAGEIFS($AA$20:$AA$1123, $F$20:$F$1123, $O$10, $Y$20:$Y$1123, "<>", $E$20:$E$1123, $O12), 0) -> 1 | T12: =IFERROR(AVERAGEIFS($Z$20:$Z$1123, $F$20:$F$1123, $O$10, $Y$20:$Y$1123, "<>", $E$20:$E$1123, $O12), 0) -> 4 | U12: =IFERROR(AVERAGEIFS($AC$20:$AC$1123, $F$20:$F$1123, $O$10, $AB$20:$AB$1123, "<>", $E$20:$E$1123, $O12), 0) -> 4
E13: Cヨミ | F13: =COUNTIFS(F20:F10107, G1, D20:D10107, "C商談済み回答待ち", E20:E10107, D9) -> 0 | G13: 0 | I13: Cヨミ | K13: =COUNTIFS(F20:F10107, G1, D20:D10107, "C商談済み回答待ち", E20:E10107, H9) -> 0 | L13: =SUMIFS( M20:M10107, F20:F10107, G1, D20:D10107, "C商談済み回答待ち", E20:E10107, H9 ) -> 0 | P13: =IFERROR(AVERAGEIFS($M$20:$M$1123, $D$20:$D$1123, "AA課金", $F$20:$F$1123, $O$10, $C$20:$C$1123, $O13), 0) -> 0 | Q13: =IFERROR(COUNTIFS($F$20:$F$1123, $O$10, $C$20:$C$1123, $O13, $D$20:$D$1123, "AA課金") / COUNTIFS($F$20:$F$1123, $O$10, $C$20:$C$1123, $O13, $D$20:$D$1123, "<>", $D$20:$D$1123, "<>無効商談", $D$20:$D$1123, "<>E商談", $D$20:$D$1123, "<>XCアポ失注", $D$20:$D$1123, "<>F日程変更中"), 0) -> 0 | R13: =IFERROR(AVERAGEIFS($W$20:$W$1123, $F$20:$F$1123, $O$10, $C$20:$C$1123, $O13, $D$20:$D$1123, "<>", $W$20:$W$1123, ">=0", $D$20:$D$1123, "<>無効商談", $D$20:$D$1123, "<>E商談", $D$20:$D$1123, "<>XCアポ失注", $D$20:$D$1123, "<>F日程変更中"), 0) -> 0 | S13: =IFERROR(AVERAGEIFS($AA$20:$AA$1123, $F$20:$F$1123, $O$10, $Y$20:$Y$1123, "<>", $C$20:$C$1123, $O13), 0) -> 0 | T13: =IFERROR(AVERAGEIFS($Z$20:$Z$1123, $F$20:$F$1123, $O$10, $Y$20:$Y$1123, "<>", $C$20:$C$1123, $O13), 0) -> 0 | U13: =IFERROR(AVERAGEIFS($AC$20:$AC$1123, $F$20:$F$1123, $O$10, $AB$20:$AB$1123, "<>", $C$20:$C$1123, $O13), 0) -> 0
D14: 決済者 | E14: Eヨミ（残りアポ） | F14: =COUNTIFS($E$20:$E$1125, $D$9, $D$20:$D$1125, "E商談①", $J$20:$J$1125, $D14, $F$20:$F$1125, TEXT($B$1, "yyyy年m月")) -> 0 | G14: =SUMIFS( M20:M10107, F20:F10107, G1, D20:D10107, "E商談①", E20:E10107, D9, J20:J10107, D14 ) -> 0 | I14: E2 | K14: =COUNTIFS(F20:F10107, G1, D20:D10107, "E商談②", E20:E10107, H9) -> 0 | L14: =SUMIFS( M20:M10107, F20:F10107, G1, D20:D10107, "E商談②", E20:E10107, H9 ) -> 0 | O14: 松岡 | P14: =IFERROR(AVERAGEIFS($M$20:$M$1123, $D$20:$D$1123, "AA課金", $F$20:$F$1123, $O$10, $C$20:$C$1123, $O14), 0) -> 382000 | Q14: =IFERROR(COUNTIFS($F$20:$F$1123, $O$10, $C$20:$C$1123, $O14, $D$20:$D$1123, "AA課金") / COUNTIFS($F$20:$F$1123, $O$10, $C$20:$C$1123, $O14, $D$20:$D$1123, "<>", $D$20:$D$1123, "<>無効商談", $D$20:$D$1123, "<>E商談", $D$20:$D$1123, "<>XCアポ失注", $D$20:$D$1123, "<>F日程変更中"), 0) -> 0.074074074 | R14: =IFERROR(AVERAGEIFS($W$20:$W$1123, $F$20:$F$1123, $O$10, $C$20:$C$1123, $O14, $D$20:$D$1123, "<>", $W$20:$W$1123, ">=0", $D$20:$D$1123, "<>無効商談", $D$20:$D$1123, "<>E商談", $D$20:$D$1123, "<>XCアポ失注", $D$20:$D$1123, "<>F日程変更中"), 0) -> 9.6923077 | S14: =IFERROR(AVERAGEIFS($AA$20:$AA$1123, $F$20:$F$1123, $O$10, $Y$20:$Y$1123, "<>", $C$20:$C$1123, $O14), 0) -> 1 | T14: =IFERROR(AVERAGEIFS($Z$20:$Z$1123, $F$20:$F$1123, $O$10, $Y$20:$Y$1123, "<>", $C$20:$C$1123, $O14), 0) -> 4 | U14: =IFERROR(AVERAGEIFS($AC$20:$AC$1123, $F$20:$F$1123, $O$10, $AB$20:$AB$1123, "<>", $C$20:$C$1123, $O14), 0) -> 4
D15: 非決済者 | E15: Eヨミ（残りアポ） | F15: =COUNTIFS($E$20:$E$1125, $D$9, $D$20:$D$1125, "E商談①", $J$20:$J$1125, $D15, $F$20:$F$1125, TEXT($B$1, "yyyy年m月")) -> 0 | G15: =SUMIFS( M20:M10107, F20:F10107, G1, D20:D10107, "E商談①", E20:E10107, D9, J20:J10107, E15 ) -> 0 | H15: 決済者 | I15: Eヨミ（残りアポ） | K15: =COUNTIFS($E$20:$E$1125, $H$9, $D$20:$D$1125, "E商談①", $J$20:$J$1125, $H15, $F$20:$F$1125, TEXT($B$1, "yyyy年m月")) -> 16 | L15: =SUMIFS( M20:M10107, F20:F10107, G1, D20:D10107, "E商談①", E20:E10107, H9, J20:J10107, H15 ) -> 4352000
H16: 非決済者 | I16: Eヨミ（残りアポ） | K16: =COUNTIFS($E$20:$E$1125, $H$9, $D$20:$D$1125, "E商談①", $J$20:$J$1125, $H16, $F$20:$F$1125, TEXT($B$1, "yyyy年m月")) -> 0 | L16: =SUMIFS( M20:M10107, F20:F10107, G1, D20:D10107, "E商談①", E20:E10107, H9, J20:J10107, H16 ) -> 0 | O16: 第一営業部 既存顧客
I17: 19日㈮までのアポ | K17: =COUNTIFS( E20:E10114, H9, F20:F10114, G1, R20:R10114, "<="&B6, D20:D10114, "E商談①" ) -> 15 | L17: =SUMIFS( M20:M10107, F20:F10107, G1, D20:D10107, "E商談①", E20:E10107, H9, R20:R10107, "<="&B6 ) -> 4080000 | O17: 第一営業部 KPI管理シート
A19: 完了 | B19: IS担当者 | C19: FS担当者 | D19: 進捗 （現在の進捗を書く） | E19: 業種 | F19: 計上月 | G19: 商材 | H19: 案件名 | I19: 担当者名 | J19: 役職 | K19: 初期費用 | L19: 月額費用 | M19: 粗利 | N19: 次回アクション日 | O19: 次回アクション内容 | P19: 再コ設定日 | Q19: アポ獲得日 | R19: ①商談日 | S19: アポ送信 | T19: 事前確認 | U19: ②商談日 | V19: 再コ→アポ | W19: アポ→商談 | X19: ①商談→②商談 | Y19: 受注予定日 | Z19: アポ→受注 | AA19: 商談→受注 | AB19: 課金日 | AC19: アポ→課金 | AD19: ログ
A20: TRUE | D20: AA課金 | E20: 買取専門店 | F20: 45809 | H20: おたからや 鉄砲町店 | I20: 中田→木村 | J20: 非決済者 | K20: 100000 | L20: 45000 | M20: 235000 | Q20: 45791 | R20: 45800 | W20: 9 | X20: =U20-R20 -> -45800 | AD20: 他4店舗あって良ければ2店舗で導入
A21: TRUE | D21: AA課金 | E21: ハウスクリーニング | F21: 45839 | H21: おそうじ本舗 宇都宮泉が丘店 | I21: 賀川 | J21: 決済者 | K21: 50000 | L21: 40000 | M21: 235000 | Q21: 45850 | R21: 45855 | W21: 5 | X21: =U21-R21 -> -45855
A22: TRUE | D22: AA課金 | E22: ハウスクリーニング | F22: 45870 | H22: おそうじ本舗 鶴見西店 | I22: 森本 | J22: 決済者 | K22: 100000 | L22: 45000 | M22: 235000 | Q22: 45875 | R22: 45881 | W22: 6 | X22: =U22-R22 -> -45881 | Y22: 45881 | Z22: 6 | AA22: 0 | AB22: 45881 | AC22: 6
A23: TRUE | D23: AA課金 | E23: ハウスクリーニング | F23: 45870 | H23: おそうじ革命 豊洲店 | I23: 檜垣 | J23: 決済者 | K23: 100000 | L23: 45000 | M23: 235000 | Q23: 45880 | R23: 45881 | W23: 1 | X23: =U23-R23 -> -45881 | Y23: 45882 | Z23: 2 | AA23: 1 | AB23: 45882 | AC23: 2
A24: TRUE | D24: AA課金 | E24: ハウスクリーニング | F24: 45870 | H24: おそうじ本舗 青梅インター店 | I24: 前島 | J24: 決済者 | K24: 50000 | L24: 40000 | M24: 180000 | Q24: 45873 | R24: 45874 | W24: 1 | X24: =U24-R24 -> -45874 | Y24: 45881 | Z24: 8 | AA24: 7 | AB24: 45881 | AC24: 8
A25: TRUE | D25: AA課金 | E25: ハウスクリーニング | F25: 45870 | H25: おそうじ本舗 瀬戸中水野店 | I25: 濱田 | J25: 決済者 | K25: 50000 | L25: 50000 | M25: 220000 | Q25: 45876 | R25: 45876 | W25: 0 | X25: =U25-R25 -> -45876 | Y25: 45881 | Z25: 5 | AA25: 5 | AB25: 45881 | AC25: 5
A26: TRUE | D26: AA課金 | E26: ハウスクリーニング | F26: 45870 | H26: おそうじ革命 相模原緑区若葉台店 | I26: 高橋 | J26: 決済者 | K26: 100000 | L26: 45000 | M26: 235000 | Q26: 45877 | R26: 45883 | W26: 6 | X26: =U26-R26 -> -45883 | Y26: 45883 | Z26: 6 | AA26: 0 | AB26: 45883 | AC26: 6
A27: TRUE | D27: AA課金 | E27: ハウスクリーニング | F27: 45870 | H27: おそうじ本舗 駒沢店 | I27: 伊東 | J27: 決済者 | K27: 50000 | L27: 40000 | M27: 180000 | Q27: 45871 | R27: 45874 | W27: 3 | X27: =U27-R27 -> -45874 | Y27: 45890 | Z27: 19 | AA27: 16 | AB27: 45890 | AC27: 19
A28: TRUE | D28: AA課金 | E28: 不用品回収 | F28: 45870 | H28: スペースケア | I28: 安藤 | J28: 決済者 | K28: 50000 | L28: 50000 | M28: 200000 | Q28: 45888 | R28: 45889 | W28: 1 | X28: =U28-R28 -> -45889 | Y28: 45894 | Z28: 6 | AA28: 5 | AB28: 45894 | AC28: 6 | AD28: 22000円CB 11月末
A29: TRUE | B29: 魚井 | C29: 縞谷 | D29: AA課金 | E29: ハウスクリーニング | F29: 45901 | H29: おそうじ本舗 茨木総持寺店 | I29: 藤田 | J29: 決済者 | K29: 50000 | L29: 50000 | M29: 220000 | Q29: 45895 | R29: 45901 | W29: 6 | X29: =U29-R29 -> -45901 | Y29: 45901 | Z29: 6 | AA29: 0 | AB29: 45901 | AC29: 6
A30: TRUE | B30: 魚井 | C30: 縞谷 | D30: AA課金 | E30: ハウスクリーニング | F30: 45901 | H30: おそうじ本舗 豊橋岩田店 | I30: 桜井 | J30: 決済者 | K30: 50000 | L30: 40000 | M30: 180000 | Q30: 45899 | R30: 45901 | W30: 2 | X30: =U30-R30 -> -45901 | Y30: 45901 | Z30: 2 | AA30: 0 | AB30: 45901 | AC30: 2
A31: TRUE | B31: 魚井 | C31: 縞谷 | D31: AA課金 | E31: ハウスクリーニング | F31: 45901 | H31: おそうじ本舗 榴ヶ岡店 | I31: 長田 | J31: 決済者 | K31: 100000 | L31: 45000 | M31: 235000 | Q31: 45905 | R31: 45910 | W31: 5 | X31: =U31-R31 -> -45910 | Y31: 45911 | Z31: 6 | AA31: 1 | AB31: 45911 | AC31: 6
A32: TRUE | B32: 魚井 | C32: 縞谷 | D32: AA課金 | E32: 不用品回収 | F32: 45901 | H32: 株式会社トップリユース | I32: 横田 | J32: 非決済者 | K32: 100000 | L32: 45000 | M32: 235000 | Q32: 45903 | R32: 45905 | W32: 2 | X32: =U32-R32 -> -45905 | Y32: 45905 | Z32: 2 | AA32: 0 | AB32: 45905 | AC32: 2
A33: TRUE | B33: 前川 | C33: 縞谷 | D33: AA課金 | E33: 不用品回収 | F33: 45901 | H33: エコロジーサービス長崎 | I33: 髙橋 | J33: 決済者 | K33: 100000 | L33: 45000 | M33: 235000 | Q33: 45905 | R33: 45910 | W33: 5 | X33: =U33-R33 -> -45910 | Y33: 45912 | Z33: 7 | AA33: 2 | AB33: 45912 | AC33: 7
A34: TRUE | B34: 長島 | C34: 縞谷 | D34: AA課金 | E34: ハウスクリーニング | F34: 45901 | H34: おそうじ本舗 大田店 | I34: 小畑 | J34: 決済者 | K34: 100000 | L34: 45000 | M34: 235000 | Q34: 45910 | R34: 45916 | W34: 6 | X34: =U34-R34 -> -45916 | Y34: 45916 | Z34: 6 | AA34: 0 | AB34: 45916 | AC34: 6
A35: TRUE | B35: 縞谷 | C35: 縞谷 | D35: AA課金 | E35: ハウスクリーニング | F35: 45901 | H35: おそうじ本舗 榴ヶ岡店 | I35: 長田 | J35: 決済者 | K35: 200000 | M35: 200000 | Q35: 45911 | R35: 45917 | W35: 6 | X35: =U35-R35 -> -45917 | Y35: 45919 | Z35: 8 | AA35: 2 | AB35: 45919 | AC35: 8
A36: TRUE | B36: 長島 | C36: 縞谷 | D36: AA課金 | E36: ハウスクリーニング | F36: 45901 | H36: おそうじ本舗 豊見城店 | I36: 髙江洲 | J36: 決済者 | K36: 50000 | L36: 40000 | M36: 120000 | N36: 45929 | O36: 回答 | Q36: 45905 | R36: 45929 | W36: 24 | X36: =U36-R36 -> -45929 | Y36: 45929 | Z36: 24 | AA36: 0 | AB36: 45929 | AC36: 24 | AD36: 不通（9/20）→折り返し 月3万円~5万円は高いもう電話してこんといて（9/20）
A37: TRUE | B37: 縞谷 | C37: 縞谷 | D37: AA課金 | E37: ハウスクリーニング | F37: 45901 | H37: おそうじ本舗 鶴岡北店 | I37: 横山 | J37: 決済者 | K37: 50000 | L37: 40000 | M37: 180000 | Q37: 45928 | R37: 45930 | W37: 2 | X37: =U37-R37 -> -45930
A38: TRUE | B38: 魚井 | C38: 魚井 | D38: AA課金 | E38: 不用品回収 | F38: 45962 | H38: 株式会社クリーンアップ | I38: 三宅 | J38: 決済者 | K38: 50000 | L38: 40000 | M38: 130000 | Q38: 45960 | R38: 45961 | W38: 1 | X38: =U38-R38 -> -45961 | Y38: 45968 | Z38: 8 | AA38: 7 | AB38: 45968 | AC38: 8 | AD38: 月額4万円であればありより。＞DMMで着地。月額4万円・初期費用55000円CB
A39: TRUE | B39: 前川 | C39: 縞谷 | D39: AA課金 | E39: ハウスクリーニング | F39: 45901 | H39: 東栄サービス | I39: 東野 | J39: 決済者 | K39: 50000 | L39: 50000 | M39: 220000 | N39: 45931 | O39: 契約締結 | Q39: 45922 | R39: 45923 | W39: 1 | X39: =U39-R39 -> -45923 | Y39: 45923 | Z39: 1 | AA39: 0 | AB39: 45931 | AC39: 9
A40: TRUE | B40: 縞谷 | C40: 縞谷 | D40: AA課金 | E40: 不用品回収 | F40: 45962 | H40: N・ウイング | I40: 川口 | J40: 決済者 | K40: 50000 | L40: 40000 | M40: 180000 | N40: 45987 | O40: 契約 | Q40: 45887 | R40: 45888 | W40: 1 | X40: =U40-R40 -> -45888 | Y40: 45891 | Z40: 4 | AA40: 3 | AB40: 45987 | AC40: 100
A41: TRUE | B41: 長島 | C41: 西田 | D41: AA課金 | E41: 飲食 | F41: 45962 | H41: あいろん亭 | J41: 決済者 | K41: 50000 | L41: 40000 | M41: 180000 | N41: 45991 | O41: 契約 | W41: 0 | X41: =U41-R41 -> 0 | Z41: 0 | AA41: 0 | AC41: 0
A42: TRUE | B42: 前川 | C42: 縞谷 | D42: AA課金 | E42: ハウスクリーニング | F42: 45992 | H42: おそうじ本舗 新柏駅前店 | I42: 西嶋 | J42: 決済者 | K42: 100000 | L42: 45000 | M42: 320000 | Q42: 45993 | R42: 45993 | W42: =R42-Q42 -> 0 | X42: =U42-R42 -> -45993 | Y42: 45993 | Z42: =Y42-Q42 -> 0 | AA42: =Y42-R42 -> 0 | AB42: 45993 | AC42: =AB42-Q42 -> 0
A43: TRUE | B43: 前川 | C43: 縞谷 | D43: AA課金 | E43: ハウスクリーニング | F43: 46023 | H43: おそうじ本舗 三河安城店 | I43: 中苑 | J43: 決済者 | K43: 100000 | L43: 45000 | M43: 320000 | N43: 46041 | O43: クロージング | Q43: 46037 | R43: 46038 | W43: =R43-Q43 -> 1 | X43: =U43-R43 -> -46038 | Y43: 46041 | Z43: =Y43-Q43 -> 4 | AA43: =Y43-R43 -> 3 | AB43: 46041 | AC43: =AB43-Q43 -> 4
A44: TRUE | B44: 前川 | C44: 縞谷 | D44: AA課金 | E44: ハウスクリーニング | F44: 46023 | H44: おそうじ本舗 長岡駅前店 | I44: 大川 | J44: 決済者 | K44: 100000 | L44: 45000 | M44: 320000 | N44: 46042 | O44: 契約（googleとLINEが刺さっている。） クロージング 料金だけ、いいものだとは思っている。 1月の埋まり具合で、再度検討できるかな？ | Q44: 46002 | R44: 46006 | W44: =R44-Q44 -> 4 | X44: =U44-R44 -> -46006 | Y44: 46042 | Z44: =Y44-Q44 -> 40 | AA44: =Y44-R44 -> 36 | AB44: 46042 | AC44: =AB44-Q44 -> 40
A45: TRUE | B45: 前川 | C45: 縞谷 | D45: AA課金 | E45: ハウスクリーニング | F45: 46023 | H45: おそうじ本舗 北名古屋店 | I45: 武藤 | J45: 決済者 | K45: 50000 | L45: 50000 | M45: 325000 | N45: 46045 | O45: クロージング | Q45: 46037 | R45: 46041 | W45: =R45-Q45 -> 4 | X45: =U45-R45 -> -46041 | Y45: 46045 | Z45: =Y45-Q45 -> 8 | AA45: =Y45-R45 -> 4 | AB45: 46045 | AC45: =AB45-Q45 -> 8
A46: TRUE | B46: 前川 | C46: 縞谷 | D46: AA課金 | E46: ハウスクリーニング | F46: 46054 | H46: おそうじ本舗 北上店 | I46: 古舘 | J46: 決済者 | K46: 100000 | L46: 45000 | M46: 320000 | N46: 46069 | O46: 契約 | Q46: 45971 | R46: 46050 | W46: =R46-Q46 -> 79 | X46: =U46-R46 -> -46050 | Z46: =Y46-Q46 -> -45971 | AA46: =Y46-R46 -> -46050 | AC46: =AB46-Q46 -> -45971
A47: TRUE | B47: 前川 | C47: 縞谷 | D47: AA課金 | E47: ハウスクリーニング | F47: 46082 | H47: おそうじ本舗 塩尻店 | I47: 小野 | J47: 決済者 | K47: 100000 | L47: 45000 | M47: 320000 | N47: 46086 | O47: 契約 | Q47: 46063 | R47: 46063 | S47: FALSE | T47: FALSE | W47: =R47-Q47 -> 0 | X47: =U47-R47 -> -46063 | Y47: 46086 | Z47: =Y47-Q47 -> 23 | AA47: =Y47-R47 -> 23 | AB47: 46095 | AC47: =AB47-Q47 -> 32 | AD47: キャッシュバック40000円、LP、公式LINE作成
A48: TRUE | D48: AA課金 | E48: ハウスクリーニング | F48: 45778 | H48: おそうじ本舗 帝塚山店 | I48: 中川 | J48: 決済者 | K48: 100000 | L48: 45000 | M48: 120000 | Q48: 45793 | R48: 45794 | W48: 1 | X48: =U48-R48 -> -45794 | Y48: 45794 | Z48: 1 | AA48: 0 | AB48: 45804 | AC48: 11
A49: TRUE | B49: 熊本 | C49: 松岡 | D49: AA課金 | E49: クリニック | F49: 46143 | G49: マイナビ | H49: 関沢クリニック（マイナビ） | I49: 関沢 | J49: 決済者 | K49: 280000 | L49: 60000 | M49: 712000 | N49: 46192 | O49: E1結果：次回E2 内容：マイナビ更新からMEO提案。本院は対策しなくても患者くるからそこまで必要ではないが、分院展開の予定がありそっちなら必要かも。分院はまだ着手し始めたところで開業まで1年以上ある。本来webサービスは3～5年とかで対策するが、分院展開時にwebしっかりやっていきたいなら本院でお試しの1年MEOやってみてそこでテストマーケティング図りませんかで次回。 懸念：スタッフ相談。口コミ集めのオペレーションうまくいくか。 次回アクション：マイナビ更新について、更新した際にあとから本院の掲載を分院に切り替えれるか質問あり、GW明け7日にマイナビに確認し連絡。 ーーーーーーーーーーーーーーーーーーーーーーーーーーーーーーーー 2回目結果:：次回3回目Cヨミ 内容：マイナビ28万6万＋MEO10万4.5万で進めたいとの言質はあり。経理担当の奥さんには共有必須で、奥さん確認でOKならそのまま回収×ならどうやって説得するかどうすれば通るかのコミュニケーションをとる。 懸念：奥さん相談 次回アクション：3回目商談 ーーーーーーーーーーーーーーーーーーーーーーーーーーーーーーーー 受注後 初期費用の決済：済み 月額費用の決済：5月12日 | P49: 46133 | Q49: 46133 | R49: 46143 | U49: 46160 | V49: =Q49-P49 -> 0 | W49: =R49-Q49 -> 10 | X49: =U49-R49 -> 17 | Y49: 46162 | Z49: =Y49-Q49 -> 29 | AA49: =Y49-R49 -> 19 | AB49: 46163 | AC49: =AB49-Q49 -> 30
B50: 高原 | C50: 松岡 | D50: AA課金 | E50: クリニック | F50: 46174 | G50: マイナビ | H50: 東海内科・内視鏡クリニック 岐阜各務原院 | I50: 神谷 | J50: 決済者 | K50: 100000 | L50: 30000 | M50: 172000 | O50: 初期済み、月額記事完成後設定。 | P50: 46181 | Q50: 46181 | R50: 46183 | V50: =Q50-P50 -> 0 | W50: =R50-Q50 -> 2 | X50: =U50-R50 -> -46183 | Y50: 46183 | Z50: =Y50-Q50 -> 2 | AA50: =Y50-R50 -> 0 | AB50: 46183 | AC50: =AB50-Q50 -> 2
B51: 高原 | C51: 松岡 | D51: AA課金 | E51: クリニック | F51: 46174 | G51: マイナビ | H51: えばら泌尿器科 | I51: 江原 | J51: 決済者 | K51: 280000 | L51: 50000 | M51: 592000 | N51: 46184 | O51: 初期済み、月額記事完成後設定。 | P51: 46178 | Q51: 46178 | R51: 46182 | U51: 46184 | V51: =Q51-P51 -> 0 | W51: =R51-Q51 -> 4 | X51: =U51-R51 -> 2 | Y51: 46184 | Z51: =Y51-Q51 -> 6 | AA51: =Y51-R51 -> 2 | AB51: 46184 | AC51: =AB51-Q51 -> 6
A52: TRUE | B52: 松岡 | C52: 松岡 | D52: AA課金 | E52: クリニック | F52: 46143 | G52: マイナビ | H52: むらもとクリニック | I52: 村元 | J52: 決済者 | K52: 280000 | L52: 30000 | M52: 352000 | N52: 46192 | O52: E1結果：次回E2 内容：マイナビ 名古屋×高血圧提案。28万6万では患者の来院の波を考えると費用対効果とりきれるか見えないと。 月3万なら対効果は見えそうだが、値下げ交渉でその場のイエスとれず時間切れもあり次回に。 懸念：データ提示で費用対効果をイメージできていない。 次回アクション：次回E2 ーーーーーーーーーーーーーーーーーーーーーーーーーーーーーーーー 2回目結果:： 内容： 懸念： 次回アクション： ーーーーーーーーーーーーーーーーーーーーーーーーーーーーーーーー 受注後 初期費用の決済：済み 月額費用の決済：5月12日 | P52: 46168 | Q52: 46168 | R52: 46169 | S52: FALSE | T52: FALSE | U52: 46171 | V52: =Q52-P52 -> 0 | W52: =R52-Q52 -> 1 | X52: =U52-R52 -> 2 | Y52: 46171 | Z52: =Y52-Q52 -> 3 | AA52: =Y52-R52 -> 2 | AB52: 46171 | AC52: =AB52-Q52 -> 3
A53: TRUE | B53: 高原 | C53: 松岡 | D53: AA課金 | E53: クリニック | F53: 46143 | G53: マイナビ | H53: 町田ながほり眼科 | I53: 永堀 | J53: 決済者 | K53: 200000 | L53: 30000 | M53: 272000 | N53: 46192 | O53: マイナビ町田市×白内障受注。翌日20日に振り込み。 月額クレカ来月12日登録。 | P53: 46156 | Q53: 46156 | R53: 46161 | S53: FALSE | T53: FALSE | U53: 46161 | V53: =Q53-P53 -> 0 | W53: =R53-Q53 -> 5 | X53: =U53-R53 -> 0 | Y53: 46161 | Z53: =Y53-Q53 -> 5 | AA53: =Y53-R53 -> 0 | AB53: 46163 | AC53: =AB53-Q53 -> 7
A54: TRUE | B54: 熊本 | C54: 松岡 | D54: AA課金 | E54: クリニック | F54: 46143 | G54: マイナビ | H54: 鴻巣北本内科クリニック | I54: 石坂 | J54: 決済者 | K54: 360000 | L54: 0 | M54: 72000 | N54: 46168 | O54: 初期36万、月額0万受注。月額クレカ登録不要。 | P54: 46161 | Q54: 46161 | R54: 46170 | S54: FALSE | T54: FALSE | U54: 46170 | V54: =Q54-P54 -> 0 | W54: =R54-Q54 -> 9 | X54: =U54-R54 -> 0 | Y54: 46170 | Z54: =Y54-Q54 -> 9 | AA54: =Y54-R54 -> 0 | AB54: 46170 | AC54: =AB54-Q54 -> 9
A55: TRUE | B55: 縞谷 | C55: 縞谷 | D55: AA課金 | E55: ハウスクリーニング | F55: 46113 | G55: MEO | H55: おそうじ本舗 守山志段味店 | I55: 長坪 | J55: 決済者 | K55: 100000 | L55: 45000 | M55: 320000 | Q55: 46118 | R55: 46119 | S55: FALSE | T55: FALSE | W55: =R55-Q55 -> 1 | X55: =U55-R55 -> -46119 | Z55: =Y55-Q55 -> -46118 | AA55: =Y55-R55 -> -46119 | AC55: =AB55-Q55 -> -46118
A56: TRUE | B56: 熊本 | C56: 松岡 | D56: AA課金 | E56: クリニック | F56: 46143 | G56: マイナビ | H56: すぎもと眼科 | I56: 杉本 | J56: 決済者 | K56: 280000 | L56: 30000 | M56: 352000 | N56: 46192 | O56: E1結果：次回E2 内容：地域的に広告不要派で今までweb広告はほぼなし。数値提示と患者の検索動向から検討土台には載っているがクリックして本当に来院しているのかは懐疑的な反応。 懸念：白内障は一般的なたんか、お姉さん相談あり 次回アクション：E2 ーーーーーーーーーーーーーーーーーーーーーーーーーーーーーーーー 2回目結果:： 内容： 懸念： 次回アクション： ーーーーーーーーーーーーーーーーーーーーーーーーーーーーーーーー 受注後 初期費用の決済：済み 月額費用の決済：5月12日 | P56: 46157 | Q56: 46157 | R56: 46167 | S56: FALSE | T56: FALSE | U56: 46169 | V56: =Q56-P56 -> 0 | W56: =R56-Q56 -> 10 | X56: =U56-R56 -> 2 | Y56: 46169 | Z56: =Y56-Q56 -> 12 | AA56: =Y56-R56 -> 2 | AB56: 46169 | AC56: =AB56-Q56 -> 12
A57: TRUE | B57: 高原 | C57: 松岡 | D57: AA課金 | E57: クリニック | F57: 46143 | G57: マイナビ | H57: 熊本みなとクリニック 内科・内視鏡内科 | I57: 岩﨑 | J57: 決済者 | K57: 200000 | L57: 30000 | M57: 272000 | N57: 46192 | O57: E1結果：次回E2 内容： 懸念：事務長に相談する、外部の人で医院にはいない為同席できない。 次回アクション：次回E2 ーーーーーーーーーーーーーーーーーーーーーーーーーーーーーーーー 2回目結果:： 内容： 懸念： 次回アクション： ーーーーーーーーーーーーーーーーーーーーーーーーーーーーーーーー 受注後 初期費用の決済：済み 月額費用の決済：5月12日 | P57: 46140 | Q57: 46157 | R57: 46168 | U57: 46170 | V57: =Q57-P57 -> 17 | W57: =R57-Q57 -> 11 | X57: =U57-R57 -> 2 | Y57: 46171 | Z57: =Y57-Q57 -> 14 | AA57: =Y57-R57 -> 3 | AB57: 46172 | AC57: =AB57-Q57 -> 15
A58: TRUE | B58: 熊本 | C58: 松岡 | D58: AA課金 | E58: クリニック | F58: 46143 | G58: MEO | H58: 関沢クリニック（MEO） | I58: 関沢 | J58: 決済者 | K58: 100000 | L58: 45000 | M58: 320000 | N58: 46164 | O58: E1結果：次回E2 内容：マイナビ更新からMEO提案。本院は対策しなくても患者くるからそこまで必要ではないが、分院展開の予定がありそっちなら必要かも。分院はまだ着手し始めたところで開業まで1年以上ある。本来webサービスは3～5年とかで対策するが、分院展開時にwebしっかりやっていきたいなら本院でお試しの1年MEOやってみてそこでテストマーケティング図りませんかで次回。 懸念：スタッフ相談。口コミ集めのオペレーションうまくいくか。 次回アクション：マイナビ更新について、更新した際にあとから本院の掲載を分院に切り替えれるか質問あり、GW明け7日にマイナビに確認し連絡。 ーーーーーーーーーーーーーーーーーーーーーーーーーーーーーーーー 2回目結果:：次回3回目Cヨミ 内容：マイナビ28万6万＋MEO10万4.5万で進めたいとの言質はあり。経理担当の奥さんには共有必須で、奥さん確認でOKならそのまま回収×ならどうやって説得するかどうすれば通るかのコミュニケーションをとる。 懸念：奥さん相談 次回アクション：3回目商談 ーーーーーーーーーーーーーーーーーーーーーーーーーーーーーーーー 受注後 初期費用の決済：済み 月額費用の決済：済み | P58: 46133 | Q58: 46133 | R58: 46143 | S58: FALSE | T58: FALSE | U58: 46160 | V58: =Q58-P58 -> 0 | W58: =R58-Q58 -> 10 | X58: =U58-R58 -> 17 | Y58: 46162 | Z58: =Y58-Q58 -> 29 | AA58: =Y58-R58 -> 19 | AB58: 46163 | AC58: =AB58-Q58 -> 30
A59: TRUE | B59: 高原 | C59: 松岡 | D59: AA課金 | E59: クリニック | F59: 46143 | G59: MEO | H59: 梅田血管外科クリニック | I59: 古林 | J59: 決済者 | K59: 100000 | L59: 45000 | M59: 320000 | N59: 46175 | O59: マイナビからMEO提案。興味はあるが詰め切れずで次回MEO再度提案。 院長は前向きとの発言ありだが、院長自身がやっているコンサル会社の社長への相談は必須とのことで、 週末その社長とご飯の際に相談して来週。→17日に電話、明日の夜相談相手と話すとのこと、お送りした資料見たうえで前向きに相談はしてくれるそう。→次回20日㈪のアポ。 KPI 1日10人のお客さんを獲得していきたい。 2回目のMEOの提案を行なって、先生が資本入れてる可能性ありのコンサル会社の社長に相談が必須 最後の商談15日で17日に電話をして、資料送って相談してください。 3回目面談入室なく明日電話にて再調整。 ＞4/21電話にて調整済 →22日に電話、コンサルからはMEO対策はいいが料金高いのではとの話、コンサルが別のMEO業者の話を今週聞いてきてくれるそうで、 来週月曜日それも踏まえて話そうと。いつMEO業者の話を聞くのかと、どこの業者かはわからないと。 24日㈮にその話どうなったか確認の電話。 24に電話したが、まだコンサルから会社どこか内容について連絡ないと。 3回目商談で、コンサルからの連絡がなかった為、WBSで今後の流れすり合わせし5月11日に再度面談。 梅田血管外科クリニック様 →次回アクション 5月1日に業者の連絡入ったか確認。 1日時点で業者の連絡はあったそうだが、日程は決まっていないGW明け確認で連絡。 2日㈫ 17時にクレカ登録、電話にて。 | P59: 46121 | Q59: 46122 | R59: 46125 | S59: FALSE | T59: FALSE | U59: 46127 | V59: =Q59-P59 -> 1 | W59: =R59-Q59 -> 3 | X59: =U59-R59 -> 2 | Y59: 46172 | Z59: =Y59-Q59 -> 50 | AA59: =Y59-R59 -> 47 | AB59: 46175 | AC59: =AB59-Q59 -> 53
A60: TRUE | B60: 高原 | C60: 松岡 | D60: AA課金 | E60: クリニック | F60: 46113 | G60: アンケート | H60: むさしの内視鏡・胃腸内科クリニック | I60: 友利 | J60: 決済者 | K60: 50000 | L60: 15000 | M60: 590000 | N60: 46162 | O60: マイナビ既存への提案。マイナビはGENOVA経由で契約。 集客対策の話からＭＥＯ提案につなげるとアンケートシステムに反応あり。 現状、ドクターや看護師の対応や定性を図る為に、紙のアンケートを使って開業時から集計しており、事務が毎度手打ちでまとめている。 また口コミを増やす対策として院内にＱＲコードの設置もあり。 上記のアンケートと口コミ機能が一つになったアンケートツール単体ならありとのことで次回提供可能か持ってきますで終話。 24日電話にて、クラウドサインとクレカ登録。→30日にヒアリングミーティング、納品後月額クレカ登録。→納品目途確認。 5月15日納品予定→同日クレカ登録。 納品＋運用方法のレクチャーMTGでクレカ登録。日程調整中。 20日に初回レクチャーのMTG設定、同日クレカ登録。→月額クレカ登録済み。 | P60: 46129 | Q60: 46129 | R60: 46133 | S60: FALSE | T60: FALSE | U60: 46135 | V60: =Q60-P60 -> 0 | W60: =R60-Q60 -> 4 | X60: =U60-R60 -> 2 | Y60: 46136 | Z60: =Y60-Q60 -> 7 | AA60: =Y60-R60 -> 3 | AB60: 46136 | AC60: =AB60-Q60 -> 7
B61: 高原 | C61: 松岡 | D61: E商談① | E61: クリニック | F61: 46204 | G61: マイナビ | H61: 吉岡医院 | I61: 吉岡 | J61: 決済者 | K61: 200000 | L61: 30000 | M61: 272000 | O61: E1結果： 内容： 懸念： 次回アクション： ーーーーーーーーーーーーーーーーーーーーーーーーーーーーーーーー 2回目結果:： 内容： 懸念： 次回アクション： ーーーーーーーーーーーーーーーーーーーーーーーーーーーーーーーー 受注後 初期費用の決済： 月額費用の決済： | P61: 46178 | Q61: 46178 | R61: 46205 | V61: =Q61-P61 -> 0 | W61: =R61-Q61 -> 27 | X61: =U61-R61 -> -46205
A62: TRUE | B62: 高原 | C62: 松岡 | D62: AA課金 | E62: クリニック | F62: 46113 | G62: マイナビ | H62: さとり循環器・内科クリニック | I62: 佐鳥 | J62: 決済者 | K62: 280000 | L62: 30000 | M62: 352000 | N62: 46171 | O62: E1結果：次回E2 内容：入室おくれ5分ほどで概要説明。28万と月6万提示で高いとなったが、月3万初期20万なら検討範囲と。次の商談があったため、検討可能なら次回面談で費用対効果とれるか判断してで次回に。 懸念：不明。ヒアリングなく概要と料金提示のみ。 次回アクション：次回面談で想定数値と想定利益を提示。 ーーーーーーーーーーーーーーーー 2回目結果:：次回3回目5月30日 内容：初期28万、月額3万でマイナビ前橋市×循環器提案。料金月額下げて問題ないと、費用対効果は想定利益からイメージもついたとのこと。最終事務の方に相談して決めると、事務の方は同席できない。 事務の方に相談するのは第三者の意見も聞きたいから、事務はwebに詳しいわけではない。 懸念：事務方へ相談 次回アクション：30日に前回商談で確認した単価と利益率から再度推定利益算出し提示。 ーーーーーーーーーーーーーーーー 修正連絡有り→修正後、月額クレカ登録。 | P62: 46128 | Q62: 46133 | R62: 46136 | S62: FALSE | T62: FALSE | U62: 46139 | V62: =Q62-P62 -> 5 | W62: =R62-Q62 -> 3 | X62: =U62-R62 -> 3 | Y62: 46142 | Z62: =Y62-Q62 -> 9 | AA62: =Y62-R62 -> 6 | AB62: 46140 | AC62: =AB62-Q62 -> 7
A63: FALSE | B63: 松岡 | C63: 縞谷 | D63: C商談済み回答待ち | E63: ハウスクリーニング | F63: 46143 | G63: MEO | H63: ハウスコーティング旭川 | I63: 伊藤 | J63: 決済者 | K63: 50000 | L63: 40000 | M63: 265000 | N63: 46161 | O63: 法人開拓のサービスを別で最近始めた、キャパ的に対応できないのが嫌なのでそれみたからやりたい、お金的には問題ないとのこと 8月くらいから検討したいかなとのこと | Q63: 46092 | R63: 46098 | S63: TRUE | T63: FALSE | V63: =Q63-P63 -> 46092 | W63: =R63-Q63 -> 6 | X63: =U63-R63 -> -46098 | Z63: =Y63-Q63 -> -46092 | AA63: =Y63-R63 -> -46098 | AC63: =AB63-Q63 -> -46092
A64: FALSE | B64: 前川 | C64: 縞谷 | D64: C商談済み回答待ち | E64: ハウスクリーニング | F64: 46143 | G64: MEO | H64: おそうじ本舗 天王寺真田山店 | I64: 山本 | J64: 決済者 | K64: 50000 | L64: 40000 | M64: 180000 | N64: 46161 | O64: 口コミいけてるかの確認、時間的に大丈夫かの確認→進捗確認 | S64: FALSE | T64: FALSE | V64: =Q64-P64 -> 0 | W64: =R64-Q64 -> 0 | X64: =U64-R64 -> 0 | Z64: =Y64-Q64 -> 0 | AA64: =Y64-R64 -> 0 | AC64: =AB64-Q64 -> 0
A65: TRUE | B65: 松岡 | C65: 松岡 | D65: AA課金 | E65: クリニック | F65: 46113 | G65: マイナビ | H65: いわもと内科おなかクリニック | I65: 岩本 | J65: 決済者 | K65: 100000 | L65: 30000 | M65: 172000 | N65: 46142 | O65: 記事完成後フォーム発行して、月額のクレカ登録未。 →17日に記事完成してメール。 → 23日にヒアリングミーティング →ミーティングにて記事打ち合わせは問題なし。記事公開後クレカ登録。 マイナビに公開日確認して、公開後にクレカ登録。 →28日に記事公開とクレカリンクを共有。30日なっても登録まだの場合電話にて催促。 月額クレカ登録済み。 | P65: 46113 | Q65: 46113 | R65: 46118 | S65: TRUE | T65: FALSE | U65: 46120 | V65: =Q65-P65 -> 0 | W65: =R65-Q65 -> 5 | X65: =U65-R65 -> 2 | Y65: 46120 | Z65: =Y65-Q65 -> 7 | AA65: =Y65-R65 -> 2 | AB65: 46120 | AC65: =AB65-Q65 -> 7
A66: FALSE | B66: 松岡 | C66: 縞谷 | D66: D商談済み回答待ち | E66: ハウスクリーニング | F66: 46235 | G66: MEO | H66: おそうじ本舗 深谷駅前店 | I66: 瀧川 | J66: 決済者 | K66: 50000 | L66: 40000 | M66: 180000 | N66: 46251 | O66: 進捗確認 | Q66: 46085 | R66: 46087 | S66: TRUE | T66: TRUE | W66: =R66-Q66 -> 2 | X66: =U66-R66 -> -46087 | Z66: =Y66-Q66 -> -46085 | AA66: =Y66-R66 -> -46087 | AC66: =AB66-Q66 -> -46085 | AD66: お金がなさすぎてできない、公庫も融資をしてもらえなかった、一年見てみたいようなので落ち着いたお盆明けで連絡
A67: FALSE | B67: 前川 | C67: 縞谷 | D67: D商談済み回答待ち | E67: ハウスクリーニング | F67: 46235 | H67: おそうじ革命 千葉流山おおたかの森店 | I67: 小川 | J67: 決済者 | K67: 100000 | L67: 45000 | M67: 320000 | N67: 46251 | O67: 1/26 進捗確認→回答（お金だけネック、内容おっけい、奥さんに金額相談している。）→お父さんがんで忙しい。内容めっちゃいいしやりたかったけどごめん。また半年後とかに連絡ちょうだい | Q67: 46038 | R67: 46044 | W67: =R67-Q67 -> 6 | X67: =U67-R67 -> -46044 | Z67: =Y67-Q67 -> -46038 | AA67: =Y67-R67 -> -46044 | AC67: =AB67-Q67 -> -46038
A68: TRUE | B68: 高原 | C68: 松岡 | D68: AA課金 | E68: クリニック | F68: 46113 | G68: MEO | H68: 心斎橋藤井クリニック | I68: 藤井 | J68: 決済者 | K68: 50000 | L68: 50000 | M68: 325000 | N68: 46132 | O68: 次回2回目面談。KWは形成外科で、形成の手術はなんでも見たい。 →次回3回目面談、料金提示まで終わり口コミ集めのオペレーションについてと細かい部分を詰める。→4回目面談で導入決まり、次回回収。→アカウント凍結時の費用について要望がありランバード確認後、20日に改めて回収。 | P68: 46115 | Q68: 46115 | R68: 46115 | S68: FALSE | T68: FALSE | U68: 46118 | V68: =Q68-P68 -> 0 | W68: =R68-Q68 -> 0 | X68: =U68-R68 -> 3 | Y68: 46132 | Z68: =Y68-Q68 -> 17 | AA68: =Y68-R68 -> 17 | AB68: 46132 | AC68: =AB68-Q68 -> 17
A69: TRUE | B69: 高原 | C69: 松岡 | D69: AA課金 | E69: クリニック | F69: 46113 | G69: マイナビ | H69: ふくろう内科・内視鏡クリニック（マイナビ6万値引き案件） | I69: 松下 | J69: 決済者 | K69: 200000 | L69: 30000 | M69: 332000 | N69: 46162 | O69: 高田馬場×消化器内科更新で提案。 内容検討はできるがDF最近始めたり今までいろいろ施策やってきたこともあり減らしていきたい意向もあり。 次回想定データと料金提示。 2回目商談→ 高田馬場での患者数を1.5倍にしたい目標。 現状、暇な人埋まっている日とでばらつきがある。開業当初は新宿区のMedical DOCやったりもしたが、今は高田馬場で絞る意識。 実際に更新した場合の想定数値を説明し、ポータルサイトで比較検討段階の層の取りこぼし防止の案内については、内容はOKですかでイエスあり。 懸念としては、初期20万と実際どういう記事つくるかイメージわかない。→初期20のネックとどういう記事を展開するかイメージ持てたら進めていただけますかでイエスあり。 初期20はなんで20かかるかの資料を使い説明済み。記事については東京の他の事例をその場でお見せ。次回実際に先生が記事つくるとしたらの草案もってきて、初期も納得いただけたら進めさせていただきますで終話。 次回アクション27日の商談まえに、明後日24日にメールにてマイナビの事例をいくつかお送りし、見といてくださいで週明け迎える。→ 今日明日送らない理由は、週末はさんでマイナビの件を忘れる前のタイミングでのリマインドが目的。→初期費用20万円は振込期日30日、月額は記事制作5月15日公開で、5月15日に登録。→月額クレカ登録済み。 | P69: 46120 | Q69: 46120 | R69: 46128 | S69: FALSE | T69: FALSE | U69: 46134 | V69: =Q69-P69 -> 0 | W69: =R69-Q69 -> 8 | X69: =U69-R69 -> 6 | Y69: 46139 | Z69: =Y69-Q69 -> 19 | AA69: =Y69-R69 -> 11 | AB69: 46142 | AC69: =AB69-Q69 -> 22
C70: 松岡 | D70: E商談① | S70: FALSE | T70: FALSE | V70: =Q70-P70 -> 0 | W70: =R70-Q70 -> 0 | X70: =U70-R70 -> 0 | Z70: =Y70-Q70 -> 0 | AA70: =Y70-R70 -> 0 | AC70: =AB70-Q70 -> 0
A71: TRUE | B71: 高原 | C71: 松岡 | D71: AA課金 | E71: クリニック | F71: 46113 | G71: マイナビ | H71: 桜のみち内科クリニック | I71: 室 | J71: 決済者 | K71: 280000 | L71: 40000 | M71: 472000 | N71: 46162 | O71: E1結果：次回E2 内容：マイナビの更新案内、カメラ件数の増患は求めている。料金28万6万提示で、次商談がある兼ね合いで次回に。 懸念：不明 次回アクション：2回目商談で再営業、マイナビ経由でのクリニック選びの重要性と定量面の効果を提示。 ーーーーーーーーーーーーーーーー 2回目結果:： 内容： 懸念： 次回アクション： ーーーーーーーーーーーーーーーー 月額クレカ登録済み。 | P71: 46135 | Q71: 46135 | R71: 46136 | S71: FALSE | T71: FALSE | U71: 46140 | V71: =Q71-P71 -> 0 | W71: =R71-Q71 -> 1 | X71: =U71-R71 -> 4 | Y71: 46140 | Z71: =Y71-Q71 -> 5 | AA71: =Y71-R71 -> 4 | AB71: 46140 | AC71: =AB71-Q71 -> 5
A72: FALSE | B72: 高原 | C72: 松岡 | D72: D商談済み回答待ち | E72: クリニック | F72: 46174 | G72: MEO | H72: 高田Ysクリニック泌尿器科・内科 | I72: 保田 | J72: 決済者 | K72: 200000 | L72: 30000 | M72: 272000 | N72: 46195 | O72: E1結果：E2日程調整中 内容：マイナビは冒頭×不信感強め。 本日は提案しませんのスタンスから、ポータルサイトで効果でない理由はMEOでの取りこぼしと指摘しMEO提案に。次回改めてMEO提案。 懸念： 次回アクション：16日にメール送信→返信ない場合17日追い。 ーーーーーーーーーーーーーーーーーーーーーーーーーーーーーーーー 2回目結果:： 内容： 懸念： 次回アクション： ーーーーーーーーーーーーーーーーーーーーーーーーーーーーーーーー 受注後 初期費用の決済： 月額費用の決済： | P72: 46183 | Q72: 46183 | R72: 46184 | V72: =Q72-P72 -> 0 | W72: =R72-Q72 -> 1 | X72: =U72-R72 -> -46184
A73: FALSE | B73: 松岡 | C73: 松岡 | D73: D商談済み回答待ち | E73: クリニック | F73: 46174 | G73: マイナビ | H73: 学園前きたにクリニック | I73: 木谷 | J73: 決済者 | K73: 280000 | L73: 50000 | M73: 592000 | N73: 46198 | O73: E1結果：E2 内容：SEOとMEO対策のみ、ポータルサイトは営業よく来るがどこがいいかわからない。1年で料金提示まで行い、費用対効果合うかのイメージ感だけだったので、次回E2。ポリペクリス60％。相談者いない。 懸念： 次回アクション： ーーーーーーーーーーーーーーーーーーーーーーーーーーーーーーーー 2回目結果:： 内容： 懸念： 次回アクション： ーーーーーーーーーーーーーーーーーーーーーーーーーーーーーーーー 受注後 初期費用の決済： 月額費用の決済： | P73: 46181 | Q73: 46181 | R73: 46188
A74: FALSE | B74: 松岡 | C74: 松岡 | D74: E商談① | E74: クリニック | F74: 46174 | G74: マイナビ | H74: 太田内科クリニック | I74: 太田 | J74: 決済者 | K74: 200000 | L74: 30000 | M74: 272000 | O74: E1結果： 内容： 懸念： 次回アクション： ーーーーーーーーーーーーーーーーーーーーーーーーーーーーーーーー 2回目結果:： 内容： 懸念： 次回アクション： ーーーーーーーーーーーーーーーーーーーーーーーーーーーーーーーー 受注後 初期費用の決済： 月額費用の決済： | P74: 46174 | Q74: 46174 | R74: 46192 | V74: =Q74-P74 -> 0 | W74: =R74-Q74 -> 18 | X74: =U74-R74 -> -46192
A75: TRUE | B75: 高原 | C75: 松岡 | D75: 無効商談 | E75: クリニック | F75: 46174 | G75: マイナビ | H75: 丸の内医院 | I75: 森 | J75: 決済者 | K75: 200000 | L75: 30000 | M75: 272000 | O75: E1結果： 内容： 懸念： 次回アクション： ーーーーーーーーーーーーーーーーーーーーーーーーーーーーーーーー 2回目結果:： 内容： 懸念： 次回アクション： ーーーーーーーーーーーーーーーーーーーーーーーーーーーーーーーー 受注後 初期費用の決済： 月額費用の決済： | P75: 46184 | Q75: 46184 | R75: 46192 | V75: =Q75-P75 -> 0 | W75: =R75-Q75 -> 8 | X75: =U75-R75 -> -46192
A76: FALSE | B76: 松岡 | C76: 松岡 | D76: E商談① | E76: クリニック | F76: 46174 | G76: マイナビ | H76: あかつき腎泌尿器科 戸田公園 | I76: 小野原 | J76: 決済者 | K76: 200000 | L76: 30000 | M76: 272000 | O76: E1結果： 内容： 懸念： 次回アクション： ーーーーーーーーーーーーーーーーーーーーーーーーーーーーーーーー 2回目結果:： 内容： 懸念： 次回アクション： ーーーーーーーーーーーーーーーーーーーーーーーーーーーーーーーー 受注後 初期費用の決済： 月額費用の決済： | P76: 46183 | Q76: 46183 | R76: 46195
A77: FALSE | B77: 高原 | C77: 松岡 | D77: E商談① | E77: クリニック | F77: 46174 | G77: マイナビ | H77: 佃リバーシティ皮膚科 | I77: 谷戸 | J77: 決済者 | K77: 200000 | L77: 30000 | M77: 272000 | O77: E1結果： 内容： 懸念： 次回アクション： ーーーーーーーーーーーーーーーーーーーーーーーーーーーーーーーー 2回目結果:： 内容： 懸念： 次回アクション： ーーーーーーーーーーーーーーーーーーーーーーーーーーーーーーーー 受注後 初期費用の決済： 月額費用の決済： | P77: 46184 | Q77: 46184 | R77: 46195 | V77: =Q77-P77 -> 0 | W77: =R77-Q77 -> 11 | X77: =U77-R77 -> -46195
A78: FALSE | B78: 松岡 | C78: 松岡 | D78: E商談① | E78: クリニック | F78: 46174 | G78: マイナビ | H78: せんだ・クリニック | I78: 千田 | J78: 決済者 | K78: 200000 | L78: 30000 | M78: 272000 | O78: E1結果： 内容： 懸念： 次回アクション： ーーーーーーーーーーーーーーーーーーーーーーーーーーーーーーーー 2回目結果:： 内容： 懸念： 次回アクション： ーーーーーーーーーーーーーーーーーーーーーーーーーーーーーーーー 受注後 初期費用の決済： 月額費用の決済： | P78: 46185 | Q78: 46185 | R78: 46199
A79: FALSE | B79: 高原 | C79: 松岡 | D79: E商談① | E79: クリニック | F79: 46174 | G79: マイナビ | H79: 本駒込耳鼻咽喉科 | I79: 吉越 | J79: 決済者 | K79: 200000 | L79: 30000 | M79: 272000 | O79: E1結果： 内容： 懸念： 次回アクション： ーーーーーーーーーーーーーーーーーーーーーーーーーーーーーーーー 2回目結果:： 内容： 懸念： 次回アクション： ーーーーーーーーーーーーーーーーーーーーーーーーーーーーーーーー 受注後 初期費用の決済： 月額費用の決済： | P79: 46189 | Q79: 46189 | R79: 46196 | V79: =Q79-P79 -> 0 | W79: =R79-Q79 -> 7 | X79: =U79-R79 -> -46196
A80: TRUE | B80: 高原 | C80: 松岡 | D80: 無効商談 | E80: クリニック | F80: 46174 | G80: マイナビ | H80: かくむクリニック | I80: 各務 | J80: 決済者 | K80: 200000 | L80: 30000 | M80: 272000 | O80: E1結果： 内容： 懸念： 次回アクション： ーーーーーーーーーーーーーーーーーーーーーーーーーーーーーーーー 2回目結果:： 内容： 懸念： 次回アクション： ーーーーーーーーーーーーーーーーーーーーーーーーーーーーーーーー 受注後 初期費用の決済： 月額費用の決済： | P80: 46189 | Q80: 46189 | R80: 46192 | V80: =Q80-P80 -> 0 | W80: =R80-Q80 -> 3 | X80: =U80-R80 -> -46192
A81: FALSE | B81: 松岡 | C81: 松岡 | D81: E商談① | E81: クリニック | F81: 46174 | G81: マイナビ | H81: 西大寺駅前A皮膚科 | I81: 鶴田 | J81: 決済者 | K81: 200000 | L81: 30000 | M81: 272000 | O81: E1結果： 内容： 懸念： 次回アクション： ーーーーーーーーーーーーーーーーーーーーーーーーーーーーーーーー 2回目結果:： 内容： 懸念： 次回アクション： ーーーーーーーーーーーーーーーーーーーーーーーーーーーーーーーー 受注後 初期費用の決済： 月額費用の決済： | P81: 46189 | Q81: 46189 | R81: 46196 | S81: FALSE | T81: FALSE
A82: FALSE | B82: 高原 | C82: 松岡 | D82: E商談① | E82: クリニック | F82: 46174 | G82: マイナビ | H82: 加藤医院 | I82: 加藤 | J82: 決済者 | K82: 200000 | L82: 30000 | M82: 272000 | O82: E1結果： 内容： 懸念： 次回アクション： ーーーーーーーーーーーーーーーーーーーーーーーーーーーーーーーー 2回目結果:： 内容： 懸念： 次回アクション： ーーーーーーーーーーーーーーーーーーーーーーーーーーーーーーーー 受注後 初期費用の決済： 月額費用の決済： | P82: 46189 | Q82: 46189 | R82: 46196 | V82: =Q82-P82 -> 0 | W82: =R82-Q82 -> 7 | X82: =U82-R82 -> -46196
A83: FALSE | B83: 松岡 | C83: 松岡 | D83: E商談① | E83: クリニック | F83: 46174 | G83: マイナビ | H83: 小関産婦人科医院 | I83: 小関 | J83: 決済者 | K83: 200000 | L83: 30000 | M83: 272000 | O83: E1結果： 内容： 懸念： 次回アクション： ーーーーーーーーーーーーーーーーーーーーーーーーーーーーーーーー 2回目結果:： 内容： 懸念： 次回アクション： ーーーーーーーーーーーーーーーーーーーーーーーーーーーーーーーー 受注後 初期費用の決済： 月額費用の決済： | P83: 46190 | Q83: 46190 | R83: 46197 | S83: FALSE | T83: FALSE
A84: FALSE | B84: 松岡 | C84: 松岡 | D84: E商談① | E84: クリニック | F84: 46174 | G84: マイナビ | H84: みどりの風クリニック | I84: 川原 | J84: 決済者 | K84: 200000 | L84: 30000 | M84: 272000 | O84: E1結果： 内容： 懸念： 次回アクション： ーーーーーーーーーーーーーーーーーーーーーーーーーーーーーーーー 2回目結果:： 内容： 懸念： 次回アクション： ーーーーーーーーーーーーーーーーーーーーーーーーーーーーーーーー 受注後 初期費用の決済： 月額費用の決済： | P84: 46190 | Q84: 46190 | R84: 46192 | S84: FALSE | T84: FALSE
A85: FALSE | B85: 松岡 | C85: 松岡 | D85: E商談① | E85: クリニック | F85: 46174 | G85: マイナビ | H85: いるかクリニック | I85: 三枝 | J85: 決済者 | K85: 200000 | L85: 30000 | M85: 272000 | O85: E1結果： 内容： 懸念： 次回アクション： ーーーーーーーーーーーーーーーーーーーーーーーーーーーーーーーー 2回目結果:： 内容： 懸念： 次回アクション： ーーーーーーーーーーーーーーーーーーーーーーーーーーーーーーーー 受注後 初期費用の決済： 月額費用の決済： | P85: 46190 | Q85: 46190 | R85: 46196 | S85: FALSE | T85: FALSE
A86: FALSE | B86: 松岡 | C86: 松岡 | D86: E商談① | E86: クリニック | F86: 46174 | G86: マイナビ | H86: とだ耳鼻咽喉科 | I86: 戸田 | J86: 決済者 | K86: 200000 | L86: 30000 | M86: 272000 | O86: E1結果： 内容： 懸念： 次回アクション： ーーーーーーーーーーーーーーーーーーーーーーーーーーーーーーーー 2回目結果:： 内容： 懸念： 次回アクション： ーーーーーーーーーーーーーーーーーーーーーーーーーーーーーーーー 受注後 初期費用の決済： 月額費用の決済： | P86: 46191 | Q86: 46191 | R86: 46195 | S86: FALSE | T86: FALSE
A87: FALSE | B87: 松岡 | C87: 松岡 | D87: E商談① | E87: クリニック | F87: 46174 | G87: マイナビ | H87: あいレディースクリニック | I87: 坂口 | J87: 決済者 | K87: 200000 | L87: 30000 | M87: 272000 | O87: "E1結果： 内容： 懸念： 次回アクション： ーーーーーーーーーーーーーーーーーーーーーーーーーーーーーーーー 2回目結果:： 内容： 懸念： 次回アクション： ーーーーーーーーーーーーーーーーーーーーーーーーーーーーーーーー 受注後 初期費用の決済： 月額費用の決済：" | P87: 46191 | Q87: 46191 | R87: 46198 | S87: FALSE | T87: FALSE
A88: FALSE | B88: 高原 | C88: 松岡 | D88: E商談① | E88: クリニック | F88: 46174 | G88: マイナビ | H88: みちかぜクリニック | I88: 舟橋 | J88: 決済者 | K88: 200000 | L88: 30000 | M88: 272000 | O88: "E1結果： 内容： 懸念： 次回アクション： ーーーーーーーーーーーーーーーーーーーーーーーーーーーーーーーー 2回目結果:： 内容： 懸念： 次回アクション： ーーーーーーーーーーーーーーーーーーーーーーーーーーーーーーーー 受注後 初期費用の決済： 月額費用の決済：" | P88: 46192 | Q88: 46192 | R88: 46198 | S88: FALSE | T88: FALSE
B89: 高原 | C89: 松岡 | D89: E商談① | E89: クリニック | F89: 46174 | G89: マイナビ | H89: 瓦谷クリニック | I89: 瓦谷 | J89: 決済者 | K89: 200000 | L89: 30000 | M89: 272000 | O89: E1結果： 内容： 懸念： 次回アクション： ーーーーーーーーーーーーーーーーーーーーーーーーーーーーーーーー 2回目結果:： 内容： 懸念： 次回アクション： ーーーーーーーーーーーーーーーーーーーーーーーーーーーーーーーー 受注後 初期費用の決済： 月額費用の決済： | P89: 46184 | Q89: 46184 | R89: 46191 | V89: =Q89-P89 -> 0 | W89: =R89-Q89 -> 7 | X89: =U89-R89 -> -46191
B90: 高原 | C90: 松岡 | D90: E商談① | E90: クリニック | F90: 46174 | G90: マイナビ | H90: 小林整形外科クリニック | I90: 小林 | J90: 決済者 | K90: 200000 | L90: 30000 | M90: 272000 | O90: E1結果： 内容： 懸念： 次回アクション： ーーーーーーーーーーーーーーーーーーーーーーーーーーーーーーーー 2回目結果:： 内容： 懸念： 次回アクション： ーーーーーーーーーーーーーーーーーーーーーーーーーーーーーーーー 受注後 初期費用の決済： 月額費用の決済： | P90: 46190 | Q90: 46190 | R90: 46192 | V90: =Q90-P90 -> 0 | W90: =R90-Q90 -> 2 | X90: =U90-R90 -> -46192
B91: 高原 | C91: 松岡 | D91: E商談① | E91: クリニック | F91: 46174 | G91: マイナビ | H91: ヒルサイドクリニック | I91: 山脇 | J91: 決済者 | K91: 200000 | L91: 30000 | M91: 272000 | O91: E1結果： 内容： 懸念： 次回アクション： ーーーーーーーーーーーーーーーーーーーーーーーーーーーーーーーー 2回目結果:： 内容： 懸念： 次回アクション： ーーーーーーーーーーーーーーーーーーーーーーーーーーーーーーーー 受注後 初期費用の決済： 月額費用の決済： | P91: 46190 | Q91: 46190 | R91: 46192 | V91: =Q91-P91 -> 0 | W91: =R91-Q91 -> 2 | X91: =U91-R91 -> -46192
B92: 高原 | C92: 松岡 | D92: F日程変更中 | E92: クリニック | F92: 46174 | G92: マイナビ | H92: 祐天寺たぐち眼科 | I92: 田口 | J92: 決済者 | K92: 200000 | L92: 30000 | M92: 272000 | N92: 46191 | O92: 返信なければtel | P92: 46184 | Q92: 46184 | R92: 46188 | V92: =Q92-P92 -> 0 | W92: =R92-Q92 -> 4 | X92: =U92-R92 -> -46188
A93: TRUE | B93: 高原 | C93: 松岡 | D93: XAプレゼン失注(決裁者) | E93: クリニック | F93: 46143 | G93: マイナビ | H93: みなみ消化器内科・内視鏡クリニック | I93: 李 | J93: 決済者 | K93: 200000 | L93: 30000 | M93: 272000 | N93: 46163 | O93: E1結果：次回E2 内容：開業1年で患者は順調に増えているが、内視鏡はまだ増やしたい意向あり。 リスティングがメインの対策で、医院に来てから患者満足度やリピートの為のLINEは導入済み。 認知からの比較検討段階層への対策としてマイナビ提案。 次回マイナビの数値面と料金提示。 懸念：効果に対して 次回アクション：次回商談にてマイナビ掲載による効果の定量を提示、費用対効果の明確化。 ーーーーーーーーーーーーーーーーーーーーーーーーーーーーーーーー 2回目結果:： 内容： 懸念： 次回アクション： ーーーーーーーーーーーーーーーーーーーーーーーーーーーーーーーー 受注後 初期費用の決済： 月額費用の決済： | P93: 46118 | Q93: 46118 | R93: 46156 | S93: TRUE | T93: FALSE | U93: 46163 | V93: =Q93-P93 -> 0 | W93: =R93-Q93 -> 38 | X93: =U93-R93 -> 7 | Z93: =Y93-Q93 -> -46118 | AA93: =Y93-R93 -> -46156 | AC93: =AB93-Q93 -> -46118
A94: TRUE | B94: 松岡 | C94: 松岡 | D94: XAプレゼン失注(決裁者) | E94: クリニック | F94: 46143 | G94: MEO | H94: 前田医院 | I94: 前田 | J94: 決済者 | K94: 100000 | L94: 45000 | M94: 320000 | N94: 46147 | O94: 地域一番になりたいと。次回院長と副院長同席で提案。→ 単価と先方要望の高さからMEO提案に切り替え、 2026/04/23 キャンセルの連絡あり、マイナビの直販のアプローチあり。 ネクストメールを送ってる。 本来で携帯に電話できるのが理想な状態。 →マイナビ側で先方がお申込みしたことにより、アポキャンセル。 マイナビ側に問い合わせし、対応について回答待ち。 MEOの話に切り替えて5月5日に再度提案。 | P94: 46106 | Q94: 46106 | R94: 46115 | S94: TRUE | T94: FALSE | U94: 46122 | V94: =Q94-P94 -> 0 | W94: =R94-Q94 -> 9 | X94: =U94-R94 -> 7 | Z94: =Y94-Q94 -> -46106 | AA94: =Y94-R94 -> -46115 | AC94: =AB94-Q94 -> -46106
A95: TRUE | B95: 高原 | C95: 松岡 | D95: XAプレゼン失注(決裁者) | E95: クリニック | F95: 46174 | G95: マイナビ | H95: あさもとクリニック産婦人科 | I95: 朝元 | J95: 決済者 | K95: 200000 | L95: 30000 | M95: 272000 | O95: E1結果： 内容： 懸念： 次回アクション： ーーーーーーーーーーーーーーーーーーーーーーーーーーーーーーーー 2回目結果:： 内容： 懸念： 次回アクション： ーーーーーーーーーーーーーーーーーーーーーーーーーーーーーーーー 受注後 初期費用の決済： 月額費用の決済： | P95: 46181 | Q95: 46181 | R95: 46190 | V95: =Q95-P95 -> 0 | W95: =R95-Q95 -> 9 | X95: =U95-R95 -> -46190
A96: TRUE | B96: 松岡 | C96: 松岡 | D96: XAプレゼン失注(決裁者) | E96: クリニック | F96: 46174 | G96: マイナビ | H96: 横浜わたなべ内科・ 内視鏡クリニック 根岸院 | I96: 渡邉 | J96: 決済者 | K96: 200000 | L96: 30000 | M96: 272000 | O96: E1結果： 内容： 懸念： 次回アクション： ーーーーーーーーーーーーーーーーーーーーーーーーーーーーーーーー 2回目結果:： 内容： 懸念： 次回アクション： ーーーーーーーーーーーーーーーーーーーーーーーーーーーーーーーー 受注後 初期費用の決済： 月額費用の決済： | P96: 46181 | Q96: 46183 | R96: 46188
A97: FALSE | B97: 松岡 | C97: 松岡 | D97: E商談① | E97: クリニック | F97: 46204 | G97: マイナビ | H97: 田中消化器科クリニック | I97: 田中 | J97: 決済者 | K97: 200000 | L97: 30000 | M97: 272000 | O97: E1結果： 内容： 懸念： 次回アクション： ーーーーーーーーーーーーーーーーーーーーーーーーーーーーーーーー 2回目結果:： 内容： 懸念： 次回アクション： ーーーーーーーーーーーーーーーーーーーーーーーーーーーーーーーー 受注後 初期費用の決済： 月額費用の決済： | P97: 46178 | Q97: 46174 | R97: 46210 | S97: FALSE | T97: FALSE
A98: TRUE | B98: 松岡 | C98: 松岡 | D98: E商談① | E98: クリニック | F98: 45809 | G98: マイナビ | H98: あい内視鏡クリニック | I98: 平井 | J98: 決済者 | K98: 200000 | L98: 30000 | M98: 272000 | O98: E1結果： 内容： 懸念： 次回アクション： ーーーーーーーーーーーーーーーーーーーーーーーーーーーーーーーー 2回目結果:： 内容： 懸念： 次回アクション： ーーーーーーーーーーーーーーーーーーーーーーーーーーーーーーーー 受注後 初期費用の決済： 月額費用の決済： | P98: 46177 | Q98: 46177 | R98: 46177 | S98: FALSE | T98: FALSE
A99: FALSE | B99: 高原 | C99: 松岡 | D99: F日程変更中 | E99: クリニック | F99: 45778 | G99: MEO | H99: 富士森内科クリニック | I99: 田中 | J99: 決済者 | K99: 100000 | L99: 45000 | M99: 320000 | N99: 46153 | O99: マイナビ→MEO提案。 MEOについては過去対策したとのことだが、提案し実際にやったことがある領域と初めて聞いた領域を確認し提案を進める。 メール届きましたか、の連絡でちなみに先生が以前やっていたＭＥＯサービス→16日先生に連絡。→ 電話にて診療が続いていたことと、 いま5年に一度の税務所がはいっていて忙しすぎるから次回アポで話してと、来週も連絡はあんまりせんでとのことで30日お願いしますで終話。→ 17日過去のMEOサービスを把握するためのメール内容考えてお送り。 →メールにてリスケ連絡、29日に候補日メール済み、30日に連絡ない場合催促の電話 | P99: 46118 | Q99: 46119 | R99: 46122 | S99: FALSE | T99: FALSE | V99: =Q99-P99 -> 1 | W99: =R99-Q99 -> 3 | X99: =U99-R99 -> -46122
A100: FALSE | B100: 高原 | C100: 松岡 | D100: F日程変更中 | E100: クリニック | F100: 45778 | G100: マイナビ | H100: まつだクリニック | I100: 松田 | J100: 決済者 | K100: 200000 | L100: 30000 | M100: 272000 | N100: 46139 | O100: メール返信なければTEL日程調整 | P100: 46133 | Q100: 46133 | R100: 46136 | S100: FALSE | T100: FALSE | V100: =Q100-P100 -> 0 | W100: =R100-Q100 -> 3 | X100: =U100-R100 -> -46136
A101: FALSE | B101: 高原 | C101: 松岡 | D101: F日程変更中 | E101: クリニック | F101: 46204 | G101: マイナビ | H101: いわや内科・内視鏡クリニック | I101: 岩屋 | J101: 決済者 | K101: 200000 | L101: 30000 | M101: 272000 | N101: 46204 | O101: 嫁。学会発表とかでも忙しく、7月にしてくれ伝言 | P101: 46129 | Q101: 46139 | R101: 46160 | S101: FALSE | T101: FALSE | V101: =Q101-P101 -> 10 | W101: =R101-Q101 -> 21 | X101: =U101-R101 -> -46160
A102: FALSE | B102: 高原 | C102: 松岡 | D102: F日程変更中 | E102: クリニック | F102: 46204 | G102: マイナビ | H102: ふじもり内科・消化器内科クリニック | I102: 藤森 | J102: 決済者 | K102: 200000 | L102: 30000 | M102: 272000 | N102: 46204 | O102: 六月からの法人化で今忙しいメール | P102: 46136 | Q102: 46136 | R102: 46155 | S102: FALSE | T102: FALSE | V102: =Q102-P102 -> 0 | W102: =R102-Q102 -> 19 | X102: =U102-R102 -> -46155
...

Sheet 【2026年5月】月間進捗管理シート（第一） 
A1: 全体 | B1: 計画値 | D1: 現状 | E1: 金 | H1: 木 | I1: 金 | J1: 土 | K1: 日 | L1: 月 | M1: 火 | N1: 水 | O1: 木 | P1: 金 | Q1: 土 | R1: 日 | S1: 月 | T1: 火 | U1: 水 | V1: 木 | W1: 金 | X1: 土 | Y1: 日 | Z1: 月 | AA1: 火 | AB1: 水 | AC1: 木 | AD1: 金 | AE1: 土 | AF1: 日
E2: 46143 | H2: 46149 | I2: 46150 | J2: 46151 | K2: 46152 | L2: 46153 | M2: 46154 | N2: 46155 | O2: 46156 | P2: 46157 | Q2: 46158 | R2: 46159 | S2: 46160 | T2: 46161 | U2: 46162 | V2: 46163 | W2: 46164 | X2: 46165 | Y2: 46166 | Z2: 46167 | AA2: 46168 | AB2: 46169 | AC2: 46170 | AD2: 46171 | AE2: 46172 | AF2: 46173
A3: 受注率 | C3: 売上 | D3: =sum(E3:J3)+sum(L3:Q3)+sum(S3:X3)+sum(Z3:AE3)+SUM(AG3:AJ3) -> 2672000 | E3: =E16+E29+E42+E55 -> 0 | F3: =F16+F29+F42+F55 -> 0 | G3: =G16+G29+G42+G55 -> 0 | H3: =H16+H29+H42+H55 -> 0 | I3: =I16+I29+I42+I55 -> 0 | J3: =J16+J29+J42+J55 -> 0 | K3: =sum(E3:J3) -> 0 | L3: =L16+L29+L42 -> 0 | M3: =M16+M29+M42 -> 0 | N3: =N16+N29+N42 -> 0 | O3: =O16+O29+O42 -> 0 | P3: =P16+P29+P42 -> 0 | Q3: =Q16+Q29+Q42 -> 0 | R3: =sum(L3:Q3) -> 0 | S3: =S16+S29+S42+S55 -> 0 | T3: =T16+T29+T42+T55 -> 0 | U3: =U16+U29+U42+U55 -> 712000 | V3: =V16+V29+V42+V55 -> 0 | W3: =W16+W29+W42+W55 -> 592000 | X3: =X16+X29+X42+X55 -> 0 | Y3: =sum(S3:X3) -> 1304000 | Z3: =Z16+Z29+Z42 -> 72000 | AA3: =AA16+AA29+AA42 -> 0 | AB3: =AB16+AB29+AB42 -> 352000 | AC3: =AC16+AC29+AC42 -> 0 | AD3: =AD16+AD29+AD42 -> 352000 | AE3: =AE16+AE29+AE42 -> 592000 | AF3: =sum(Z3:AE3) -> 1368000 | AG3: =AG16+AG29+AG42 -> 0 | AH3: =AH16+AH29+AH42 -> 0 | AI3: =AI16+AI29+AI42 -> 0 | AJ3: =AJ16+AJ29+AJ42 -> 0 | AK3: =AK16+AK29+AK42 -> 0 | AL3: =AL16+AL29+AL42 -> 0 | AM3: =sum(AG3:AL3) -> 0
A4: =D4/D5 -> 0.29166667 | C4: 受注数 | D4: =sum(E4:J4)+sum(L4:Q4)+sum(S4:X4)+sum(Z4:AE4)+sum(AG4:AJ4) -> 7 | E4: =E17+E30+E43+E56 -> 0 | F4: =F17+F30+F43+F56 -> 0 | G4: =G17+G30+G43+G56 -> 0 | H4: =H17+H30+H43+H56 -> 0 | I4: =I17+I30+I43+I56 -> 0 | J4: =J17+J30+J43+J56 -> 0 | K4: =sum(E4:J4) -> 0 | L4: =L17+L30+L43+L56 -> 0 | M4: =M17+M30+M43+M56 -> 0 | N4: =N17+N30+N43+N56 -> 0 | O4: =O17+O30+O43+O56 -> 0 | P4: =P17+P30+P43+P56 -> 0 | Q4: =Q17+Q30+Q43+Q56 -> 0 | R4: =sum(L4:Q4) -> 0 | S4: =S17+S30+S43+S56 -> 0 | T4: =T17+T30+T43+T56 -> 0 | U4: =U17+U30+U43+U56 -> 1 | V4: =V17+V30+V43+V56 -> 0 | W4: =W17+W30+W43+W56 -> 1 | X4: =X17+X30+X43+X56 -> 0 | Y4: =sum(S4:X4) -> 2 | Z4: =Z17+Z30+Z43 -> 1 | AA4: =AA17+AA30+AA43 -> 0 | AB4: =AB17+AB30+AB43 -> 1 | AC4: =AC17+AC30+AC43 -> 0 | AD4: =AD17+AD30+AD43 -> 1 | AE4: =AE17+AE30+AE43 -> 2 | AF4: =sum(Z4:AE4) -> 5 | AG4: =AG17+AG30+AG43 -> 0 | AH4: =AH17+AH30+AH43 -> 0 | AI4: =AI17+AI30+AI43 -> 0 | AJ4: =AJ17+AJ30+AJ43 -> 0 | AK4: =AK17+AK30+AK43 -> 0 | AL4: =AL17+AL30+AL43 -> 0 | AM4: =sum(AG4:AL4) -> 0
A5: 有効商談率 | C5: 有効商談数 | D5: =sum(E5:J5)+sum(L5:Q5)+sum(S5:X5)+sum(Z5:AE5)+sum(AG5:AH5) -> 24 | E5: =E18+E31+E44+E57 -> 1 | F5: =F18+F31+F44+F57 -> 0 | G5: =G18+G31+G44+G57 -> 0 | H5: =H18+H31+H44+H57 -> 0 | I5: =I18+I31+I44+I57 -> 3 | J5: =J18+J31+J44+J57 -> 0 | K5: =sum(E5:J5) -> 4 | L5: =L18+L31+L44+L57 -> 1 | M5: =M18+M31+M44+M57 -> 1 | N5: =N18+N31+N44+N57 -> 0 | O5: =O18+O31+O44+O57 -> 5 | P5: =P18+P31+P44+P57 -> 2 | Q5: =Q18+Q31+Q44+Q57 -> 0 | R5: =sum(L5:Q5) -> 9 | S5: =S18+S31+S44+S57 -> 0 | T5: =T18+T31+T44+T57 -> 1 | U5: =U18+U31+U44+U57 -> 1 | V5: =V18+V31+V44+V57 -> 0 | W5: =W18+W31+W44+W57 -> 1 | X5: =X18+X31+X44+X57 -> 0 | Y5: =sum(S5:X5) -> 3 | Z5: =Z18+Z31+Z44 -> 4 | AA5: =AA18+AA31+AA44 -> 1 | AB5: =AB18+AB31+AB44 -> 1 | AC5: =AC18+AC31+AC44 -> 1 | AD5: =AD18+AD31+AD44 -> 1 | AE5: =AE18+AE31+AE44 -> 0 | AF5: =sum(Z5:AE5) -> 8 | AG5: =AG18+AG31+AG44 -> 0 | AH5: =AH18+AH31+AH44 -> 0 | AI5: =AI18+AI31+AI44 -> 0 | AJ5: =AJ18+AJ31+AJ44 -> 0 | AK5: =AK18+AK31+AK44 -> 0 | AL5: =AL18+AL31+AL44 -> 0 | AM5: =sum(AG5:AL5) -> 0
A6: =D5/sum(D5:D6) -> 0.64864865 | C6: 無効商談数 | D6: =sum(E6:J6)+sum(L6:Q6)+sum(S6:X6)+sum(Z6:AE6)+sum(AG6:AH6) -> 13 | E6: =E19+E32+E45+E58 -> 2 | F6: =F19+F32+F45+F58 -> 0 | G6: =G19+G32+G45+G58 -> 0 | H6: =H19+H32+H45+H58 -> 0 | I6: =I19+I32+I45+I58 -> 0 | J6: =J19+J32+J45+J58 -> 0 | K6: =sum(E6:J6) -> 2 | L6: =L19+L32+L45+L58 -> 0 | M6: =M19+M32+M45+M58 -> 1 | N6: =N19+N32+N45+N58 -> 2 | O6: =O19+O32+O45+O58 -> 1 | P6: =P19+P32+P45+P58 -> 1 | Q6: =Q19+Q32+Q45+Q58 -> 0 | R6: =sum(L6:Q6) -> 5 | S6: =S19+S32+S45+S58 -> 0 | T6: =T19+T32+T45+T58 -> 0 | U6: =U19+U32+U45+U58 -> 2 | V6: =V19+V32+V45+V58 -> 0 | W6: =W19+W32+W45+W58 -> 1 | X6: =X19+X32+X45+X58 -> 0 | Y6: =sum(S6:X6) -> 3 | Z6: =Z19+Z32+Z45 -> 0 | AA6: =AA19+AA32+AA45 -> 1 | AB6: =AB19+AB32+AB45 -> 0 | AC6: =AC19+AC32+AC45 -> 1 | AD6: =AD19+AD32+AD45 -> 1 | AE6: =AE19+AE32+AE45 -> 0 | AF6: =sum(Z6:AE6) -> 3 | AG6: =AG19+AG32+AG45 -> 0 | AH6: =AH19+AH32+AH45 -> 0 | AI6: =AI19+AI32+AI45 -> 0 | AJ6: =AJ19+AJ32+AJ45 -> 0 | AK6: =AK19+AK32+AK45 -> 0 | AL6: =AL19+AL32+AL45 -> 0 | AM6: =sum(AG6:AL6) -> 0
A7: 出席率 | C7: 商談設定数 | D7: =sum(E7:J7)+sum(L7:Q7)+sum(S7:X7)+sum(Z7:AE7)+sum(AG7:AH7) -> 50 | E7: =E20+E33+E46+E59 -> 3 | F7: =F20+F33+F46+F59 -> 0 | G7: =G20+G33+G46+G59 -> 0 | H7: =H20+H33+H46+H59 -> 0 | I7: =I20+I33+I46+I59 -> 3 | J7: =J20+J33+J46+J59 -> 0 | K7: =sum(E7:J7) -> 6 | L7: =L20+L33+L46+L59 -> 1 | M7: =M20+M33+M46+M59 -> 4 | N7: =N20+N33+N46+N59 -> 4 | O7: =O20+O33+O46+O59 -> 7 | P7: =P20+P33+P46+P59 -> 4 | Q7: =Q20+Q33+Q46+Q59 -> 0 | R7: =sum(L7:Q7) -> 20 | S7: =S20+S33+S46+S59 -> 1 | T7: =T20+T33+T46+T59 -> 1 | U7: =U20+U33+U46+U59 -> 4 | V7: =V20+V33+V46+V59 -> 2 | W7: =W20+W33+W46+W59 -> 4 | X7: =X20+X33+X46+X59 -> 0 | Y7: =sum(S7:X7) -> 12 | Z7: =Z20+Z33+Z46 -> 4 | AA7: =AA20+AA33+AA46 -> 3 | AB7: =AB20+AB33+AB46 -> 1 | AC7: =AC20+AC33+AC46 -> 2 | AD7: =AD20+AD33+AD46 -> 2 | AE7: =AE20+AE33+AE46 -> 0 | AF7: =sum(Z7:AE7) -> 12 | AG7: =AG20+AG33+AG46 -> 0 | AH7: =AH20+AH33+AH46 -> 0 | AI7: =AI20+AI33+AI46 -> 0 | AJ7: =AJ20+AJ33+AJ46 -> 0 | AK7: =AK20+AK33+AK46 -> 0 | AL7: =AL20+AL33+AL46 -> 0 | AM7: =sum(AG7:AL7) -> 0
A8: =(D5+D6)/D7 -> 0.74 | C8: アポ数 | D8: =sum(E8:J8)+sum(L8:Q8)+sum(S8:X8)+sum(Z8:AE8)+sum(AG8:AH8) -> 43 | E8: =E21+E34+E47+E60 -> 0 | F8: =F21+F34+F47+F60 -> 0 | G8: =G21+G34+G47+G60 -> 0 | H8: =H21+H34+H47+H60 -> 6 | I8: =I21+I34+I47+I60 -> 2 | J8: =J21+J34+J47+J60 -> 0 | K8: =sum(E8:J8) -> 8 | L8: =L21+L34+L47+L60 -> 3 | M8: =M21+M34+M47+M60 -> 4 | N8: =N21+N34+N47+N60 -> 4 | O8: =O21+O34+O47+O60 -> 2 | P8: =P21+P34+P47+P60 -> 6 | Q8: =Q21+Q34+Q47+Q60 -> 0 | R8: =sum(L8:Q8) -> 19 | S8: =S21+S34+S47+S60 -> 1 | T8: =T21+T34+T47+T60 -> 5 | U8: =U21+U34+U47+U60 -> 4 | V8: =V21+V34+V47+V60 -> 2 | W8: =W21+W34+W47+W60 -> 2 | X8: =X21+X34+X47+X60 -> 0 | Y8: =sum(S8:X8) -> 14 | Z8: =Z21+Z34+Z47 -> 0 | AA8: =AA21+AA34+AA47 -> 2 | AB8: =AB21+AB34+AB47 -> 0 | AC8: =AC21+AC34+AC47 -> 0 | AD8: =AD21+AD34+AD47 -> 0 | AE8: =AE21+AE34+AE47 -> 0 | AF8: =sum(Z8:AE8) -> 2 | AG8: =AG21+AG34+AG47 -> 0 | AH8: =AH21+AH34+AH47 -> 0 | AI8: =AI21+AI34+AI47 -> 0 | AJ8: =AJ21+AJ34+AJ47 -> 0 | AK8: =AK21+AK34+AK47 -> 0 | AL8: =AL21+AL34+AL47 -> 0 | AM8: =sum(AG8:AL8) -> 0
A9: アポ率 | B9: =D8/D12 -> 0.012420566 | C9: フル数 | D9: =sum(E9:J9)+sum(L9:Q9)+sum(S9:X9)+sum(Z9:AE9)+sum(AG9:AH9) -> 70 | E9: =E22+E35+E48+E61 -> 0 | F9: =F22+F35+F48+F61 -> 0 | G9: =G22+G35+G48+G61 -> 0 | H9: =H22+H35+H48+H61 -> 5 | I9: =I22+I35+I48+I61 -> 7 | J9: =J22+J35+J48+J61 -> 0 | K9: =sum(E9:J9) -> 12 | L9: =L22+L35+L48+L61 -> 3 | M9: =M22+M35+M48+M61 -> 6 | N9: =N22+N35+N48+N61 -> 6 | O9: =O22+O35+O48+O61 -> 6 | P9: =P22+P35+P48+P61 -> 7 | Q9: =Q22+Q35+Q48+Q61 -> 0 | R9: =sum(L9:Q9) -> 28 | S9: =S22+S35+S48+S61 -> 3 | T9: =T22+T35+T48+T61 -> 11 | U9: =U22+U35+U48+U61 -> 8 | V9: =V22+V35+V48+V61 -> 2 | W9: =W22+W35+W48+W61 -> 4 | X9: =X22+X35+X48+X61 -> 0 | Y9: =sum(S9:X9) -> 28 | Z9: =Z22+Z35+Z48 -> 0 | AA9: =AA22+AA35+AA48 -> 2 | AB9: =AB22+AB35+AB48 -> 0 | AC9: =AC22+AC35+AC48 -> 0 | AD9: =AD22+AD35+AD48 -> 0 | AE9: =AE22+AE35+AE48 -> 0 | AF9: =sum(Z9:AE9) -> 2 | AG9: =AG22+AG35+AG48 -> 0 | AH9: =AH22+AH35+AH48 -> 0 | AI9: =AI22+AI35+AI48 -> 0 | AJ9: =AJ22+AJ35+AJ48 -> 0 | AK9: =AK22+AK35+AK48 -> 0 | AL9: =AL22+AL35+AL48 -> 0 | AM9: =sum(AG9:AL9) -> 0
A10: フル→アポ | B10: =D8/D9 -> 0.61428571 | C10: オーナー数 | D10: =sum(E10:J10)+sum(L10:Q10)+sum(S10:X10)+sum(Z10:AE10)+sum(AG10:AH10) -> 127 | E10: =E23+E36+E49+E62 -> 0 | F10: =F23+F36+F49+F62 -> 0 | G10: =G23+G36+G49+G62 -> 0 | H10: =H23+H36+H49+H62 -> 9 | I10: =I23+I36+I49+I62 -> 11 | J10: =J23+J36+J49+J62 -> 0 | K10: =sum(E10:J10) -> 20 | L10: =L23+L36+L49+L62 -> 5 | M10: =M23+M36+M49+M62 -> 11 | N10: =N23+N36+N49+N62 -> 10 | O10: =O23+O36+O49+O62 -> 12 | P10: =P23+P36+P49+P62 -> 12 | Q10: =Q23+Q36+Q49+Q62 -> 0 | R10: =sum(L10:Q10) -> 50 | S10: =S23+S36+S49+S62 -> 16 | T10: =T23+T36+T49+T62 -> 15 | U10: =U23+U36+U49+U62 -> 12 | V10: =V23+V36+V49+V62 -> 2 | W10: =W23+W36+W49+W62 -> 8 | X10: =X23+X36+X49+X62 -> 0 | Y10: =sum(S10:X10) -> 53 | Z10: =Z23+Z36+Z49 -> 0 | AA10: =AA23+AA36+AA49 -> 4 | AB10: =AB23+AB36+AB49 -> 0 | AC10: =AC23+AC36+AC49 -> 0 | AD10: =AD23+AD36+AD49 -> 0 | AE10: =AE23+AE36+AE49 -> 0 | AF10: =sum(Z10:AE10) -> 4 | AG10: =AG23+AG36+AG49 -> 0 | AH10: =AH23+AH36+AH49 -> 0 | AI10: =AI23+AI36+AI49 -> 0 | AJ10: =AJ23+AJ36+AJ49 -> 0 | AK10: =AK23+AK36+AK49 -> 0 | AL10: =AL23+AL36+AL49 -> 0 | AM10: =sum(AG10:AL10) -> 0
A11: オーナー→フル | B11: =D9/D10 -> 0.5511811 | C11: 接続 | D11: =sum(E11:J11)+sum(L11:Q11)+sum(S11:X11)+sum(Z11:AE11)+sum(AG11:AH11) -> 1863 | E11: =E24+E37+E50+E63 -> 0 | F11: =F24+F37+F50+F63 -> 0 | G11: =G24+G37+G50+G63 -> 0 | H11: =H24+H37+H50+H63 -> 110 | I11: =I24+I37+I50+I63 -> 70 | J11: =J24+J37+J50+J63 -> 0 | K11: =sum(E11:J11) -> 180 | L11: =L24+L37+L50+L63 -> 102 | M11: =M24+M37+M50+M63 -> 255 | N11: =N24+N37+N50+N63 -> 207 | O11: =O24+O37+O50+O63 -> 183 | P11: =P24+P37+P50+P63 -> 287 | Q11: =Q24+Q37+Q50+Q63 -> 0 | R11: =sum(L11:Q11) -> 1034 | S11: =S24+S37+S50+S63 -> 152 | T11: =T24+T37+T50+T63 -> 175 | U11: =U24+U37+U50+U63 -> 157 | V11: =V24+V37+V50+V63 -> 27 | W11: =W24+W37+W50+W63 -> 51 | X11: =X24+X37+X50+X63 -> 0 | Y11: =sum(S11:X11) -> 562 | Z11: =Z24+Z37+Z50 -> 25 | AA11: =AA24+AA37+AA50 -> 22 | AB11: =AB24+AB37+AB50 -> 40 | AC11: =AC24+AC37+AC50 -> 0 | AD11: =AD24+AD37+AD50 -> 0 | AE11: =AE24+AE37+AE50 -> 0 | AF11: =sum(Z11:AE11) -> 87 | AG11: =AG24+AG37+AG50 -> 0 | AH11: =AH24+AH37+AH50 -> 0 | AI11: =AI24+AI37+AI50 -> 0 | AJ11: =AJ24+AJ37+AJ50 -> 0 | AK11: =AK24+AK37+AK50 -> 0 | AL11: =AL24+AL37+AL50 -> 0 | AM11: =sum(AG11:AL11) -> 0
A12: 接続→オーナー数 | B12: =D10/D11 -> 0.068169619 | C12: 架電数 | D12: =sum(E12:J12)+sum(L12:Q12)+sum(S12:X12)+sum(Z12:AE12)+sum(AG12:AH12) -> 3462 | E12: =E25+E38+E51+E64 -> 0 | F12: =F25+F38+F51+F64 -> 0 | G12: =G25+G38+G51+G64 -> 0 | H12: =H25+H38+H51+H64 -> 283 | I12: =I25+I38+I51+I64 -> 176 | J12: =J25+J38+J51+J64 -> 0 | K12: =sum(E12:J12) -> 459 | L12: =L25+L38+L51+L64 -> 165 | M12: =M25+M38+M51+M64 -> 403 | N12: =N25+N38+N51+N64 -> 467 | O12: =O25+O38+O51+O64 -> 420 | P12: =P25+P38+P51+P64 -> 408 | Q12: =Q25+Q38+Q51+Q64 -> 0 | R12: =sum(L12:Q12) -> 1863 | S12: =S25+S38+S51+S64 -> 366 | T12: =T25+T38+T51+T64 -> 250 | U12: =U25+U38+U51+U64 -> 232 | V12: =V25+V38+V51+V64 -> 71 | W12: =W25+W38+W51+W64 -> 101 | X12: =X25+X38+X51+X64 -> 0 | Y12: =sum(S12:X12) -> 1020 | Z12: =Z25+Z38+Z51 -> 35 | AA12: =AA25+AA38+AA51 -> 30 | AB12: =AB25+AB38+AB51 -> 55 | AC12: =AC25+AC38+AC51 -> 0 | AD12: =AD25+AD38+AD51 -> 0 | AE12: =AE25+AE38+AE51 -> 0 | AF12: =sum(Z12:AE12) -> 120 | AG12: =AG25+AG38+AG51 -> 0 | AH12: =AH25+AH38+AH51 -> 0 | AI12: =AI25+AI38+AI51 -> 0 | AJ12: =AJ25+AJ38+AJ51 -> 0 | AK12: =AK25+AK38+AK51 -> 0 | AL12: =AL25+AL38+AL51 -> 0 | AM12: =sum(AG12:AL12) -> 0
A13: 架電→接続 | B13: =D11/D12 -> 0.53812825
A16: 縞谷 | C16: 売上 | D16: =sum(E16:J16)+sum(L16:Q16)+sum(S16:X16)+sum(Z16:AE16)+SUM(AG16:AH16) -> 0 | K16: =sum(E16:J16) -> 0 | R16: =sum(L16:Q16) -> 0 | Y16: =sum(S16:X16) -> 0 | AF16: =sum(Z16:AE16) -> 0 | AM16: =sum(AG16:AL16) -> 0
A17: 受注率 | C17: 受注数 | D17: =sum(E17:J17)+sum(L17:Q17)+sum(S17:X17)+sum(Z17:AE17)+sum(AG17:AH17) -> 0 | K17: =sum(E17:J17) -> 0 | R17: =sum(L17:Q17) -> 0 | Y17: =sum(S17:X17) -> 0 | AF17: =sum(Z17:AE17) -> 0 | AM17: =sum(AG17:AL17) -> 0
A18: =D17/D18 -> #DIV/0! | C18: 有効商談数 | D18: =sum(E18:J18)+sum(L18:Q18)+sum(S18:X18)+sum(Z18:AE18)+sum(AG18:AH18) -> 0 | K18: =sum(E18:J18) -> 0 | R18: =sum(L18:Q18) -> 0 | Y18: =sum(S18:X18) -> 0 | AF18: =sum(Z18:AE18) -> 0 | AM18: =sum(AG18:AL18) -> 0
A19: 有効商談率 | C19: 無効商談数 | D19: =sum(E19:J19)+sum(L19:Q19)+sum(S19:X19)+sum(Z19:AE19)+sum(AG19:AH19) -> 0 | K19: =sum(E19:J19) -> 0 | R19: =sum(L19:Q19) -> 0 | Y19: =sum(S19:X19) -> 0 | AF19: =sum(Z19:AE19) -> 0 | AM19: =sum(AG19:AL19) -> 0
